Workbook

Sheet Invoices
B2: Total | H2: =SUM(H5:H2997) -> 1865516.3 | I2: =SUM(I5:I2997) -> 1804280.6 | J2: =SUM(J5:J2997) -> 12996.923 | K2: =SUM(K5:K2997) -> 1817277.5 | L2: =SUM(L5:L2997) -> 272620.7 | M2: =SUM(M5:M2997) -> 2089898.2
B4: ID | C4: Invoice Date | D4: EOMONTH | E4: Invoice ID | F4: Contractor | G4: Description | H4: Contract Amt. (NET + CNPAIA) (€) | I4: NET (€) | J4: CNPAIA (€) | K4: Invoiced Amt. (NET + CNPAIA) (€) | L4: VAT Invoiced | M4: Gross Invoiced Amt. (€) | N4: Contract Approved? | O4: Invoice Received? | P4: Invoice Approved | Q4: Approved by (UHG/Michiel) | R4: Paid?
B5: 1 | C5: 45716 | D5: =EOMONTH(C5,0) -> 45716 | E5: 2003066 | F5: Stylt | G5: The Usual Hotel Corona Competition+ Travel costs | H5: 4000 | I5: 4000 | J5: 0 | K5: =SUM(I5,J5) -> 4000 | L5: 0 | M5: =SUM(K5,L5) -> 4000 | N5: 1 | O5: 1 | P5: 1 | Q5: 1 | R5: 1 | T5: =K5-'[1]Contracts & Invoices'!R12 -> 0
B6: 2 | C6: 45729 | D6: =EOMONTH(C6,0) -> 45747 | E6: 2025/072 | F6: Joi-Design | G6: Interior design planning services | H6: 2500 | I6: 2500 | J6: 0 | K6: =SUM(I6,J6) -> 2500 | L6: 0 | M6: =SUM(K6,L6) -> 2500 | N6: 1 | O6: 1 | P6: 1 | Q6: 1 | R6: 1 | T6: =K6-'[1]Contracts & Invoices'!R13 -> 0
B7: 3 | C7: 45745 | D7: =EOMONTH(C7,0) -> 45747 | E7: n.9/001 | F7: Rizoma | G7: Renovation of Hotel Corona-Interior Contest | H7: 2600 | I7: 2500 | J7: 100 | K7: =SUM(I7,J7) -> 2600 | L7: 572 | M7: =SUM(K7,L7) -> 3172 | N7: 1 | O7: 1 | P7: 1 | Q7: 1 | R7: 1 | T7: =K7-'[1]Contracts & Invoices'!R14 -> 0
B8: 4 | C8: 45807 | D8: =EOMONTH(C8,0) -> 45808 | E8: VMI25_00270 | F8: Artelia | G8: Project Management | H8: 29200 | I8: 29200 | J8: 0 | K8: =SUM(I8,J8) -> 29200 | L8: 6424 | M8: =SUM(K8,L8) -> 35624 | N8: 1 | O8: 1 | P8: 1 | Q8: 1 | R8: 1 | T8: =K8-'[1]Contracts & Invoices'!R15 -> 0
B9: 5 | C9: 45807 | D9: =EOMONTH(C9,0) -> 45808 | E9: VMI25_00270 | F9: Artelia | G9: Construction Management | H9: 8000 | I9: 8000 | J9: 0 | K9: =SUM(I9,J9) -> 8000 | L9: 1760 | M9: =SUM(K9,L9) -> 9760 | N9: 1 | O9: 1 | P9: 1 | Q9: 1 | R9: 1 | T9: =K9-'[1]Contracts & Invoices'!R16 -> 0
B10: 6 | C10: 45807 | D10: =EOMONTH(C10,0) -> 45808 | E10: VMI25_00270 | F10: Artelia | G10: Multidisciplinary Engineering Design | H10: 28080 | I10: 27000 | J10: 0 | K10: =SUM(I10,J10) -> 27000 | L10: 5940 | M10: =SUM(K10,L10) -> 32940 | N10: 1 | O10: 1 | P10: 1 | Q10: 1 | R10: 1 | T10: =K10-'[1]Contracts & Invoices'!R17 -> 0
B11: 7 | C11: 45821 | D11: =EOMONTH(C11,0) -> 45838 | E11: VMI25_00444 | F11: Artelia /Stylt | G11: Phase 1 - 4 | H11: 76240 | I11: 76240 | J11: 0 | K11: =SUM(I11,J11) -> 76240 | L11: 16772.8 | M11: =SUM(K11,L11) -> 93012.8 | N11: 1 | O11: 1 | P11: 1 | Q11: 1 | R11: 1 | T11: =K11-'[1]Contracts & Invoices'!R18 -> 0
B12: 8 | C12: 45838 | D12: =EOMONTH(C12,0) -> 45838 | E12: VMI25_00356 | F12: Artelia | G12: Project Management | H12: 11426.087 | I12: 11350.44 | J12: 0 | K12: =SUM(I12,J12) -> 11350.44 | L12: 2497.0968 | M12: =SUM(K12,L12) -> 13847.537 | N12: 1 | O12: 1 | P12: 1 | Q12: 1 | R12: 1 | T12: =K12-'[1]Contracts & Invoices'!R19 -> 0
B13: 9 | C13: 45838 | D13: =EOMONTH(C13,0) -> 45838 | E13: VMI25_00356 | F13: Artelia | G13: Construction Management | H13: 3130.4348 | I13: 3304.35 | J13: 0 | K13: =SUM(I13,J13) -> 3304.35 | L13: 726.957 | M13: =SUM(K13,L13) -> 4031.307 | N13: 1 | O13: 1 | P13: 1 | Q13: 1 | R13: 1 | T13: =K13-'[1]Contracts & Invoices'!R20 -> 0
B14: 10 | C14: 45838 | D14: =EOMONTH(C14,0) -> 45838 | E14: VMI25_00356 | F14: Artelia | G14: Multidisciplinary Engineering Design | H14: 84240 | I14: 76950 | J14: 3078 | K14: =SUM(I14,J14) -> 80028 | L14: 17606.16 | M14: =SUM(K14,L14) -> 97634.16 | N14: 1 | O14: 1 | P14: 1 | Q14: 1 | R14: 1 | T14: =K14-'[1]Contracts & Invoices'!R21 -> 0
B15: 11 | C15: 45838 | D15: =EOMONTH(C15,0) -> 45838 | E15: VMI25_00356 | F15: Artelia | G15: BREEAM Consultancy | H15: 2600 | I15: 2375 | J15: 95 | K15: =SUM(I15,J15) -> 2470 | L15: 543.4 | M15: =SUM(K15,L15) -> 3013.4 | N15: 1 | O15: 1 | P15: 1 | Q15: 1 | R15: 1 | T15: =K15-'[1]Contracts & Invoices'!R22 -> 0
B16: 12 | C16: 45852 | D16: =EOMONTH(C16,0) -> 45869 | E16: 146 | F16: Gaia Group | G16: Rilievi Laser Scanner 3D, modellazione 3D Piano Terra e 2D | H16: 16000 | I16: 16000 | J16: 0 | K16: =SUM(I16,J16) -> 16000 | L16: 3520 | M16: =SUM(K16,L16) -> 19520 | N16: 1 | O16: 1 | P16: 1 | Q16: 1 | R16: 1 | T16: =K16-'[1]Contracts & Invoices'!R23 -> 0
... B20: 16 | C20: 45898 | D20: =EOMONTH(C20,0) -> 45900 | E20: VMI25_00445 | F20: Artelia | G20: Multidisciplinary Engineering Design | H20: 0 | I20: 0 | J20: 0 | K20: =SUM(I20,J20) -> 0 | L20: 0 | M20: =SUM(K20,L20) -> 0 | N20: 1 | O20: 1 | P20: 1 | Q20: 1 | R20: 1 | T20: =K20-'[1]Contracts & Invoices'!R27 -> 0
B21: 17 | C21: 45908 | D21: =EOMONTH(C21,0) -> 45930 | E21: 3000103 | F21: HC /Stylt | G21: Travel Costs | H21: 4036 | I21: 4036 | J21: 0 | K21: =SUM(I21,J21) -> 4036 | L21: 0 | M21: =SUM(K21,L21) -> 4036 | N21: 1 | O21: 1 | P21: 1 | Q21: 1 | R21: 1 | T21: =K21-'[1]Contracts & Invoices'!R28 -> 0
B22: 18 | C22: 45916 | D22: =EOMONTH(C22,0) -> 45930 | E22: 075_2025 | F22: Sese | G22: Mock up room n.01 | H22: 14046 | I22: 14046 | J22: 0 | K22: =SUM(I22,J22) -> 14046 | L22: 3090.12 | M22: =SUM(K22,L22) -> 17136.12 | N22: 1 | O22: 1 | P22: 1 | Q22: 1 | R22: 0 | T22: =K22-'[1]Contracts & Invoices'!R29 -> 0
B23: 19 | C23: 45917 | D23: =EOMONTH(C23,0) -> 45930 | E23: 3000105 | F23: HC /Stylt | G23: Extra Costs | H23: 6120 | I23: 6120 | J23: 0 | K23: =SUM(I23,J23) -> 6120 | L23: 0 | M23: =SUM(K23,L23) -> 6120 | N23: 1 | O23: 1 | P23: 1 | Q23: 1 | R23: 0 | T23: =K23-'[1]Contracts & Invoices'!R30 -> 0
B24: 20 | C24: 45922 | D24: =EOMONTH(C24,0) -> 45930 | E24: VMI25_00510 | F24: Artelia /Stylt | G24: Phase 1 - 4 | H24: 57180 | I24: 57180 | J24: 0 | K24: =SUM(I24,J24) -> 57180 | L24: 12579.6 | M24: =SUM(K24,L24) -> 69759.6 | N24: 1 | O24: 1 | P24: 1 | Q24: 1 | R24: 1 | T24: =K24-'[1]Contracts & Invoices'!R31 -> 0
B25: 21 | C25: 45922 | D25: =EOMONTH(C25,0) -> 45930 | E25: VMI25_00509 | F25: Artelia /Stylt | G25: Phase 1 - 4 | H25: 38120 | I25: 38120 | J25: 0 | K25: =SUM(I25,J25) -> 38120 | L25: 8386.4 | M25: =SUM(K25,L25) -> 46506.4 | N25: 1 | O25: 1 | P25: 1 | Q25: 1 | R25: 1 | T25: =K25-'[1]Contracts & Invoices'!R32 -> 0
B26: 22 | C26: 45922 | D26: =EOMONTH(C26,0) -> 45930 | E26: VMI25_00511 | F26: Artelia | G26: Project Management | H26: 11426.087 | I26: 11426.087 | J26: 0 | K26: =SUM(I26,J26) -> 11426.087 | L26: 2513.7391 | M26: =SUM(K26,L26) -> 13939.826 | N26: 1 | O26: 1 | P26: 1 | Q26: 1 | R26: 1 | T26: =K26-'[1]Contracts & Invoices'!R33 -> 0
B27: 23 | C27: 45922 | D27: =EOMONTH(C27,0) -> 45930 | E27: VMI25_00511 | F27: Artelia | G27: Project Management | H27: 11426.087 | I27: 11426.087 | J27: 0 | K27: =SUM(I27,J27) -> 11426.087 | L27: 2513.7391 | M27: =SUM(K27,L27) -> 13939.826 | N27: 1 | O27: 1 | P27: 1 | Q27: 1 | R27: 1 | T27: =K27-'[1]Contracts & Invoices'!R34 -> 0
B28: 24 | C28: 45922 | D28: =EOMONTH(C28,0) -> 45930 | E28: VMI25_00511 | F28: Artelia | G28: Project Management | H28: 0 | I28: 0 | J28: 0 | K28: =SUM(I28,J28) -> 0 | L28: 0.076521739 | M28: =SUM(K28,L28) -> 0.076521739 | N28: 1 | O28: 1 | P28: 1 | Q28: 1 | R28: 1 | T28: =K28-'[1]Contracts & Invoices'!R35 -> 0
B29: 25 | C29: 45922 | D29: =EOMONTH(C29,0) -> 45930 | E29: VMI25_00511 | F29: Artelia | G29: Construction Management | H29: 3130.4348 | I29: 3130.4348 | J29: 0 | K29: =SUM(I29,J29) -> 3130.4348 | L29: 688.69565 | M29: =SUM(K29,L29) -> 3819.1304 | N29: 1 | O29: 1 | P29: 1 | Q29: 1 | R29: 1 | T29: =K29-'[1]Contracts & Invoices'!R36 -> 0
B30: 26 | C30: 45922 | D30: =EOMONTH(C30,0) -> 45930 | E30: VMI25_00511 | F30: Artelia | G30: Construction Management | H30: 3130.4348 | I30: 3130.4348 | J30: 0 | K30: =SUM(I30,J30) -> 3130.4348 | L30: 688.69565 | M30: =SUM(K30,L30) -> 3819.1304 | N30: 1 | O30: 1 | P30: 1 | Q30: 1 | R30: 1 | T30: =K30-'[1]Contracts & Invoices'!R37 -> 0
B31: 27 | C31: 45922 | D31: =EOMONTH(C31,0) -> 45930 | E31: VMI25_00511 | F31: Artelia | G31: Construction Management | H31: 0 | I31: 0 | J31: 0 | K31: =SUM(I31,J31) -> 0 | L31: 2513.7391 | M31: =SUM(K31,L31) -> 2513.7391 | N31: 1 | O31: 1 | P31: 1 | Q31: 1 | R31: 1 | T31: =K31-'[1]Contracts & Invoices'!R38 -> 0
B32: 28 | C32: 45922 | D32: =EOMONTH(C32,0) -> 45930 | E32: VMI25_00511 | F32: Artelia | G32: Multidisciplinary Engineering Design | H32: 84240 | I32: 81000 | J32: 3240 | K32: =SUM(I32,J32) -> 84240 | L32: 18532.8 | M32: =SUM(K32,L32) -> 102772.8 | N32: 1 | O32: 1 | P32: 1 | Q32: 1 | R32: 1 | T32: =K32-'[1]Contracts & Invoices'!R39 -> 0
B33: 29 | C33: 45922 | D33: =EOMONTH(C33,0) -> 45930 | E33: VMI25_00511 | F33: Artelia | G33: Multidisciplinary Engineering Design | H33: 0 | I33: 4050 | J33: 162 | K33: =SUM(I33,J33) -> 4212 | L33: 926.64 | M33: =SUM(K33,L33) -> 5138.64 | N33: 1 | O33: 1 | P33: 1 | Q33: 1 | R33: 1 | T33: =K33-'[1]Contracts & Invoices'!R40 -> 0
B34: 30 | C34: 45922 | D34: =EOMONTH(C34,0) -> 45930 | E34: VMI25_00511 | F34: Artelia | G34: ID Coordination | H34: 869.56522 | I34: 869.56522 | J34: 0 | K34: =SUM(I34,J34) -> 869.56522 | L34: 191.30435 | M34: =SUM(K34,L34) -> 1060.8696 | N34: 1 | O34: 1 | P34: 1 | Q34: 1 | R34: 1 | T34: =K34-'[1]Contracts & Invoices'!R41 -> 0
B35: 31 | C35: 45922 | D35: =EOMONTH(C35,0) -> 45930 | E35: VMI25_00511 | F35: Artelia | G35: ID Coordination | H35: 869.56522 | I35: 869.56522 | J35: 0 | K35: =SUM(I35,J35) -> 869.56522 | L35: 191.30435 | M35: =SUM(K35,L35) -> 1060.8696 | N35: 1 | O35: 1 | P35: 1 | Q35: 1 | R35: 1 | T35: =K35-'[1]Contracts & Invoices'!R42 -> 0
... B43: 39 | C43: 45930 | D43: =EOMONTH(C43,0) -> 45930 | E43: B250410 | F43: Contract | G43: Mock up room n.01 | H43: 16716.28 | I43: 16716.28 | J43: 0 | K43: =SUM(I43,J43) -> 16716.28 | L43: 3677.5816 | M43: =SUM(K43,L43) -> 20393.862 | N43: 1 | O43: 1 | P43: 1 | Q43: 1 | R43: 0 | T43: =K43-'[1]Contracts & Invoices'!R50 -> 0
B44: 40 | C44: 45938 | D44: =EOMONTH(C44,0) -> 45961 | E44: 3000129 | F44: HC /Stylt | G44: Extra Costs | H44: 5040 | I44: 5040 | J44: 0 | K44: =SUM(I44,J44) -> 5040 | L44: 0 | M44: =SUM(K44,L44) -> 5040 | N44: 1 | O44: 1 | P44: 1 | Q44: 1 | R44: 0 | T44: =K44-'[1]Contracts & Invoices'!R51 -> 0
B45: 41 | C45: 45938 | D45: =EOMONTH(C45,0) -> 45961 | E45: 3000126 | F45: HC /Stylt | G45: Extra Costs | H45: 720 | I45: 720 | J45: 0 | K45: =SUM(I45,J45) -> 720 | L45: 0 | M45: =SUM(K45,L45) -> 720 | N45: 1 | O45: 1 | P45: 1 | Q45: 1 | R45: 1 | T45: =K45-'[1]Contracts & Invoices'!R52 -> 0
B46: 42 | C46: 45945 | D46: =EOMONTH(C46,0) -> 45961 | E46: - | F46: Municipality | G46: Comune di Firenze | H46: 16 | I46: 16 | J46: 0 | K46: =SUM(I46,J46) -> 16 | L46: 0 | M46: =SUM(K46,L46) -> 16 | N46: 1 | O46: 1 | P46: 1 | Q46: 1 | R46: 1 | T46: =K46-'[1]Contracts & Invoices'!R53 -> 0
B47: 43 | C47: 45957 | D47: =EOMONTH(C47,0) -> 45961 | E47: 3000134 | F47: HC /Stylt | G47: Extra Costs | H47: -720 | I47: -720 | J47: 0 | K47: =SUM(I47,J47) -> -720 | L47: 0 | M47: =SUM(K47,L47) -> -720 | N47: 1 | O47: 1 | P47: 1 | Q47: 1 | R47: 1 | T47: =K47-'[1]Contracts & Invoices'!R54 -> 0
B48: 44 | C48: 45958 | D48: =EOMONTH(C48,0) -> 45961 | E48: - | F48: Municipality_Asl | G48: Comune di Firenze | H48: 1056 | I48: 1056 | J48: 0 | K48: =SUM(I48,J48) -> 1056 | L48: 0 | M48: =SUM(K48,L48) -> 1056 | N48: 1 | O48: 1 | P48: 1 | Q48: 1 | R48: 1 | T48: =K48-'[1]Contracts & Invoices'!R55 -> 0
B49: 45 | C49: 45961 | D49: =EOMONTH(C49,0) -> 45961 | E49: VMI25_00595 | F49: Artelia | G49: Project Management | H49: 11426.087 | I49: 11426.087 | J49: 0 | K49: =SUM(I49,J49) -> 11426.087 | L49: 2513.7391 | M49: =SUM(K49,L49) -> 13939.826 | N49: 1 | O49: 1 | P49: 1 | Q49: 1 | R49: 1 | T49: =K49-'[1]Contracts & Invoices'!R56 -> 0
B50: 46 | C50: 45961 | D50: =EOMONTH(C50,0) -> 45961 | E50: VMI25_00595 | F50: Artelia | G50: Construction Management | H50: 3130.4348 | I50: 3130.4348 | J50: 0 | K50: =SUM(I50,J50) -> 3130.4348 | L50: 688.69565 | M50: =SUM(K50,L50) -> 3819.1304 | N50: 1 | O50: 1 | P50: 1 | Q50: 1 | R50: 1 | T50: =K50-'[1]Contracts & Invoices'!R57 -> 0
B51: 47 | C51: 45961 | D51: =EOMONTH(C51,0) -> 45961 | E51: VMI25_00595 | F51: Artelia | G51: ID Coordination | H51: 869.56522 | I51: 869.56522 | J51: 0 | K51: =SUM(I51,J51) -> 869.56522 | L51: 191.30435 | M51: =SUM(K51,L51) -> 1060.8696 | N51: 1 | O51: 1 | P51: 1 | Q51: 1 | R51: 1 | T51: =K51-'[1]Contracts & Invoices'!R58 -> 0
B52: 48 | C52: 45965 | D52: =EOMONTH(C52,0) -> 45991 | E52: 3000143 | F52: HC /Stylt | G52: Extra Costs | H52: 1680 | I52: 1680 | J52: 0 | K52: =SUM(I52,J52) -> 1680 | L52: 0 | M52: =SUM(K52,L52) -> 1680 | N52: 1 | O52: 1 | P52: 1 | Q52: 1 | R52: 1 | T52: =K52-'[1]Contracts & Invoices'!R59 -> 0
B53: 49 | C53: 45974 | D53: =EOMONTH(C53,0) -> 45991 | E53: FV-25-2267 | F53: TPC | G53: Mock up room n.02 | H53: 5430 | I53: 5430 | J53: 0 | K53: =SUM(I53,J53) -> 5430 | L53: 1194.6 | M53: =SUM(K53,L53) -> 6624.6 | N53: 1 | O53: 1 | P53: 1 | Q53: 1 | R53: 1 | T53: =K53-'[1]Contracts & Invoices'!R60 -> 0
B54: 50 | C54: 45979 | D54: =EOMONTH(C54,0) -> 45991 | E54: 104_2025 | F54: Sese | G54: Mock up room n.02 | H54: 6122 | I54: 6122 | J54: 0 | K54: =SUM(I54,J54) -> 6122 | L54: 1346.84 | M54: =SUM(K54,L54) -> 7468.84 | N54: 1 | O54: 1 | P54: 1 | Q54: 1 | R54: 0 | T54: =K54-'[1]Contracts & Invoices'!R61 -> 0
B55: 51 | C55: 45980 | D55: =EOMONTH(C55,0) -> 45991 | E55: - | F55: Municipality_Asl | G55: Comune di Firenze | H55: 278 | I55: 278 | J55: 0 | K55: =SUM(I55,J55) -> 278 | L55: 0 | M55: =SUM(K55,L55) -> 278 | N55: 1 | O55: 1 | P55: 1 | Q55: 1 | R55: 1 | T55: =K55-'[1]Contracts & Invoices'!R62 -> 0
B56: 52 | C56: 45980 | D56: =EOMONTH(C56,0) -> 45991 | E56: - | F56: Municipality_Asl | G56: Comune di Firenze | H56: 30 | I56: 30 | J56: 0 | K56: =SUM(I56,J56) -> 30 | L56: 0 | M56: =SUM(K56,L56) -> 30 | N56: 1 | O56: 1 | P56: 1 | Q56: 1 | R56: 1 | T56: =K56-'[1]Contracts & Invoices'!R63 -> 0
B57: 53 | C57: 45989 | D57: =EOMONTH(C57,0) -> 45991 | E57: VMI25_00688 | F57: Artelia /Stylt | G57: Phase 1 - 4 | H57: 9530 | I57: 9530 | J57: 0 | K57: =SUM(I57,J57) -> 9530 | L57: 2096.6 | M57: =SUM(K57,L57) -> 11626.6 | N57: 1 | O57: 1 | P57: 1 | Q57: 1 | R57: 1 | T57: =K57-'[1]Contracts & Invoices'!R64 -> 0
B58: 54 | C58: 45989 | D58: =EOMONTH(C58,0) -> 45991 | E58: VMI25_00688 | F58: Artelia | G58: Project Management | H58: 11426.087 | I58: 11426.087 | J58: 0 | K58: =SUM(I58,J58) -> 11426.087 | L58: 2513.7391 | M58: =SUM(K58,L58) -> 13939.826 | N58: 1 | O58: 1 | P58: 1 | Q58: 1 | R58: 1 | T58: =K58-'[1]Contracts & Invoices'!R65 -> 0
B59: 55 | C59: 45989 | D59: =EOMONTH(C59,0) -> 45991 | E59: VMI25_00688 | F59: Artelia | G59: Construction Management | H59: 3130.4348 | I59: 3130.4348 | J59: 0 | K59: =SUM(I59,J59) -> 3130.4348 | L59: 688.69565 | M59: =SUM(K59,L59) -> 3819.1304 | N59: 1 | O59: 1 | P59: 1 | Q59: 1 | R59: 1 | T59: =K59-'[1]Contracts & Invoices'!R66 -> 0
B60: 56 | C60: 45989 | D60: =EOMONTH(C60,0) -> 45991 | E60: VMI25_00688 | F60: Artelia | G60: Direzione Lavori | H60: 9360 | I60: 9000 | J60: 360 | K60: =SUM(I60,J60) -> 9360 | L60: 2059.2 | M60: =SUM(K60,L60) -> 11419.2 | N60: 1 | O60: 1 | P60: 1 | Q60: 1 | R60: 1 | T60: =K60-'[1]Contracts & Invoices'!R67 -> 0
B61: 57 | C61: 45989 | D61: =EOMONTH(C61,0) -> 45991 | E61: VMI25_00688 | F61: Artelia | G61: Health & Safety | H61: 6240 | I61: 6000 | J61: 240 | K61: =SUM(I61,J61) -> 6240 | L61: 1372.8 | M61: =SUM(K61,L61) -> 7612.8 | N61: 1 | O61: 1 | P61: 1 | Q61: 1 | R61: 1 | T61: =K61-'[1]Contracts & Invoices'!R68 -> 0
B62: 58 | C62: 45989 | D62: =EOMONTH(C62,0) -> 45991 | E62: VMI25_00688 | F62: Artelia | G62: ID Coordination | H62: 869.56522 | I62: 869.56522 | J62: 0 | K62: =SUM(I62,J62) -> 869.56522 | L62: 191.30435 | M62: =SUM(K62,L62) -> 1060.8696 | N62: 1 | O62: 1 | P62: 1 | Q62: 1 | R62: 1 | T62: =K62-'[1]Contracts & Invoices'!R69 -> 0
B63: 59 | C63: 45999 | D63: =EOMONTH(C63,0) -> 46022 | E63: XXXXXX | F63: HC /Stylt | G63: Travel Costs | H63: 5579.5652 | I63: 0 | J63: 0 | K63: =SUM(I63,J63) -> 0 | L63: 0 | M63: =SUM(K63,L63) -> 0 | N63: 1 | O63: 0 | P63: 0 | R63: 0 | T63: =K63-'[1]Contracts & Invoices'!R70 -> 0
B64: 60 | C64: 46009 | D64: =EOMONTH(C64,0) -> 46022 | E64: FV-25-2608 | F64: TPC | G64: Mock up room n.02 | H64: 11906.24 | I64: 11906.24 | J64: 0 | K64: =SUM(I64,J64) -> 11906.24 | L64: 2619.3728 | M64: =SUM(K64,L64) -> 14525.613 | N64: 1 | O64: 1 | P64: 1 | Q64: 1 | R64: 1 | T64: =K64-'[1]Contracts & Invoices'!R71 -> 0
B65: 61 | C65: 46010 | D65: =EOMONTH(C65,0) -> 46022 | E65: - | F65: Municipality_SCIA | G65: Comune di Firenze | H65: 30 | I65: 30 | J65: 0 | K65: =SUM(I65,J65) -> 30 | L65: 0 | M65: =SUM(K65,L65) -> 30 | N65: 1 | O65: 1 | P65: 1 | Q65: 1 | R65: 1 | T65: =K65-'[1]Contracts & Invoices'!R72 -> 0
B66: 62 | C66: 46021 | D66: =EOMONTH(C66,0) -> 46022 | E66: VMI25_00752 | F66: Artelia | G66: Project Management | H66: 11426.087 | I66: 11426.087 | J66: 0 | K66: =SUM(I66,J66) -> 11426.087 | L66: 2513.7391 | M66: =SUM(K66,L66) -> 13939.826 | N66: 1 | O66: 1 | P66: 1 | Q66: 1 | R66: 0 | T66: =K66-'[1]Contracts & Invoices'!R73 -> 0
B67: 63 | C67: 46021 | D67: =EOMONTH(C67,0) -> 46022 | E67: VMI25_00752 | F67: Artelia | G67: Construction Management | H67: 3130.4348 | I67: 3130.4348 | J67: 0 | K67: =SUM(I67,J67) -> 3130.4348 | L67: 688.69565 | M67: =SUM(K67,L67) -> 3819.1304 | N67: 1 | O67: 1 | P67: 1 | Q67: 1 | R67: 0 | T67: =K67-'[1]Contracts & Invoices'!R74 -> 0
B68: 64 | C68: 46021 | D68: =EOMONTH(C68,0) -> 46022 | E68: VMI25_00752 | F68: Artelia | G68: Direzione Lavori | H68: 6480 | I68: 6230.76 | J68: 249.2304 | K68: =SUM(I68,J68) -> 6479.9904 | L68: 1425.5979 | M68: =SUM(K68,L68) -> 7905.5883 | N68: 1 | O68: 1 | P68: 1 | Q68: 1 | R68: 0 | T68: =K68-'[1]Contracts & Invoices'!R75 -> 0
B69: 65 | C69: 46021 | D69: =EOMONTH(C69,0) -> 46022 | E69: VMI25_00752 | F69: Artelia | G69: Health & Safety | H69: 4320 | I69: 4153.84 | J69: 166.1536 | K69: =SUM(I69,J69) -> 4319.9936 | L69: 950.39859 | M69: =SUM(K69,L69) -> 5270.3922 | N69: 1 | O69: 1 | P69: 1 | Q69: 1 | R69: 0 | T69: =K69-'[1]Contracts & Invoices'!R76 -> 0
B70: 66 | C70: 46021 | D70: =EOMONTH(C70,0) -> 46022 | E70: VMI25_00752 | F70: Artelia | G70: ID Coordination | H70: 869.56522 | I70: 869.56522 | J70: 0 | K70: =SUM(I70,J70) -> 869.56522 | L70: 191.30435 | M70: =SUM(K70,L70) -> 1060.8696 | N70: 1 | O70: 1 | P70: 1 | Q70: 1 | R70: 0 | T70: =K70-'[1]Contracts & Invoices'!R77 -> 0
B71: 67 | C71: 46031 | D71: =EOMONTH(C71,0) -> 46053 | E71: FV-26-0026 | F71: TPC | G71: Mock up room n.02 | H71: 763.7 | I71: 763.7 | J71: 0 | K71: =SUM(I71,J71) -> 763.7 | L71: 168.014 | M71: =SUM(K71,L71) -> 931.714 | N71: 1 | O71: 1 | P71: 1 | Q71: 1 | R71: 1 | T71: =K71-'[1]Contracts & Invoices'!R78 -> 0
B72: 68 | C72: 46035 | D72: =EOMONTH(C72,0) -> 46053 | E72: 3000197 | F72: HC /Stylt | G72: Travel Costs | H72: 4854 | I72: 4854 | J72: 0 | K72: =SUM(I72,J72) -> 4854 | L72: 0 | M72: =SUM(K72,L72) -> 4854 | N72: 1 | O72: 1 | P72: 1 | Q72: 1 | R72: 0 | T72: =K72-'[1]Contracts & Invoices'!R79 -> 0
B73: 69 | C73: 46042 | D73: =EOMONTH(C73,0) -> 46053 | E73: VMI26_00002 | F73: Artelia | G73: Project Management | H73: 45704.348 | I73: 45704 | J73: 0 | K73: =SUM(I73,J73) -> 45704 | L73: 10054.88 | M73: =SUM(K73,L73) -> 55758.88 | N73: 1 | O73: 1 | P73: 1 | R73: 0 | T73: =K73-'[1]Contracts & Invoices'!R80 -> 0
B74: 70 | C74: 46042 | D74: =EOMONTH(C74,0) -> 46053 | E74: VMI26_00002 | F74: Artelia | G74: Construction Management | H74: 12521.739 | I74: 12520 | J74: 0 | K74: =SUM(I74,J74) -> 12520 | L74: 2754.4 | M74: =SUM(K74,L74) -> 15274.4 | N74: 1 | O74: 1 | P74: 1 | R74: 0 | T74: =K74-'[1]Contracts & Invoices'!R81 -> 0
B75: 71 | C75: 46042 | D75: =EOMONTH(C75,0) -> 46053 | E75: VMI26_00002 | F75: Artelia | G75: ID Coordination | H75: 3478.2609 | I75: 3480 | J75: 0 | K75: =SUM(I75,J75) -> 3480 | L75: 765.6 | M75: =SUM(K75,L75) -> 4245.6 | N75: 1 | O75: 1 | P75: 1 | R75: 0 | T75: =K75-'[1]Contracts & Invoices'!R82 -> 0
B76: 72 | C76: 46044 | D76: =EOMONTH(C76,0) -> 46053 | E76: XXXX | F76: Municipality_Asl | G76: Comune di Firenze:Pagamenti sportello unico attività produttive | H76: 1288.32 | I76: 1288.32 | J76: 0 | K76: =SUM(I76,J76) -> 1288.32 | L76: 0 | M76: =SUM(K76,L76) -> 1288.32 | N76: 1 | O76: 1 | P76: 1 | Q76: 1 | R76: 1 | T76: =K76-'[1]Contracts & Invoices'!R83 -> 0
B77: 73 | C77: 46052 | D77: =EOMONTH(C77,0) -> 46053 | E77: 3000216 | F77: HC /Stylt | G77: Signage | H77: 3000 | I77: 3000 | J77: 0 | K77: =SUM(I77,J77) -> 3000 | L77: 0 | M77: =SUM(K77,L77) -> 3000 | N77: 1 | O77: 1 | P77: 1 | Q77: 1 | R77: 0 | T77: =K77-'[1]Contracts & Invoices'!R84 -> 0
B78: 74 | C78: 46052 | D78: =EOMONTH(C78,0) -> 46053 | E78: 3000217 | F78: HC /Stylt | G78: Art&Props | H78: 10000 | I78: 10000 | J78: 0 | K78: =SUM(I78,J78) -> 10000 | L78: 0 | M78: =SUM(K78,L78) -> 10000 | N78: 1 | O78: 1 | P78: 1 | Q78: 1 | R78: 0 | T78: =K78-'[1]Contracts & Invoices'!R85 -> 0
B79: 75 | C79: 46052 | D79: =EOMONTH(C79,0) -> 46053 | E79: XXXX | F79: HC /Stylt | G79: Art&Props | H79: 25000 | I79: 0 | J79: 0 | K79: =SUM(I79,J79) -> 0 | L79: 0 | M79: =SUM(K79,L79) -> 0 | N79: 1 | O79: 0 | P79: 0 | R79: 0 | T79: =K79-'[1]Contracts & Invoices'!R86 -> 0
B80: 76 | C80: 46052 | D80: =EOMONTH(C80,0) -> 46053 | E80: XXXX | F80: Protos | G80: Monitoring | H80: 5000 | I80: 0 | J80: 0 | K80: =SUM(I80,J80) -> 0 | L80: 0 | M80: =SUM(K80,L80) -> 0 | N80: 1 | O80: 0 | P80: 0 | R80: 0 | T80: =K80-'[1]Contracts & Invoices'!R87 -> 0
B81: 77 | C81: 46057 | D81: =EOMONTH(C81,0) -> 46081 | E81: 3000231 | F81: HC /Stylt | G81: Extra Costs | H81: 1620 | I81: 1620 | J81: 0 | K81: =SUM(I81,J81) -> 1620 | L81: 0 | M81: =SUM(K81,L81) -> 1620 | N81: 1 | O81: 1 | P81: 1 | Q81: 1 | R81: 0 | T81: =K81-'[1]Contracts & Invoices'!R88 -> 0
B82: 78 | C82: 46057 | D82: =EOMONTH(C82,0) -> 46081 | E82: 3000232 | F82: HC /Stylt | G82: Extra Costs | H82: 2580 | I82: 2580 | J82: 0 | K82: =SUM(I82,J82) -> 2580 | L82: 0 | M82: =SUM(K82,L82) -> 2580 | N82: 1 | O82: 1 | P82: 1 | Q82: 1 | R82: 0 | T82: =K82-'[1]Contracts & Invoices'!R89 -> 0
B83: 79 | C83: 46080 | D83: =EOMONTH(C83,0) -> 46081 | E83: - | F83: ENEL | G83: ENEL | H83: 20419.39 | I83: 20442.39 | J83: 0 | K83: =SUM(I83,J83) -> 20442.39 | L83: 4497.3258 | M83: =SUM(K83,L83) -> 24939.716 | N83: 1 | O83: 1 | P83: 1 | Q83: 1 | R83: 1 | T83: =K83-'[1]Contracts & Invoices'!R90 -> 0
B84: 80 | C84: 46081 | D84: =EOMONTH(C84,0) -> 46081 | E84: VMI26_00108 | F84: Artelia /Stylt | G84: Phase 1 - 4 | H84: 9530 | I84: 9530 | J84: 0 | K84: =SUM(I84,J84) -> 9530 | L84: 2096.6 | M84: =SUM(K84,L84) -> 11626.6 | N84: 1 | O84: 1 | P84: 1 | R84: 0 | T84: =K84-'[1]Contracts & Invoices'!R91 -> 0
B85: 81 | C85: 46081 | D85: =EOMONTH(C85,0) -> 46081 | E85: VMI26_00105 | F85: Artelia | G85: Project Management | H85: 11426.087 | I85: 11426 | J85: 0 | K85: =SUM(I85,J85) -> 11426 | L85: 2513.72 | M85: =SUM(K85,L85) -> 13939.72 | N85: 1 | O85: 1 | P85: 1 | R85: 0 | T85: =K85-'[1]Contracts & Invoices'!R92 -> 0
B86: 82 | C86: 46081 | D86: =EOMONTH(C86,0) -> 46081 | E86: VMI26_00106 | F86: Artelia | G86: Project Management | H86: 11426.087 | I86: 11426 | J86: 0 | K86: =SUM(I86,J86) -> 11426 | L86: 2513.72 | M86: =SUM(K86,L86) -> 13939.72 | N86: 1 | O86: 1 | P86: 1 | R86: 0 | T86: =K86-'[1]Contracts & Invoices'!R93 -> 0
B87: 83 | C87: 46081 | D87: =EOMONTH(C87,0) -> 46081 | E87: VMI26_00105 | F87: Artelia | G87: Construction Management | H87: 3130.4348 | I87: 3130.65 | J87: 0 | K87: =SUM(I87,J87) -> 3130.65 | L87: 688.743 | M87: =SUM(K87,L87) -> 3819.393 | N87: 1 | O87: 1 | P87: 1 | R87: 0 | T87: =K87-'[1]Contracts & Invoices'!R94 -> 0
B88: 84 | C88: 46081 | D88: =EOMONTH(C88,0) -> 46081 | E88: VMI26_00106 | F88: Artelia | G88: Construction Management | H88: 3130.4348 | I88: 3130.65 | J88: 0 | K88: =SUM(I88,J88) -> 3130.65 | L88: 688.743 | M88: =SUM(K88,L88) -> 3819.393 | N88: 1 | O88: 1 | P88: 1 | R88: 0 | T88: =K88-'[1]Contracts & Invoices'!R95 -> 0
B89: 85 | C89: 46081 | D89: =EOMONTH(C89,0) -> 46081 | E89: VMI26_00105 | F89: Artelia | G89: Direzione Lavori | H89: 6480 | I89: 6230.77 | J89: 249.2308 | K89: =SUM(I89,J89) -> 6480.0008 | L89: 1425.6002 | M89: =SUM(K89,L89) -> 7905.601 | N89: 1 | O89: 1 | P89: 1 | R89: 0 | T89: =K89-'[1]Contracts & Invoices'!R96 -> 0
B90: 86 | C90: 46081 | D90: =EOMONTH(C90,0) -> 46081 | E90: VMI26_00106 | F90: Artelia | G90: Direzione Lavori | H90: 6480 | I90: 6230.77 | J90: 249.2308 | K90: =SUM(I90,J90) -> 6480.0008 | L90: 1425.6002 | M90: =SUM(K90,L90) -> 7905.601 | N90: 1 | O90: 1 | P90: 1 | R90: 0 | T90: =K90-'[1]Contracts & Invoices'!R97 -> 0
B91: 87 | C91: 46081 | D91: =EOMONTH(C91,0) -> 46081 | E91: VMI26_00105 | F91: Artelia | G91: Health & Safety | H91: 4320 | I91: 4153.85 | J91: 166.154 | K91: =SUM(I91,J91) -> 4320.004 | L91: 950.40088 | M91: =SUM(K91,L91) -> 5270.4049 | N91: 1 | O91: 1 | P91: 1 | R91: 0 | T91: =K91-'[1]Contracts & Invoices'!R98 -> 0
B92: 88 | C92: 46081 | D92: =EOMONTH(C92,0) -> 46081 | E92: VMI26_00106 | F92: Artelia | G92: Health & Safety | H92: 4320 | I92: 4153.85 | J92: 166.154 | K92: =SUM(I92,J92) -> 4320.004 | L92: 950.40088 | M92: =SUM(K92,L92) -> 5270.4049 | N92: 1 | O92: 1 | P92: 1 | R92: 0 | T92: =K92-'[1]Contracts & Invoices'!R99 -> 0
B93: 89 | C93: 46081 | D93: =EOMONTH(C93,0) -> 46081 | E93: VMI26_00105 | F93: Artelia | G93: ID Coordination | H93: 869.56522 | I93: 869.34 | J93: 0 | K93: =SUM(I93,J93) -> 869.34 | L93: 191.2548 | M93: =SUM(K93,L93) -> 1060.5948 | N93: 1 | O93: 1 | P93: 1 | R93: 0 | T93: =K93-'[1]Contracts & Invoices'!R100 -> 0
B94: 90 | C94: 46081 | D94: =EOMONTH(C94,0) -> 46081 | E94: VMI26_00106 | F94: Artelia | G94: ID Coordination | H94: 869.56522 | I94: 869.34 | J94: 0 | K94: =SUM(I94,J94) -> 869.34 | L94: 191.2548 | M94: =SUM(K94,L94) -> 1060.5948 | N94: 1 | O94: 1 | P94: 1 | R94: 0 | T94: =K94-'[1]Contracts & Invoices'!R101 -> 0
B95: 91 | C95: 46081 | D95: =EOMONTH(C95,0) -> 46081 | E95: XXXX | F95: CO.E.LIVE_GC | G95: GC Works | H95: 11179.111 | I95: 11179.111 | J95: 0 | K95: =SUM(I95,J95) -> 11179.111 | L95: 0 | M95: =SUM(K95,L95) -> 11179.111 | N95: 1 | O95: 0 | P95: 0 | R95: 0 | T95: =K95-'[1]Contracts & Invoices'!R102 -> 11179.111
... B114: 110 | C114: 46112 | D114: =EOMONTH(C114,0) -> 46112 | E114: TD01-30 | F114: CO.E.LIVE_GC | G114: GC Works | H114: 16545.78 | I114: 16545.78 | J114: 0 | K114: =SUM(I114,J114) -> 16545.78 | L114: 3640.0716 | M114: =SUM(K114,L114) -> 20185.852 | N114: 1 | O114: 1 | P114: 1 | R114: 0 | T114: =K114-'[1]Contracts & Invoices'!R121 -> 0
B115: 111 | C115: 46136 | D115: =EOMONTH(C115,0) -> 46142 | E115: 0534_00000011649 | F115: Wentzo | G115: Hardware and instal. for network & wifi | H115: 85317.5 | I115: 85317.5 | J115: 0 | K115: =SUM(I115,J115) -> 85317.5 | L115: 5011.86 | M115: =SUM(K115,L115) -> 90329.36 | N115: 1 | O115: 1 | P115: 1 | Q115: 1 | R115: 1 | T115: =K115-'[1]Contracts & Invoices'!R122 -> 61451.5
B116: 112 | C116: 46142 | D116: =EOMONTH(C116,0) -> 46142 | E116: VMI26_00214 | F116: Artelia /Stylt | G116: Phase 5 | H116: 7950 | I116: 7950 | J116: 0 | K116: =SUM(I116,J116) -> 7950 | L116: 0 | M116: =SUM(K116,L116) -> 7950 | N116: 1 | O116: 1 | P116: 1 | R116: 0 | T116: =K116-'[1]Contracts & Invoices'!R123 -> 0
B117: 113 | C117: 46142 | D117: =EOMONTH(C117,0) -> 46142 | E117: VMI26_00222 | F117: Artelia /Stylt | G117: Phase 5 | H117: 1650 | I117: 1650 | J117: 0 | K117: =SUM(I117,J117) -> 1650 | L117: 0 | M117: =SUM(K117,L117) -> 1650 | N117: 1 | O117: 1 | P117: 1 | T117: =K117-'[1]Contracts & Invoices'!R124 -> 0
B118: 114 | C118: 46142 | D118: =EOMONTH(C118,0) -> 46142 | E118: VMI26_00201 | F118: Artelia | G118: Project Management | H118: 11426.087 | I118: 11426.14 | J118: 0 | K118: =SUM(I118,J118) -> 11426.14 | L118: 0 | M118: =SUM(K118,L118) -> 11426.14 | N118: 1 | O118: 0 | P118: 0 | R118: 0 | T118: =K118-'[1]Contracts & Invoices'!R125 -> 0
B119: 115 | C119: 46142 | D119: =EOMONTH(C119,0) -> 46142 | E119: VMI26_00201 | F119: Artelia | G119: Construction Management | H119: 3130.4348 | I119: 3130.56 | J119: 0 | K119: =SUM(I119,J119) -> 3130.56 | L119: 0 | M119: =SUM(K119,L119) -> 3130.56 | N119: 1 | O119: 0 | P119: 0 | R119: 0 | T119: =K119-'[1]Contracts & Invoices'!R126 -> 0
B120: 116 | C120: 46142 | D120: =EOMONTH(C120,0) -> 46142 | E120: VMI26_00201 | F120: Artelia | G120: Direzione Lavori | H120: 6480 | I120: 6230.77 | J120: 249.2308 | K120: =SUM(I120,J120) -> 6480.0008 | L120: 0 | M120: =SUM(K120,L120) -> 6480.0008 | N120: 1 | O120: 0 | P120: 0 | R120: 0 | T120: =K120-'[1]Contracts & Invoices'!R127 -> 0
B121: 117 | C121: 46142 | D121: =EOMONTH(C121,0) -> 46142 | E121: VMI26_00201 | F121: Artelia | G121: Health & Safety | H121: 4320 | I121: 4153.85 | J121: 166.154 | K121: =SUM(I121,J121) -> 4320.004 | L121: 0 | M121: =SUM(K121,L121) -> 4320.004 | N121: 1 | O121: 0 | P121: 0 | R121: 0 | T121: =K121-'[1]Contracts & Invoices'!R128 -> 0
B122: 118 | C122: 46142 | D122: =EOMONTH(C122,0) -> 46142 | E122: VMI26_00201 | F122: Artelia | G122: ID Coordination | H122: 869.56522 | I122: 869.43 | J122: 0 | K122: =SUM(I122,J122) -> 869.43 | L122: 0 | M122: =SUM(K122,L122) -> 869.43 | N122: 1 | O122: 0 | P122: 0 | R122: 0 | T122: =K122-'[1]Contracts & Invoices'!R129 -> 0
B123: 119 | C123: 46142 | D123: =EOMONTH(C123,0) -> 46142 | E123: XXXX | F123: Protos | G123: Monitoring | H123: 2700 | I123: 0 | J123: 0 | K123: =SUM(I123,J123) -> 0 | L123: 0 | M123: =SUM(K123,L123) -> 0 | N123: 1 | O123: 0 | P123: 0 | R123: 0 | T123: =K123-'[1]Contracts & Invoices'!R130 -> 0
B124: 120 | C124: 46142 | D124: =EOMONTH(C124,0) -> 46142 | E124: XXXX | F124: Catalyst | G124: Flood risk ass.+Resources Inv.services | H124: 9000 | I124: 0 | J124: 0 | K124: =SUM(I124,J124) -> 0 | L124: 0 | M124: =SUM(K124,L124) -> 0 | N124: 1 | O124: 0 | P124: 0 | R124: 0 | T124: =K124-'[1]Contracts & Invoices'!R131 -> 0

Sheet Model - Capex
B2: To Date | D2: 46112
B3: Period | F3: 0 | G3: 0 | H3: 0 | I3: =F3+1 -> 1 | J3: =G3+1 -> 1 | K3: =H3+1 -> 1 | L3: =I3+1 -> 2 | M3: =J3+1 -> 2 | N3: =K3+1 -> 2 | O3: =L3+1 -> 3 | P3: =M3+1 -> 3 | ... AL3: =AI3+1 -> 10 | AN3: 0 | AO3: =AN3+1 -> 1 | AP3: =AO3+1 -> 2 | AQ3: =AP3+1 -> 3 | AR3: =AQ3+1 -> 4 | AS3: =AR3+1 -> 5 | AT3: =AS3+1 -> 6 | AU3: =AT3+1 -> 7 | AV3: =AU3+1 -> 8 | ... AX3: =AW3+1 -> 10
B4: BoP | F4: 45658 | G4: =F5+1 -> 45689 | H4: =G5+1 -> 45717 | I4: =H5+1 -> 45748 | J4: =I5+1 -> 45778 | K4: =J5+1 -> 45809 | L4: =K5+1 -> 45839 | M4: =L5+1 -> 45870 | N4: =M5+1 -> 45901 | ... AL4: =AK5+1 -> 46631 | AN4: 45658 | AO4: =AN5+1 -> 45748 | AP4: =AO5+1 -> 45839 | AQ4: =AP5+1 -> 45931 | AR4: =AQ5+1 -> 46023 | AS4: =AR5+1 -> 46113 | AT4: =AS5+1 -> 46204 | AU4: =AT5+1 -> 46296 | AV4: =AU5+1 -> 46388 | ... AX4: =AW5+1 -> 46569
B5: EoP | D5: Total | F5: 45688 | G5: =EOMONTH(F5,1) -> 45716 | H5: =EOMONTH(G5,1) -> 45747 | I5: =EOMONTH(H5,1) -> 45777 | J5: =EOMONTH(I5,1) -> 45808 | K5: =EOMONTH(J5,1) -> 45838 | L5: =EOMONTH(K5,1) -> 45869 | M5: =EOMONTH(L5,1) -> 45900 | N5: =EOMONTH(M5,1) -> 45930 | ... AL5: =EOMONTH(AK5,1) -> 46660 | AN5: 45747 | AO5: =EOMONTH(AN5,3) -> 45838 | AP5: =EOMONTH(AO5,3) -> 45930 | AQ5: =EOMONTH(AP5,3) -> 46022 | AR5: =EOMONTH(AQ5,3) -> 46112 | AS5: =EOMONTH(AR5,3) -> 46203 | AT5: =EOMONTH(AS5,3) -> 46295 | AU5: =EOMONTH(AT5,3) -> 46387 | AV5: =EOMONTH(AU5,3) -> 46477 | ... AX5: =EOMONTH(AW5,3) -> 46660
B7: Paid | D7: =SUM(F7:AL7) -> 840931.24 | F7: =SUMIFS(Invoices!$K$5:$K$2998,Invoices!$D$5:$D$2998,F$5,Invoices!$R$5:$R$2998,1)*(F$5<=$D$2) -> 0 | G7: =SUMIFS(Invoices!$K$5:$K$2998,Invoices!$D$5:$D$2998,G$5,Invoices!$R$5:$R$2998,1)*(G$5<=$D$2) -> 4000 | H7: =SUMIFS(Invoices!$K$5:$K$2998,Invoices!$D$5:$D$2998,H$5,Invoices!$R$5:$R$2998,1)*(H$5<=$D$2) -> 5100 | I7: =SUMIFS(Invoices!$K$5:$K$2998,Invoices!$D$5:$D$2998,I$5,Invoices!$R$5:$R$2998,1)*(I$5<=$D$2) -> 0 | J7: =SUMIFS(Invoices!$K$5:$K$2998,Invoices!$D$5:$D$2998,J$5,Invoices!$R$5:$R$2998,1)*(J$5<=$D$2) -> 64200 | K7: =SUMIFS(Invoices!$K$5:$K$2998,Invoices!$D$5:$D$2998,K$5,Invoices!$R$5:$R$2998,1)*(K$5<=$D$2) -> 173392.79 | L7: =SUMIFS(Invoices!$K$5:$K$2998,Invoices!$D$5:$D$2998,L$5,Invoices!$R$5:$R$2998,1)*(L$5<=$D$2) -> 16000 | M7: =SUMIFS(Invoices!$K$5:$K$2998,Invoices!$D$5:$D$2998,M$5,Invoices!$R$5:$R$2998,1)*(M$5<=$D$2) -> 6802 | ... AL7: =SUMIFS(Invoices!$K$5:$K$2998,Invoices!$D$5:$D$2998,AL$5,Invoices!$R$5:$R$2998,1)*(AL$5<=$D$2) -> 0 | AN7: =-SUMIFS($F7:$AL7,$F$3:$AL$3,AN$3) -> -9100 | AO7: =-SUMIFS($F7:$AL7,$F$3:$AL$3,AO$3) -> -237592.79 | AP7: =-SUMIFS($F7:$AL7,$F$3:$AL$3,AP$3) -> -352507.83 | AQ7: =-SUMIFS($F7:$AL7,$F$3:$AL$3,AQ$3) -> -76408.414 | AR7: =-SUMIFS($F7:$AL7,$F$3:$AL$3,AR$3) -> -165322.21 | AS7: =-SUMIFS($F7:$AL7,$F$3:$AL$3,AS$3) -> 0 | AT7: =-SUMIFS($F7:$AL7,$F$3:$AL$3,AT$3) -> 0 | AU7: =-SUMIFS($F7:$AL7,$F$3:$AL$3,AU$3) -> 0 | ... AX7: =-SUMIFS($F7:$AL7,$F$3:$AL$3,AX$3) -> 0 | AZ7: =SUM(AN7:AX7) -> -840931.24
B8: VAT | D8: =SUM(F8:AL8) -> 182741.1 | F8: =SUMIFS(Invoices!$L$5:$L$2998,Invoices!$D$5:$D$2998,F$5,Invoices!$R$5:$R$2998,1)*(F$5<=$D$2) -> 0 | G8: =SUMIFS(Invoices!$L$5:$L$2998,Invoices!$D$5:$D$2998,G$5,Invoices!$R$5:$R$2998,1)*(G$5<=$D$2) -> 0 | H8: =SUMIFS(Invoices!$L$5:$L$2998,Invoices!$D$5:$D$2998,H$5,Invoices!$R$5:$R$2998,1)*(H$5<=$D$2) -> 572 | I8: =SUMIFS(Invoices!$L$5:$L$2998,Invoices!$D$5:$D$2998,I$5,Invoices!$R$5:$R$2998,1)*(I$5<=$D$2) -> 0 | J8: =SUMIFS(Invoices!$L$5:$L$2998,Invoices!$D$5:$D$2998,J$5,Invoices!$R$5:$R$2998,1)*(J$5<=$D$2) -> 14124 | K8: =SUMIFS(Invoices!$L$5:$L$2998,Invoices!$D$5:$D$2998,K$5,Invoices!$R$5:$R$2998,1)*(K$5<=$D$2) -> 38146.414 | L8: =SUMIFS(Invoices!$L$5:$L$2998,Invoices!$D$5:$D$2998,L$5,Invoices!$R$5:$R$2998,1)*(L$5<=$D$2) -> 3520 | M8: =SUMIFS(Invoices!$L$5:$L$2998,Invoices!$D$5:$D$2998,M$5,Invoices!$R$5:$R$2998,1)*(M$5<=$D$2) -> 0 | ... AL8: =SUMIFS(Invoices!$L$5:$L$2998,Invoices!$D$5:$D$2998,AL$5,Invoices!$R$5:$R$2998,1)*(AL$5<=$D$2) -> 0 | AN8: =-SUMIFS($F8:$AL8,$F$3:$AL$3,AN$3) -> -572 | AO8: =-SUMIFS($F8:$AL8,$F$3:$AL$3,AO$3) -> -52270.414 | AP8: =-SUMIFS($F8:$AL8,$F$3:$AL$3,AP$3) -> -77681.177 | AQ8: =-SUMIFS($F8:$AL8,$F$3:$AL$3,AQ$3) -> -16130.051 | AR8: =-SUMIFS($F8:$AL8,$F$3:$AL$3,AR$3) -> -36087.457 | AS8: =-SUMIFS($F8:$AL8,$F$3:$AL$3,AS$3) -> 0 | AT8: =-SUMIFS($F8:$AL8,$F$3:$AL$3,AT$3) -> 0 | AU8: =-SUMIFS($F8:$AL8,$F$3:$AL$3,AU$3) -> 0 | ... AX8: =-SUMIFS($F8:$AL8,$F$3:$AL$3,AX$3) -> 0 | AZ8: =SUM(AN8:AX8) -> -182741.1
B9: Gross Paid | D9: =SUM(F9:AL9) -> 1023672.3 | F9: =SUM(F7:F8) -> 0 | G9: =SUM(G7:G8) -> 4000 | H9: =SUM(H7:H8) -> 5672 | I9: =SUM(I7:I8) -> 0 | J9: =SUM(J7:J8) -> 78324 | K9: =SUM(K7:K8) -> 211539.2 | L9: =SUM(L7:L8) -> 19520 | M9: =SUM(M7:M8) -> 6802 | ... AL9: =SUM(AL7:AL8) -> 0 | AN9: =SUM(AN7:AN8) -> -9672 | AO9: =SUM(AO7:AO8) -> -289863.2 | AP9: =SUM(AP7:AP8) -> -430189 | AQ9: =SUM(AQ7:AQ8) -> -92538.465 | AR9: =SUM(AR7:AR8) -> -201409.67 | AS9: =SUM(AS7:AS8) -> 0 | AT9: =SUM(AT7:AT8) -> 0 | AU9: =SUM(AU7:AU8) -> 0 | ... AX9: =SUM(AX7:AX8) -> 0 | AZ9: =SUM(AN9:AX9) -> -1023672.3
B12: Artelia Forecast | D12: =SUM(F12:AL12) -> 7343225 | F12: 0 | G12: 0 | H12: 0 | I12: 0 | J12: 0 | K12: 0 | L12: 0 | M12: 0 | N12: 0 | O12: 0 | P12: 0 | Q12: 0 | R12: 0 | S12: 0 | T12: 0 | U12: 598243.08 | V12: 680821.78 | W12: 770821.78 | X12: 766417.33 | Y12: 682774.66 | Z12: 795274.66 | AA12: 810274.66 | AB12: 831274.66 | AC12: 649195.96 | AD12: 758126.4 | AE12: 0 | AF12: 0 | AG12: 0 | AH12: 0 | AI12: 0 | AJ12: 0 | AK12: 0 | AL12: 0
B13: % Total | D13: =SUM(F13:AL13) -> 1 | F13: =IFERROR(F12/$D$12,0) -> 0 | G13: =IFERROR(G12/$D$12,0) -> 0 | H13: =IFERROR(H12/$D$12,0) -> 0 | I13: =IFERROR(I12/$D$12,0) -> 0 | J13: =IFERROR(J12/$D$12,0) -> 0 | K13: =IFERROR(K12/$D$12,0) -> 0 | L13: =IFERROR(L12/$D$12,0) -> 0 | M13: =IFERROR(M12/$D$12,0) -> 0 | ... AL13: =IFERROR(AL12/$D$12,0) -> 0
B14: % Total - Forecast Curve | D14: =SUM(F14:AL14) -> 1 | F14: 0 | G14: 0 | H14: 0 | I14: 0 | J14: 0 | K14: 0 | L14: 0 | M14: 0 | N14: 0 | O14: 0 | P14: 0 | Q14: 0 | R14: 0 | S14: 0 | T14: 0 | U14: =IFERROR(U13/SUM($U$13:$AL$13),0) -> 0.081468712 | V14: =IFERROR(V13/SUM($U$13:$AL$13),0) -> 0.092714275 | W14: =IFERROR(W13/SUM($U$13:$AL$13),0) -> 0.10497047 | X14: =IFERROR(X13/SUM($U$13:$AL$13),0) -> 0.10437067 | Y14: =IFERROR(Y13/SUM($U$13:$AL$13),0) -> 0.092980218 | Z14: =IFERROR(Z13/SUM($U$13:$AL$13),0) -> 0.10830046 | AA14: =IFERROR(AA13/SUM($U$13:$AL$13),0) -> 0.11034316 | AB14: =IFERROR(AB13/SUM($U$13:$AL$13),0) -> 0.11320294 | ... AL14: =IFERROR(AL13/SUM($U$13:$AL$13),0) -> 0
B15: Remaining Spend | D15: =9000000-D7-300000 -> 7859068.8 | F15: =F$14*$D$15 -> 0 | G15: =G$14*$D$15 -> 0 | H15: =H$14*$D$15 -> 0 | I15: =I$14*$D$15 -> 0 | J15: =J$14*$D$15 -> 0 | K15: =K$14*$D$15 -> 0 | L15: =L$14*$D$15 -> 0 | M15: =M$14*$D$15 -> 0 | ... AL15: =AL$14*$D$15 -> 0 | AN15: =-SUMIFS($F15:$AL15,$F$3:$AL$3,AN$3) -> 0 | AO15: =-SUMIFS($F15:$AL15,$F$3:$AL$3,AO$3) -> 0 | AP15: =-SUMIFS($F15:$AL15,$F$3:$AL$3,AP$3) -> 0 | AQ15: =-SUMIFS($F15:$AL15,$F$3:$AL$3,AQ$3) -> 0 | AR15: =-SUMIFS($F15:$AL15,$F$3:$AL$3,AR$3) -> 0 | AS15: =-SUMIFS($F15:$AL15,$F$3:$AL$3,AS$3) -> -2193886.2 | AT15: =-SUMIFS($F15:$AL15,$F$3:$AL$3,AT$3) -> -2402135 | AU15: =-SUMIFS($F15:$AL15,$F$3:$AL$3,AU$3) -> -2451664.6 | ... AX15: =-SUMIFS($F15:$AL15,$F$3:$AL$3,AX$3) -> 0 | AZ15: =SUM(AN15:AX15) -> -7859068.8
B16: VAT (Assumption) | D16: =SUM(F16:AL16) -> 1728995.1 | F16: =F15*22% -> 0 | G16: =G15*22% -> 0 | H16: =H15*22% -> 0 | I16: =I15*22% -> 0 | J16: =J15*22% -> 0 | K16: =K15*22% -> 0 | L16: =L15*22% -> 0 | M16: =M15*22% -> 0 | ... AL16: =AL15*22% -> 0 | AN16: =-SUMIFS($F16:$AL16,$F$3:$AL$3,AN$3) -> 0 | AO16: =-SUMIFS($F16:$AL16,$F$3:$AL$3,AO$3) -> 0 | AP16: =-SUMIFS($F16:$AL16,$F$3:$AL$3,AP$3) -> 0 | AQ16: =-SUMIFS($F16:$AL16,$F$3:$AL$3,AQ$3) -> 0 | AR16: =-SUMIFS($F16:$AL16,$F$3:$AL$3,AR$3) -> 0 | AS16: =-SUMIFS($F16:$AL16,$F$3:$AL$3,AS$3) -> -482654.97 | AT16: =-SUMIFS($F16:$AL16,$F$3:$AL$3,AT$3) -> -528469.7 | AU16: =-SUMIFS($F16:$AL16,$F$3:$AL$3,AU$3) -> -539366.21 | ... AX16: =-SUMIFS($F16:$AL16,$F$3:$AL$3,AX$3) -> 0 | AZ16: =SUM(AN16:AX16) -> -1728995.1
B17: Remaining + VAT | D17: =SUM(F17:AN17) -> 9588063.9 | F17: =SUM(F15,F16) -> 0 | G17: =SUM(G15,G16) -> 0 | H17: =SUM(H15,H16) -> 0 | I17: =SUM(I15,I16) -> 0 | J17: =SUM(J15,J16) -> 0 | K17: =SUM(K15,K16) -> 0 | L17: =SUM(L15,L16) -> 0 | M17: =SUM(M15,M16) -> 0 | ... AL17: =SUM(AL15,AL16) -> 0 | AN17: =SUM(AN15,AN16) -> 0 | AO17: =SUM(AO15,AO16) -> 0 | AP17: =SUM(AP15,AP16) -> 0 | AQ17: =SUM(AQ15,AQ16) -> 0 | AR17: =SUM(AR15,AR16) -> 0 | AS17: =SUM(AS15,AS16) -> -2676541.2 | AT17: =SUM(AT15,AT16) -> -2930604.7 | AU17: =SUM(AU15,AU16) -> -2991030.8 | ... AX17: =SUM(AX15,AX16) -> 0 | AZ17: =SUM(AN17:AX17) -> -9588063.9
B19: Model - Dev Costs | D19: =SUM(F19:AL19) -> 7859068.8 | F19: 0 | G19: 0 | H19: 0 | I19: 0 | J19: 0 | K19: 0 | L19: 0 | M19: 0 | N19: 0 | O19: 0 | P19: 0 | Q19: 0 | R19: 0 | S19: 0 | T19: 0 | U19: =SUM(U7,U15) -> 640268.21 | V19: =SUM(V7,V15) -> 728647.86 | W19: =SUM(W7,W15) -> 824970.14 | X19: =SUM(X7,X15) -> 820256.29 | Y19: =SUM(Y7,Y15) -> 730737.93 | Z19: =SUM(Z7,Z15) -> 851140.78 | AA19: =SUM(AA7,AA15) -> 867194.49 | AB19: =SUM(AB7,AB15) -> 889669.69 | ... AL19: =SUM(AL7,AL15) -> 0 | AN19: 0 | AO19: 0 | AP19: 0 | AQ19: 0 | AR19: 0 | AS19: =SUM(AS7,AS15) -> -2193886.2 | AT19: =SUM(AT7,AT15) -> -2402135 | AU19: =SUM(AU7,AU15) -> -2451664.6 | AV19: =SUM(AV7,AV15) -> -811382.95 | AW19: =SUM(AW7,AW15) -> 0 | AX19: =SUM(AX7,AX15) -> 0 | AZ19: =SUM(AN19:AX19) -> -7859068.8
B20: Model - VAT Due | D20: =SUM(F20:AL20) -> 1728995.1 | F20: 0 | G20: 0 | H20: 0 | I20: 0 | J20: 0 | K20: 0 | L20: 0 | M20: 0 | N20: 0 | O20: 0 | P20: 0 | Q20: 0 | R20: 0 | S20: 0 | T20: 0 | U20: =U16+U8 -> 140859.01 | V20: =V16 -> 160302.53 | W20: =W16 -> 181493.43 | X20: =X16 -> 180456.38 | Y20: =Y16 -> 160762.34 | Z20: =Z16 -> 187250.97 | AA20: =AA16 -> 190782.79 | AB20: =AB16 -> 195727.33 | AC20: =AC16 -> 152856.09 | ... AL20: =AL16 -> 0 | AN20: 0 | AO20: 0 | AP20: 0 | AQ20: 0 | AR20: 0 | AS20: =SUM(AS8,AS16) -> -482654.97 | AT20: =SUM(AT8,AT16) -> -528469.7 | AU20: =SUM(AU8,AU16) -> -539366.21 | AV20: =SUM(AV8,AV16) -> -178504.25 | AW20: =SUM(AW8,AW16) -> 0 | AX20: =SUM(AX8,AX16) -> 0 | AZ20: =SUM(AN20:AX20) -> -1728995.1
B21: Model - VAT Repaid | D21: =SUM(F21:AL21) -> -1728995.1 | F21: 0 | G21: 0 | H21: 0 | I21: 0 | J21: 0 | K21: 0 | L21: 0 | M21: 0 | N21: 0 | O21: 0 | P21: 0 | Q21: 0 | R21: 0 | S21: 0 | T21: 0 | U21: 0 | V21: 0 | W21: 0 | X21: 0 | Y21: 0 | Z21: 0 | AA21: =-U20 -> -140859.01 | AB21: =-V20 -> -160302.53 | AC21: =-W20 -> -181493.43 | AD21: =-X20 -> -180456.38 | AE21: =-Y20 -> -160762.34 | AF21: =-Z20 -> -187250.97 | AG21: =-AA20 -> -190782.79 | AH21: =-AB20 -> -195727.33 | ... AL21: =-AF20 -> 0 | AN21: 0 | AO21: 0 | AP21: 0 | AQ21: 0 | AR21: 0 | AS21: 0 | AT21: 0 | AU21: =-AS20 -> 482654.97 | AV21: =-AT20 -> 528469.7 | AW21: =-AU20 -> 539366.21 | AX21: =-AV20 -> 178504.25 | AZ21: =SUM(AN21:AX21) -> 1728995.1
AN26: =AN7/SUM($AZ$7,$AZ$15) -> 0.001045977 | AO26: =AO7/SUM($AZ$7,$AZ$15) -> 0.027309516 | AP26: =AP7/SUM($AZ$7,$AZ$15) -> 0.040518141 | AQ26: =AQ7/SUM($AZ$7,$AZ$15) -> 0.0087825763 | AR26: =AR7/SUM($AZ$7,$AZ$15) -> 0.019002553 | AS26: =AS15/SUM($AZ$7,$AZ$15) -> 0.25217083 | AT26: =AT15/SUM($AZ$7,$AZ$15) -> 0.27610747 | AU26: =AU15/SUM($AZ$7,$AZ$15) -> 0.28180053 | AV26: =AV15/SUM($AZ$7,$AZ$15) -> 0.093262408

Sheet Model - Preopening & Fees
B2: Florence - Preopening Budget | F2: =SUMIFS(F$11:F$162,$A$11:$A$162,1) -> 1104145 | G2: =SUMIFS(G$11:G$162,$A$11:$A$162,1) -> 307666.22 | H2: =SUMIFS(H$11:H$162,$A$11:$A$162,1) -> 798480.02
B4: Actuals To Date | J4: 46203
B5: Period | L5: 0 | M5: 0 | N5: 0 | O5: =L5+1 -> 1 | P5: =M5+1 -> 1 | Q5: =N5+1 -> 1 | R5: =O5+1 -> 2 | S5: =P5+1 -> 2 | T5: =Q5+1 -> 2 | U5: =R5+1 -> 3 | V5: =S5+1 -> 3 | ... AR5: =AO5+1 -> 10 | AT5: 0 | AU5: =AT5+1 -> 1 | AV5: =AU5+1 -> 2 | AW5: =AV5+1 -> 3 | AX5: =AW5+1 -> 4 | AY5: =AX5+1 -> 5 | AZ5: =AY5+1 -> 6 | BA5: =AZ5+1 -> 7 | BB5: =BA5+1 -> 8 | ... BD5: =BC5+1 -> 10
B6: BoP | L6: 45658 | M6: =L7+1 -> 45689 | N6: =M7+1 -> 45717 | O6: =N7+1 -> 45748 | P6: =O7+1 -> 45778 | Q6: =P7+1 -> 45809 | R6: =Q7+1 -> 45839 | S6: =R7+1 -> 45870 | T6: =S7+1 -> 45901 | ... AR6: =AQ7+1 -> 46631 | AT6: 45658 | AU6: =AT7+1 -> 45748 | AV6: =AU7+1 -> 45839 | AW6: =AV7+1 -> 45931 | AX6: =AW7+1 -> 46023 | AY6: =AX7+1 -> 46113 | AZ6: =AY7+1 -> 46204 | BA6: =AZ7+1 -> 46296 | BB6: =BA7+1 -> 46388 | ... BD6: =BC7+1 -> 46569
B7: EoP | J7: Total | L7: 45688 | M7: =EOMONTH(L7,1) -> 45716 | N7: =EOMONTH(M7,1) -> 45747 | O7: =EOMONTH(N7,1) -> 45777 | P7: =EOMONTH(O7,1) -> 45808 | Q7: =EOMONTH(P7,1) -> 45838 | R7: =EOMONTH(Q7,1) -> 45869 | S7: =EOMONTH(R7,1) -> 45900 | T7: =EOMONTH(S7,1) -> 45930 | ... AR7: =EOMONTH(AQ7,1) -> 46660 | AT7: 45747 | AU7: =EOMONTH(AT7,3) -> 45838 | AV7: =EOMONTH(AU7,3) -> 45930 | AW7: =EOMONTH(AV7,3) -> 46022 | AX7: =EOMONTH(AW7,3) -> 46112 | AY7: =EOMONTH(AX7,3) -> 46203 | AZ7: =EOMONTH(AY7,3) -> 46295 | BA7: =EOMONTH(AZ7,3) -> 46387 | BB7: =EOMONTH(BA7,3) -> 46477 | ... BD7: =EOMONTH(BC7,3) -> 46660
B9: Marketing
B11: Budget | C11: Description | D11: Bucket | E11: Owner | F11: Budget | G11: Spent | H11: Remaining
B13: PR & Communications
A14: 1 | B14: Communication Plan (with Local Agency) | D14: Marketing | E14: Aniek | F14: 20000 | G14: =SUMIFS($L14:$AR14,$L$7:$AR$7,"<="&$J$4) -> 0 | H14: =J14-G14 -> 20000 | J14: =SUM(L14:AR14) -> 20000 | L14: =SUMIFS('Invoices - Preopening'!$I$20:$I$299,'Invoices - Preopening'!$H$20:$H$299,">="&L$6,'Invoices - Preopening'!$H$20:$H$299,"<="&L$7,'Invoices - Preopening'!$C$20:$C$299,'Model - Preopening & Fees'!$B14) -> 0 | M14: =SUMIFS('Invoices - Preopening'!$I$20:$I$299,'Invoices - Preopening'!$H$20:$H$299,">="&M$6,'Invoices - Preopening'!$H$20:$H$299,"<="&M$7,'Invoices - Preopening'!$C$20:$C$299,'Model - Preopening & Fees'!$B14) -> 0 | N14: =SUMIFS('Invoices - Preopening'!$I$20:$I$299,'Invoices - Preopening'!$H$20:$H$299,">="&N$6,'Invoices - Preopening'!$H$20:$H$299,"<="&N$7,'Invoices - Preopening'!$C$20:$C$299,'Model - Preopening & Fees'!$B14) -> 0 | O14: =SUMIFS('Invoices - Preopening'!$I$20:$I$299,'Invoices - Preopening'!$H$20:$H$299,">="&O$6,'Invoices - Preopening'!$H$20:$H$299,"<="&O$7,'Invoices - Preopening'!$C$20:$C$299,'Model - Preopening & Fees'!$B14) -> 0 | P14: =SUMIFS('Invoices - Preopening'!$I$20:$I$299,'Invoices - Preopening'!$H$20:$H$299,">="&P$6,'Invoices - Preopening'!$H$20:$H$299,"<="&P$7,'Invoices - Preopening'!$C$20:$C$299,'Model - Preopening & Fees'!$B14) -> 0 | Q14: =SUMIFS('Invoices - Preopening'!$I$20:$I$299,'Invoices - Preopening'!$H$20:$H$299,">="&Q$6,'Invoices - Preopening'!$H$20:$H$299,"<="&Q$7,'Invoices - Preopening'!$C$20:$C$299,'Model - Preopening & Fees'!$B14) -> 0 | R14: =SUMIFS('Invoices - Preopening'!$I$20:$I$299,'Invoices - Preopening'!$H$20:$H$299,">="&R$6,'Invoices - Preopening'!$H$20:$H$299,"<="&R$7,'Invoices - Preopening'!$C$20:$C$299,'Model - Preopening & Fees'!$B14) -> 0 | S14: =SUMIFS('Invoices - Preopening'!$I$20:$I$299,'Invoices - Preopening'!$H$20:$H$299,">="&S$6,'Invoices - Preopening'!$H$20:$H$299,"<="&S$7,'Invoices - Preopening'!$C$20:$C$299,'Model - Preopening & Fees'!$B14) -> 0 | ... AC14: =SUMIFS('Invoices - Preopening'!$I$20:$I$299,'Invoices - Preopening'!$H$20:$H$299,">="&AC$6,'Invoices - Preopening'!$H$20:$H$299,"<="&AC$7,'Invoices - Preopening'!$C$20:$C$299,'Model - Preopening & Fees'!$B14) -> 0 | AD14: 20000 | AE14: 0 | AF14: 0 | AG14: 0 | AH14: 0 | AI14: 0 | AJ14: 0 | AK14: 0 | AL14: 0 | AM14: 0 | AN14: 0 | AO14: 0 | AP14: 0 | AQ14: 0 | AR14: 0 | AT14: =-SUMIFS($L14:$AR14,$L$5:$AR$5,AT$5) -> 0 | AU14: =-SUMIFS($L14:$AR14,$L$5:$AR$5,AU$5) -> 0 | AV14: =-SUMIFS($L14:$AR14,$L$5:$AR$5,AV$5) -> 0 | AW14: =-SUMIFS($L14:$AR14,$L$5:$AR$5,AW$5) -> 0 | AX14: =-SUMIFS($L14:$AR14,$L$5:$AR$5,AX$5) -> 0 | AY14: =-SUMIFS($L14:$AR14,$L$5:$AR$5,AY$5) -> 0 | AZ14: =-SUMIFS($L14:$AR14,$L$5:$AR$5,AZ$5) -> -20000 | BA14: =-SUMIFS($L14:$AR14,$L$5:$AR$5,BA$5) -> 0 | ... BD14: =-SUMIFS($L14:$AR14,$L$5:$AR$5,BD$5) -> 0 | BF14: =SUM(AT14:BD14) -> -20000
A15: 1 | B15: PR (with Local Agency) year retainer | D15: Marketing | E15: Aniek | F15: 26500 | G15: =SUMIFS($L15:$AR15,$L$7:$AR$7,"<="&$J$4) -> 0 | H15: =J15-G15 -> 14000 | J15: =SUM(L15:AR15) -> 14000 | L15: =SUMIFS('Invoices - Preopening'!$I$20:$I$299,'Invoices - Preopening'!$H$20:$H$299,">="&L$6,'Invoices - Preopening'!$H$20:$H$299,"<="&L$7,'Invoices - Preopening'!$C$20:$C$299,'Model - Preopening & Fees'!$B15) -> 0 | M15: =SUMIFS('Invoices - Preopening'!$I$20:$I$299,'Invoices - Preopening'!$H$20:$H$299,">="&M$6,'Invoices - Preopening'!$H$20:$H$299,"<="&M$7,'Invoices - Preopening'!$C$20:$C$299,'Model - Preopening & Fees'!$B15) -> 0 | N15: =SUMIFS('Invoices - Preopening'!$I$20:$I$299,'Invoices - Preopening'!$H$20:$H$299,">="&N$6,'Invoices - Preopening'!$H$20:$H$299,"<="&N$7,'Invoices - Preopening'!$C$20:$C$299,'Model - Preopening & Fees'!$B15) -> 0 | O15: =SUMIFS('Invoices - Preopening'!$I$20:$I$299,'Invoices - Preopening'!$H$20:$H$299,">="&O$6,'Invoices - Preopening'!$H$20:$H$299,"<="&O$7,'Invoices - Preopening'!$C$20:$C$299,'Model - Preopening & Fees'!$B15) -> 0 | P15: =SUMIFS('Invoices - Preopening'!$I$20:$I$299,'Invoices - Preopening'!$H$20:$H$299,">="&P$6,'Invoices - Preopening'!$H$20:$H$299,"<="&P$7,'Invoices - Preopening'!$C$20:$C$299,'Model - Preopening & Fees'!$B15) -> 0 | Q15: =SUMIFS('Invoices - Preopening'!$I$20:$I$299,'Invoices - Preopening'!$H$20:$H$299,">="&Q$6,'Invoices - Preopening'!$H$20:$H$299,"<="&Q$7,'Invoices - Preopening'!$C$20:$C$299,'Model - Preopening & Fees'!$B15) -> 0 | R15: =SUMIFS('Invoices - Preopening'!$I$20:$I$299,'Invoices - Preopening'!$H$20:$H$299,">="&R$6,'Invoices - Preopening'!$H$20:$H$299,"<="&R$7,'Invoices - Preopening'!$C$20:$C$299,'Model - Preopening & Fees'!$B15) -> 0 | S15: =SUMIFS('Invoices - Preopening'!$I$20:$I$299,'Invoices - Preopening'!$H$20:$H$299,">="&S$6,'Invoices - Preopening'!$H$20:$H$299,"<="&S$7,'Invoices - Preopening'!$C$20:$C$299,'Model - Preopening & Fees'!$B15) -> 0 | ... AC15: =SUMIFS('Invoices - Preopening'!$I$20:$I$299,'Invoices - Preopening'!$H$20:$H$299,">="&AC$6,'Invoices - Preopening'!$H$20:$H$299,"<="&AC$7,'Invoices - Preopening'!$C$20:$C$299,'Model - Preopening & Fees'!$B15) -> 0 | AD15: 0 | AE15: 2000 | AF15: 2000 | AG15: 2000 | AH15: 2000 | AI15: 2000 | AJ15: 2000 | AK15: 2000 | AL15: 0 | AM15: 0 | AN15: 0 | AO15: 0 | AP15: 0 | AQ15: 0 | AR15: 0 | AT15: =-SUMIFS($L15:$AR15,$L$5:$AR$5,AT$5) -> 0 | AU15: =-SUMIFS($L15:$AR15,$L$5:$AR$5,AU$5) -> 0 | AV15: =-SUMIFS($L15:$AR15,$L$5:$AR$5,AV$5) -> 0 | AW15: =-SUMIFS($L15:$AR15,$L$5:$AR$5,AW$5) -> 0 | AX15: =-SUMIFS($L15:$AR15,$L$5:$AR$5,AX$5) -> 0 | AY15: =-SUMIFS($L15:$AR15,$L$5:$AR$5,AY$5) -> 0 | AZ15: =-SUMIFS($L15:$AR15,$L$5:$AR$5,AZ$5) -> -4000 | BA15: =-SUMIFS($L15:$AR15,$L$5:$AR$5,BA$5) -> -6000 | ... BD15: =-SUMIFS($L15:$AR15,$L$5:$AR$5,BD$5) -> 0 | BF15: =SUM(AT15:BD15) -> -14000
B17: Photo & Video
A18: 1 | B18: Photoshoot September - Mock Up Rooms | D18: Marketing | E18: Aniek | F18: 3000 | G18: =SUMIFS($L18:$AR18,$L$7:$AR$7,"<="&$J$4) -> 1000 | H18: =J18-G18 -> 2000 | J18: =SUM(L18:AR18) -> 3000 | L18: =SUMIFS('Invoices - Preopening'!$I$20:$I$299,'Invoices - Preopening'!$H$20:$H$299,">="&L$6,'Invoices - Preopening'!$H$20:$H$299,"<="&L$7,'Invoices - Preopening'!$C$20:$C$299,'Model - Preopening & Fees'!$B18) -> 0 | M18: =SUMIFS('Invoices - Preopening'!$I$20:$I$299,'Invoices - Preopening'!$H$20:$H$299,">="&M$6,'Invoices - Preopening'!$H$20:$H$299,"<="&M$7,'Invoices - Preopening'!$C$20:$C$299,'Model - Preopening & Fees'!$B18) -> 0 | N18: =SUMIFS('Invoices - Preopening'!$I$20:$I$299,'Invoices - Preopening'!$H$20:$H$299,">="&N$6,'Invoices - Preopening'!$H$20:$H$299,"<="&N$7,'Invoices - Preopening'!$C$20:$C$299,'Model - Preopening & Fees'!$B18) -> 0 | O18: =SUMIFS('Invoices - Preopening'!$I$20:$I$299,'Invoices - Preopening'!$H$20:$H$299,">="&O$6,'Invoices - Preopening'!$H$20:$H$299,"<="&O$7,'Invoices - Preopening'!$C$20:$C$299,'Model - Preopening & Fees'!$B18) -> 0 | P18: =SUMIFS('Invoices - Preopening'!$I$20:$I$299,'Invoices - Preopening'!$H$20:$H$299,">="&P$6,'Invoices - Preopening'!$H$20:$H$299,"<="&P$7,'Invoices - Preopening'!$C$20:$C$299,'Model - Preopening & Fees'!$B18) -> 0 | Q18: =SUMIFS('Invoices - Preopening'!$I$20:$I$299,'Invoices - Preopening'!$H$20:$H$299,">="&Q$6,'Invoices - Preopening'!$H$20:$H$299,"<="&Q$7,'Invoices - Preopening'!$C$20:$C$299,'Model - Preopening & Fees'!$B18) -> 0 | R18: =SUMIFS('Invoices - Preopening'!$I$20:$I$299,'Invoices - Preopening'!$H$20:$H$299,">="&R$6,'Invoices - Preopening'!$H$20:$H$299,"<="&R$7,'Invoices - Preopening'!$C$20:$C$299,'Model - Preopening & Fees'!$B18) -> 0 | S18: =SUMIFS('Invoices - Preopening'!$I$20:$I$299,'Invoices - Preopening'!$H$20:$H$299,">="&S$6,'Invoices - Preopening'!$H$20:$H$299,"<="&S$7,'Invoices - Preopening'!$C$20:$C$299,'Model - Preopening & Fees'!$B18) -> 0 | ... AC18: =SUMIFS('Invoices - Preopening'!$I$20:$I$299,'Invoices - Preopening'!$H$20:$H$299,">="&AC$6,'Invoices - Preopening'!$H$20:$H$299,"<="&AC$7,'Invoices - Preopening'!$C$20:$C$299,'Model - Preopening & Fees'!$B18) -> 0 | AD18: 0 | AE18: 0 | AF18: 2000 | AG18: 0 | AH18: 0 | AI18: 0 | AJ18: 0 | AK18: 0 | AL18: 0 | AM18: 0 | AN18: 0 | AO18: 0 | AP18: 0 | AQ18: 0 | AR18: 0 | AT18: =-SUMIFS($L18:$AR18,$L$5:$AR$5,AT$5) -> 0 | AU18: =-SUMIFS($L18:$AR18,$L$5:$AR$5,AU$5) -> 0 | AV18: =-SUMIFS($L18:$AR18,$L$5:$AR$5,AV$5) -> 0 | AW18: =-SUMIFS($L18:$AR18,$L$5:$AR$5,AW$5) -> -1000 | AX18: =-SUMIFS($L18:$AR18,$L$5:$AR$5,AX$5) -> 0 | AY18: =-SUMIFS($L18:$AR18,$L$5:$AR$5,AY$5) -> 0 | AZ18: =-SUMIFS($L18:$AR18,$L$5:$AR$5,AZ$5) -> -2000 | BA18: =-SUMIFS($L18:$AR18,$L$5:$AR$5,BA$5) -> 0 | ... BD18: =-SUMIFS($L18:$AR18,$L$5:$AR$5,BD$5) -> 0 | BF18: =SUM(AT18:BD18) -> -3000
A19: 1 | B19: Photoshoot Full February | D19: Marketing | E19: Aniek | F19: 4000 | G19: =SUMIFS($L19:$AR19,$L$7:$AR$7,"<="&$J$4) -> 0 | H19: =J19-G19 -> 4000 | J19: =SUM(L19:AR19) -> 4000 | L19: =SUMIFS('Invoices - Preopening'!$I$20:$I$299,'Invoices - Preopening'!$H$20:$H$299,">="&L$6,'Invoices - Preopening'!$H$20:$H$299,"<="&L$7,'Invoices - Preopening'!$C$20:$C$299,'Model - Preopening & Fees'!$B19) -> 0 | M19: =SUMIFS('Invoices - Preopening'!$I$20:$I$299,'Invoices - Preopening'!$H$20:$H$299,">="&M$6,'Invoices - Preopening'!$H$20:$H$299,"<="&M$7,'Invoices - Preopening'!$C$20:$C$299,'Model - Preopening & Fees'!$B19) -> 0 | N19: =SUMIFS('Invoices - Preopening'!$I$20:$I$299,'Invoices - Preopening'!$H$20:$H$299,">="&N$6,'Invoices - Preopening'!$H$20:$H$299,"<="&N$7,'Invoices - Preopening'!$C$20:$C$299,'Model - Preopening & Fees'!$B19) -> 0 | O19: =SUMIFS('Invoices - Preopening'!$I$20:$I$299,'Invoices - Preopening'!$H$20:$H$299,">="&O$6,'Invoices - Preopening'!$H$20:$H$299,"<="&O$7,'Invoices - Preopening'!$C$20:$C$299,'Model - Preopening & Fees'!$B19) -> 0 | P19: =SUMIFS('Invoices - Preopening'!$I$20:$I$299,'Invoices - Preopening'!$H$20:$H$299,">="&P$6,'Invoices - Preopening'!$H$20:$H$299,"<="&P$7,'Invoices - Preopening'!$C$20:$C$299,'Model - Preopening & Fees'!$B19) -> 0 | Q19: =SUMIFS('Invoices - Preopening'!$I$20:$I$299,'Invoices - Preopening'!$H$20:$H$299,">="&Q$6,'Invoices - Preopening'!$H$20:$H$299,"<="&Q$7,'Invoices - Preopening'!$C$20:$C$299,'Model - Preopening & Fees'!$B19) -> 0 | R19: =SUMIFS('Invoices - Preopening'!$I$20:$I$299,'Invoices - Preopening'!$H$20:$H$299,">="&R$6,'Invoices - Preopening'!$H$20:$H$299,"<="&R$7,'Invoices - Preopening'!$C$20:$C$299,'Model - Preopening & Fees'!$B19) -> 0 | S19: =SUMIFS('Invoices - Preopening'!$I$20:$I$299,'Invoices - Preopening'!$H$20:$H$299,">="&S$6,'Invoices - Preopening'!$H$20:$H$299,"<="&S$7,'Invoices - Preopening'!$C$20:$C$299,'Model - Preopening & Fees'!$B19) -> 0 | ... AC19: =SUMIFS('Invoices - Preopening'!$I$20:$I$299,'Invoices - Preopening'!$H$20:$H$299,">="&AC$6,'Invoices - Preopening'!$H$20:$H$299,"<="&AC$7,'Invoices - Preopening'!$C$20:$C$299,'Model - Preopening & Fees'!$B19) -> 0 | AD19: 0 | AE19: 0 | AF19: 0 | AG19: 0 | AH19: 0 | AI19: 0 | AJ19: 0 | AK19: 4000 | AL19: 0 | AM19: 0 | AN19: 0 | AO19: 0 | AP19: 0 | AQ19: 0 | AR19: 0 | AT19: =-SUMIFS($L19:$AR19,$L$5:$AR$5,AT$5) -> 0 | AU19: =-SUMIFS($L19:$AR19,$L$5:$AR$5,AU$5) -> 0 | AV19: =-SUMIFS($L19:$AR19,$L$5:$AR$5,AV$5) -> 0 | AW19: =-SUMIFS($L19:$AR19,$L$5:$AR$5,AW$5) -> 0 | AX19: =-SUMIFS($L19:$AR19,$L$5:$AR$5,AX$5) -> 0 | AY19: =-SUMIFS($L19:$AR19,$L$5:$AR$5,AY$5) -> 0 | AZ19: =-SUMIFS($L19:$AR19,$L$5:$AR$5,AZ$5) -> 0 | BA19: =-SUMIFS($L19:$AR19,$L$5:$AR$5,BA$5) -> 0 | ... BD19: =-SUMIFS($L19:$AR19,$L$5:$AR$5,BD$5) -> 0 | BF19: =SUM(AT19:BD19) -> -4000
B20: Videoshoot (included in Diginauts scope) | D20: Marketing | E20: Aniek | F20: 0 | G20: =SUMIFS($L20:$AR20,$L$7:$AR$7,"<="&$J$4) -> 0 | H20: =J20-G20 -> 0 | J20: =SUM(L20:AR20) -> 0 | L20: =SUMIFS('Invoices - Preopening'!$I$20:$I$299,'Invoices - Preopening'!$H$20:$H$299,">="&L$6,'Invoices - Preopening'!$H$20:$H$299,"<="&L$7,'Invoices - Preopening'!$C$20:$C$299,'Model - Preopening & Fees'!$B20) -> 0 | M20: =SUMIFS('Invoices - Preopening'!$I$20:$I$299,'Invoices - Preopening'!$H$20:$H$299,">="&M$6,'Invoices - Preopening'!$H$20:$H$299,"<="&M$7,'Invoices - Preopening'!$C$20:$C$299,'Model - Preopening & Fees'!$B20) -> 0 | N20: =SUMIFS('Invoices - Preopening'!$I$20:$I$299,'Invoices - Preopening'!$H$20:$H$299,">="&N$6,'Invoices - Preopening'!$H$20:$H$299,"<="&N$7,'Invoices - Preopening'!$C$20:$C$299,'Model - Preopening & Fees'!$B20) -> 0 | O20: =SUMIFS('Invoices - Preopening'!$I$20:$I$299,'Invoices - Preopening'!$H$20:$H$299,">="&O$6,'Invoices - Preopening'!$H$20:$H$299,"<="&O$7,'Invoices - Preopening'!$C$20:$C$299,'Model - Preopening & Fees'!$B20) -> 0 | P20: =SUMIFS('Invoices - Preopening'!$I$20:$I$299,'Invoices - Preopening'!$H$20:$H$299,">="&P$6,'Invoices - Preopening'!$H$20:$H$299,"<="&P$7,'Invoices - Preopening'!$C$20:$C$299,'Model - Preopening & Fees'!$B20) -> 0 | Q20: =SUMIFS('Invoices - Preopening'!$I$20:$I$299,'Invoices - Preopening'!$H$20:$H$299,">="&Q$6,'Invoices - Preopening'!$H$20:$H$299,"<="&Q$7,'Invoices - Preopening'!$C$20:$C$299,'Model - Preopening & Fees'!$B20) -> 0 | R20: =SUMIFS('Invoices - Preopening'!$I$20:$I$299,'Invoices - Preopening'!$H$20:$H$299,">="&R$6,'Invoices - Preopening'!$H$20:$H$299,"<="&R$7,'Invoices - Preopening'!$C$20:$C$299,'Model - Preopening & Fees'!$B20) -> 0 | S20: =SUMIFS('Invoices - Preopening'!$I$20:$I$299,'Invoices - Preopening'!$H$20:$H$299,">="&S$6,'Invoices - Preopening'!$H$20:$H$299,"<="&S$7,'Invoices - Preopening'!$C$20:$C$299,'Model - Preopening & Fees'!$B20) -> 0 | ... AC20: =SUMIFS('Invoices - Preopening'!$I$20:$I$299,'Invoices - Preopening'!$H$20:$H$299,">="&AC$6,'Invoices - Preopening'!$H$20:$H$299,"<="&AC$7,'Invoices - Preopening'!$C$20:$C$299,'Model - Preopening & Fees'!$B20) -> 0 | AD20: 0 | AE20: 0 | AF20: 0 | AG20: 0 | AH20: 0 | AI20: 0 | AJ20: 0 | AK20: 0 | AL20: 0 | AM20: 0 | AN20: 0 | AO20: 0 | AP20: 0 | AQ20: 0 | AR20: 0
A21: 1 | B21: Videoshoot Lifestyle February | D21: Marketing | E21: Aniek | F21: 4000 | G21: =SUMIFS($L21:$AR21,$L$7:$AR$7,"<="&$J$4) -> 0 | H21: =J21-G21 -> 4000 | J21: =SUM(L21:AR21) -> 4000 | L21: =SUMIFS('Invoices - Preopening'!$I$20:$I$299,'Invoices - Preopening'!$H$20:$H$299,">="&L$6,'Invoices - Preopening'!$H$20:$H$299,"<="&L$7,'Invoices - Preopening'!$C$20:$C$299,'Model - Preopening & Fees'!$B21) -> 0 | M21: =SUMIFS('Invoices - Preopening'!$I$20:$I$299,'Invoices - Preopening'!$H$20:$H$299,">="&M$6,'Invoices - Preopening'!$H$20:$H$299,"<="&M$7,'Invoices - Preopening'!$C$20:$C$299,'Model - Preopening & Fees'!$B21) -> 0 | N21: =SUMIFS('Invoices - Preopening'!$I$20:$I$299,'Invoices - Preopening'!$H$20:$H$299,">="&N$6,'Invoices - Preopening'!$H$20:$H$299,"<="&N$7,'Invoices - Preopening'!$C$20:$C$299,'Model - Preopening & Fees'!$B21) -> 0 | O21: =SUMIFS('Invoices - Preopening'!$I$20:$I$299,'Invoices - Preopening'!$H$20:$H$299,">="&O$6,'Invoices - Preopening'!$H$20:$H$299,"<="&O$7,'Invoices - Preopening'!$C$20:$C$299,'Model - Preopening & Fees'!$B21) -> 0 | P21: =SUMIFS('Invoices - Preopening'!$I$20:$I$299,'Invoices - Preopening'!$H$20:$H$299,">="&P$6,'Invoices - Preopening'!$H$20:$H$299,"<="&P$7,'Invoices - Preopening'!$C$20:$C$299,'Model - Preopening & Fees'!$B21) -> 0 | Q21: =SUMIFS('Invoices - Preopening'!$I$20:$I$299,'Invoices - Preopening'!$H$20:$H$299,">="&Q$6,'Invoices - Preopening'!$H$20:$H$299,"<="&Q$7,'Invoices - Preopening'!$C$20:$C$299,'Model - Preopening & Fees'!$B21) -> 0 | R21: =SUMIFS('Invoices - Preopening'!$I$20:$I$299,'Invoices - Preopening'!$H$20:$H$299,">="&R$6,'Invoices - Preopening'!$H$20:$H$299,"<="&R$7,'Invoices - Preopening'!$C$20:$C$299,'Model - Preopening & Fees'!$B21) -> 0 | S21: =SUMIFS('Invoices - Preopening'!$I$20:$I$299,'Invoices - Preopening'!$H$20:$H$299,">="&S$6,'Invoices - Preopening'!$H$20:$H$299,"<="&S$7,'Invoices - Preopening'!$C$20:$C$299,'Model - Preopening & Fees'!$B21) -> 0 | ... AC21: =SUMIFS('Invoices - Preopening'!$I$20:$I$299,'Invoices - Preopening'!$H$20:$H$299,">="&AC$6,'Invoices - Preopening'!$H$20:$H$299,"<="&AC$7,'Invoices - Preopening'!$C$20:$C$299,'Model - Preopening & Fees'!$B21) -> 0 | AD21: 0 | AE21: 0 | AF21: 0 | AG21: 0 | AH21: 0 | AI21: 0 | AJ21: 0 | AK21: 4000 | AL21: 0 | AM21: 0 | AN21: 0 | AO21: 0 | AP21: 0 | AQ21: 0 | AR21: 0
A22: 1 | B22: Photoshoot Lifestyle & City February | D22: Marketing | E22: Aniek | F22: 4000 | G22: =SUMIFS($L22:$AR22,$L$7:$AR$7,"<="&$J$4) -> 0 | H22: =J22-G22 -> 4000 | J22: =SUM(L22:AR22) -> 4000 | L22: =SUMIFS('Invoices - Preopening'!$I$20:$I$299,'Invoices - Preopening'!$H$20:$H$299,">="&L$6,'Invoices - Preopening'!$H$20:$H$299,"<="&L$7,'Invoices - Preopening'!$C$20:$C$299,'Model - Preopening & Fees'!$B22) -> 0 | M22: =SUMIFS('Invoices - Preopening'!$I$20:$I$299,'Invoices - Preopening'!$H$20:$H$299,">="&M$6,'Invoices - Preopening'!$H$20:$H$299,"<="&M$7,'Invoices - Preopening'!$C$20:$C$299,'Model - Preopening & Fees'!$B22) -> 0 | N22: =SUMIFS('Invoices - Preopening'!$I$20:$I$299,'Invoices - Preopening'!$H$20:$H$299,">="&N$6,'Invoices - Preopening'!$H$20:$H$299,"<="&N$7,'Invoices - Preopening'!$C$20:$C$299,'Model - Preopening & Fees'!$B22) -> 0 | O22: =SUMIFS('Invoices - Preopening'!$I$20:$I$299,'Invoices - Preopening'!$H$20:$H$299,">="&O$6,'Invoices - Preopening'!$H$20:$H$299,"<="&O$7,'Invoices - Preopening'!$C$20:$C$299,'Model - Preopening & Fees'!$B22) -> 0 | P22: =SUMIFS('Invoices - Preopening'!$I$20:$I$299,'Invoices - Preopening'!$H$20:$H$299,">="&P$6,'Invoices - Preopening'!$H$20:$H$299,"<="&P$7,'Invoices - Preopening'!$C$20:$C$299,'Model - Preopening & Fees'!$B22) -> 0 | Q22: =SUMIFS('Invoices - Preopening'!$I$20:$I$299,'Invoices - Preopening'!$H$20:$H$299,">="&Q$6,'Invoices - Preopening'!$H$20:$H$299,"<="&Q$7,'Invoices - Preopening'!$C$20:$C$299,'Model - Preopening & Fees'!$B22) -> 0 | R22: =SUMIFS('Invoices - Preopening'!$I$20:$I$299,'Invoices - Preopening'!$H$20:$H$299,">="&R$6,'Invoices - Preopening'!$H$20:$H$299,"<="&R$7,'Invoices - Preopening'!$C$20:$C$299,'Model - Preopening & Fees'!$B22) -> 0 | S22: =SUMIFS('Invoices - Preopening'!$I$20:$I$299,'Invoices - Preopening'!$H$20:$H$299,">="&S$6,'Invoices - Preopening'!$H$20:$H$299,"<="&S$7,'Invoices - Preopening'!$C$20:$C$299,'Model - Preopening & Fees'!$B22) -> 0 | ... AC22: =SUMIFS('Invoices - Preopening'!$I$20:$I$299,'Invoices - Preopening'!$H$20:$H$299,">="&AC$6,'Invoices - Preopening'!$H$20:$H$299,"<="&AC$7,'Invoices - Preopening'!$C$20:$C$299,'Model - Preopening & Fees'!$B22) -> 0 | AD22: 0 | AE22: 0 | AF22: 0 | AG22: 0 | AH22: 0 | AI22: 0 | AJ22: 0 | AK22: 4000 | AL22: 0 | AM22: 0 | AN22: 0 | AO22: 0 | AP22: 0 | AQ22: 0 | AR22: 0
B24: F&B - Il Solito Branding
A25: 1 | B25: Visual Identity Development (Logo, Fonts, Guidelines) | D25: Marketing | E25: Aniek | F25: 15000 | G25: =SUMIFS($L25:$AR25,$L$7:$AR$7,"<="&$J$4) -> 0 | H25: =J25-G25 -> 15000 | J25: =SUM(L25:AR25) -> 15000 | L25: =SUMIFS('Invoices - Preopening'!$I$20:$I$299,'Invoices - Preopening'!$H$20:$H$299,">="&L$6,'Invoices - Preopening'!$H$20:$H$299,"<="&L$7,'Invoices - Preopening'!$C$20:$C$299,'Model - Preopening & Fees'!$B25) -> 0 | M25: =SUMIFS('Invoices - Preopening'!$I$20:$I$299,'Invoices - Preopening'!$H$20:$H$299,">="&M$6,'Invoices - Preopening'!$H$20:$H$299,"<="&M$7,'Invoices - Preopening'!$C$20:$C$299,'Model - Preopening & Fees'!$B25) -> 0 | N25: =SUMIFS('Invoices - Preopening'!$I$20:$I$299,'Invoices - Preopening'!$H$20:$H$299,">="&N$6,'Invoices - Preopening'!$H$20:$H$299,"<="&N$7,'Invoices - Preopening'!$C$20:$C$299,'Model - Preopening & Fees'!$B25) -> 0 | O25: =SUMIFS('Invoices - Preopening'!$I$20:$I$299,'Invoices - Preopening'!$H$20:$H$299,">="&O$6,'Invoices - Preopening'!$H$20:$H$299,"<="&O$7,'Invoices - Preopening'!$C$20:$C$299,'Model - Preopening & Fees'!$B25) -> 0 | P25: =SUMIFS('Invoices - Preopening'!$I$20:$I$299,'Invoices - Preopening'!$H$20:$H$299,">="&P$6,'Invoices - Preopening'!$H$20:$H$299,"<="&P$7,'Invoices - Preopening'!$C$20:$C$299,'Model - Preopening & Fees'!$B25) -> 0 | Q25: =SUMIFS('Invoices - Preopening'!$I$20:$I$299,'Invoices - Preopening'!$H$20:$H$299,">="&Q$6,'Invoices - Preopening'!$H$20:$H$299,"<="&Q$7,'Invoices - Preopening'!$C$20:$C$299,'Model - Preopening & Fees'!$B25) -> 0 | R25: =SUMIFS('Invoices - Preopening'!$I$20:$I$299,'Invoices - Preopening'!$H$20:$H$299,">="&R$6,'Invoices - Preopening'!$H$20:$H$299,"<="&R$7,'Invoices - Preopening'!$C$20:$C$299,'Model - Preopening & Fees'!$B25) -> 0 | S25: =SUMIFS('Invoices - Preopening'!$I$20:$I$299,'Invoices - Preopening'!$H$20:$H$299,">="&S$6,'Invoices - Preopening'!$H$20:$H$299,"<="&S$7,'Invoices - Preopening'!$C$20:$C$299,'Model - Preopening & Fees'!$B25) -> 0 | ... AC25: =SUMIFS('Invoices - Preopening'!$I$20:$I$299,'Invoices - Preopening'!$H$20:$H$299,">="&AC$6,'Invoices - Preopening'!$H$20:$H$299,"<="&AC$7,'Invoices - Preopening'!$C$20:$C$299,'Model - Preopening & Fees'!$B25) -> 0 | AD25: 7500 | AE25: 7500 | AF25: 0 | AG25: 0 | AH25: 0 | AI25: 0 | AJ25: 0 | AK25: 0 | AL25: 0 | AM25: 0 | AN25: 0 | AO25: 0 | AP25: 0 | AQ25: 0 | AR25: 0 | AT25: =-SUMIFS($L25:$AR25,$L$5:$AR$5,AT$5) -> 0 | AU25: =-SUMIFS($L25:$AR25,$L$5:$AR$5,AU$5) -> 0 | AV25: =-SUMIFS($L25:$AR25,$L$5:$AR$5,AV$5) -> 0 | AW25: =-SUMIFS($L25:$AR25,$L$5:$AR$5,AW$5) -> 0 | AX25: =-SUMIFS($L25:$AR25,$L$5:$AR$5,AX$5) -> 0 | AY25: =-SUMIFS($L25:$AR25,$L$5:$AR$5,AY$5) -> 0 | AZ25: =-SUMIFS($L25:$AR25,$L$5:$AR$5,AZ$5) -> -15000 | BA25: =-SUMIFS($L25:$AR25,$L$5:$AR$5,BA$5) -> 0 | ... BD25: =-SUMIFS($L25:$AR25,$L$5:$AR$5,BD$5) -> 0 | BF25: =SUM(AT25:BD25) -> -15000
A26: 1 | B26: Photography F&B | D26: Marketing | E26: Aniek | F26: 2000 | G26: =SUMIFS($L26:$AR26,$L$7:$AR$7,"<="&$J$4) -> 0 | H26: =J26-G26 -> 2000 | J26: =SUM(L26:AR26) -> 2000 | L26: =SUMIFS('Invoices - Preopening'!$I$20:$I$299,'Invoices - Preopening'!$H$20:$H$299,">="&L$6,'Invoices - Preopening'!$H$20:$H$299,"<="&L$7,'Invoices - Preopening'!$C$20:$C$299,'Model - Preopening & Fees'!$B26) -> 0 | M26: =SUMIFS('Invoices - Preopening'!$I$20:$I$299,'Invoices - Preopening'!$H$20:$H$299,">="&M$6,'Invoices - Preopening'!$H$20:$H$299,"<="&M$7,'Invoices - Preopening'!$C$20:$C$299,'Model - Preopening & Fees'!$B26) -> 0 | N26: =SUMIFS('Invoices - Preopening'!$I$20:$I$299,'Invoices - Preopening'!$H$20:$H$299,">="&N$6,'Invoices - Preopening'!$H$20:$H$299,"<="&N$7,'Invoices - Preopening'!$C$20:$C$299,'Model - Preopening & Fees'!$B26) -> 0 | O26: =SUMIFS('Invoices - Preopening'!$I$20:$I$299,'Invoices - Preopening'!$H$20:$H$299,">="&O$6,'Invoices - Preopening'!$H$20:$H$299,"<="&O$7,'Invoices - Preopening'!$C$20:$C$299,'Model - Preopening & Fees'!$B26) -> 0 | P26: =SUMIFS('Invoices - Preopening'!$I$20:$I$299,'Invoices - Preopening'!$H$20:$H$299,">="&P$6,'Invoices - Preopening'!$H$20:$H$299,"<="&P$7,'Invoices - Preopening'!$C$20:$C$299,'Model - Preopening & Fees'!$B26) -> 0 | Q26: =SUMIFS('Invoices - Preopening'!$I$20:$I$299,'Invoices - Preopening'!$H$20:$H$299,">="&Q$6,'Invoices - Preopening'!$H$20:$H$299,"<="&Q$7,'Invoices - Preopening'!$C$20:$C$299,'Model - Preopening & Fees'!$B26) -> 0 | R26: =SUMIFS('Invoices - Preopening'!$I$20:$I$299,'Invoices - Preopening'!$H$20:$H$299,">="&R$6,'Invoices - Preopening'!$H$20:$H$299,"<="&R$7,'Invoices - Preopening'!$C$20:$C$299,'Model - Preopening & Fees'!$B26) -> 0 | S26: =SUMIFS('Invoices - Preopening'!$I$20:$I$299,'Invoices - Preopening'!$H$20:$H$299,">="&S$6,'Invoices - Preopening'!$H$20:$H$299,"<="&S$7,'Invoices - Preopening'!$C$20:$C$299,'Model - Preopening & Fees'!$B26) -> 0 | ... AC26: =SUMIFS('Invoices - Preopening'!$I$20:$I$299,'Invoices - Preopening'!$H$20:$H$299,">="&AC$6,'Invoices - Preopening'!$H$20:$H$299,"<="&AC$7,'Invoices - Preopening'!$C$20:$C$299,'Model - Preopening & Fees'!$B26) -> 0 | AD26: 0 | AE26: 0 | AF26: 0 | AG26: 0 | AH26: 0 | AI26: 0 | AJ26: 0 | AK26: 2000 | AL26: 0 | AM26: 0 | AN26: 0 | AO26: 0 | AP26: 0 | AQ26: 0 | AR26: 0 | AT26: =-SUMIFS($L26:$AR26,$L$5:$AR$5,AT$5) -> 0 | AU26: =-SUMIFS($L26:$AR26,$L$5:$AR$5,AU$5) -> 0 | AV26: =-SUMIFS($L26:$AR26,$L$5:$AR$5,AV$5) -> 0 | AW26: =-SUMIFS($L26:$AR26,$L$5:$AR$5,AW$5) -> 0 | AX26: =-SUMIFS($L26:$AR26,$L$5:$AR$5,AX$5) -> 0 | AY26: =-SUMIFS($L26:$AR26,$L$5:$AR$5,AY$5) -> 0 | AZ26: =-SUMIFS($L26:$AR26,$L$5:$AR$5,AZ$5) -> 0 | BA26: =-SUMIFS($L26:$AR26,$L$5:$AR$5,BA$5) -> 0 | ... BD26: =-SUMIFS($L26:$AR26,$L$5:$AR$5,BD$5) -> 0 | BF26: =SUM(AT26:BD26) -> -2000
B28: Social Media
A29: 1 | B29: Influencer Fees | D29: Marketing | E29: Aniek | F29: 13200 | G29: =SUMIFS($L29:$AR29,$L$7:$AR$7,"<="&$J$4) -> 0 | H29: =J29-G29 -> 11200 | J29: =SUM(L29:AR29) -> 11200 | L29: =SUMIFS('Invoices - Preopening'!$I$20:$I$299,'Invoices - Preopening'!$H$20:$H$299,">="&L$6,'Invoices - Preopening'!$H$20:$H$299,"<="&L$7,'Invoices - Preopening'!$C$20:$C$299,'Model - Preopening & Fees'!$B29) -> 0 | M29: =SUMIFS('Invoices - Preopening'!$I$20:$I$299,'Invoices - Preopening'!$H$20:$H$299,">="&M$6,'Invoices - Preopening'!$H$20:$H$299,"<="&M$7,'Invoices - Preopening'!$C$20:$C$299,'Model - Preopening & Fees'!$B29) -> 0 | N29: =SUMIFS('Invoices - Preopening'!$I$20:$I$299,'Invoices - Preopening'!$H$20:$H$299,">="&N$6,'Invoices - Preopening'!$H$20:$H$299,"<="&N$7,'Invoices - Preopening'!$C$20:$C$299,'Model - Preopening & Fees'!$B29) -> 0 | O29: =SUMIFS('Invoices - Preopening'!$I$20:$I$299,'Invoices - Preopening'!$H$20:$H$299,">="&O$6,'Invoices - Preopening'!$H$20:$H$299,"<="&O$7,'Invoices - Preopening'!$C$20:$C$299,'Model - Preopening & Fees'!$B29) -> 0 | P29: =SUMIFS('Invoices - Preopening'!$I$20:$I$299,'Invoices - Preopening'!$H$20:$H$299,">="&P$6,'Invoices - Preopening'!$H$20:$H$299,"<="&P$7,'Invoices - Preopening'!$C$20:$C$299,'Model - Preopening & Fees'!$B29) -> 0 | Q29: =SUMIFS('Invoices - Preopening'!$I$20:$I$299,'Invoices - Preopening'!$H$20:$H$299,">="&Q$6,'Invoices - Preopening'!$H$20:$H$299,"<="&Q$7,'Invoices - Preopening'!$C$20:$C$299,'Model - Preopening & Fees'!$B29) -> 0 | R29: =SUMIFS('Invoices - Preopening'!$I$20:$I$299,'Invoices - Preopening'!$H$20:$H$299,">="&R$6,'Invoices - Preopening'!$H$20:$H$299,"<="&R$7,'Invoices - Preopening'!$C$20:$C$299,'Model - Preopening & Fees'!$B29) -> 0 | S29: =SUMIFS('Invoices - Preopening'!$I$20:$I$299,'Invoices - Preopening'!$H$20:$H$299,">="&S$6,'Invoices - Preopening'!$H$20:$H$299,"<="&S$7,'Invoices - Preopening'!$C$20:$C$299,'Model - Preopening & Fees'!$B29) -> 0 | ... AC29: =SUMIFS('Invoices - Preopening'!$I$20:$I$299,'Invoices - Preopening'!$H$20:$H$299,">="&AC$6,'Invoices - Preopening'!$H$20:$H$299,"<="&AC$7,'Invoices - Preopening'!$C$20:$C$299,'Model - Preopening & Fees'!$B29) -> 0 | AD29: 0 | AE29: 0 | AF29: 0 | AG29: 0 | AH29: 0 | AI29: 0 | AJ29: 0 | AK29: 2300 | AL29: 4400 | AM29: 4500 | AN29: 0 | AO29: 0 | AP29: 0 | AQ29: 0 | AR29: 0 | AT29: =-SUMIFS($L29:$AR29,$L$5:$AR$5,AT$5) -> 0 | AU29: =-SUMIFS($L29:$AR29,$L$5:$AR$5,AU$5) -> 0 | AV29: =-SUMIFS($L29:$AR29,$L$5:$AR$5,AV$5) -> 0 | AW29: =-SUMIFS($L29:$AR29,$L$5:$AR$5,AW$5) -> 0 | AX29: =-SUMIFS($L29:$AR29,$L$5:$AR$5,AX$5) -> 0 | AY29: =-SUMIFS($L29:$AR29,$L$5:$AR$5,AY$5) -> 0 | AZ29: =-SUMIFS($L29:$AR29,$L$5:$AR$5,AZ$5) -> 0 | BA29: =-SUMIFS($L29:$AR29,$L$5:$AR$5,BA$5) -> 0 | ... BD29: =-SUMIFS($L29:$AR29,$L$5:$AR$5,BD$5) -> 0 | BF29: =SUM(AT29:BD29) -> -11200
A30: 1 | B30: Boosting Organic Content | D30: Marketing | E30: Aniek | F30: 1600 | G30: =SUMIFS($L30:$AR30,$L$7:$AR$7,"<="&$J$4) -> 0 | H30: =J30-G30 -> 800 | J30: =SUM(L30:AR30) -> 800 | L30: =SUMIFS('Invoices - Preopening'!$I$20:$I$299,'Invoices - Preopening'!$H$20:$H$299,">="&L$6,'Invoices - Preopening'!$H$20:$H$299,"<="&L$7,'Invoices - Preopening'!$C$20:$C$299,'Model - Preopening & Fees'!$B30) -> 0 | M30: =SUMIFS('Invoices - Preopening'!$I$20:$I$299,'Invoices - Preopening'!$H$20:$H$299,">="&M$6,'Invoices - Preopening'!$H$20:$H$299,"<="&M$7,'Invoices - Preopening'!$C$20:$C$299,'Model - Preopening & Fees'!$B30) -> 0 | N30: =SUMIFS('Invoices - Preopening'!$I$20:$I$299,'Invoices - Preopening'!$H$20:$H$299,">="&N$6,'Invoices - Preopening'!$H$20:$H$299,"<="&N$7,'Invoices - Preopening'!$C$20:$C$299,'Model - Preopening & Fees'!$B30) -> 0 | O30: =SUMIFS('Invoices - Preopening'!$I$20:$I$299,'Invoices - Preopening'!$H$20:$H$299,">="&O$6,'Invoices - Preopening'!$H$20:$H$299,"<="&O$7,'Invoices - Preopening'!$C$20:$C$299,'Model - Preopening & Fees'!$B30) -> 0 | P30: =SUMIFS('Invoices - Preopening'!$I$20:$I$299,'Invoices - Preopening'!$H$20:$H$299,">="&P$6,'Invoices - Preopening'!$H$20:$H$299,"<="&P$7,'Invoices - Preopening'!$C$20:$C$299,'Model - Preopening & Fees'!$B30) -> 0 | Q30: =SUMIFS('Invoices - Preopening'!$I$20:$I$299,'Invoices - Preopening'!$H$20:$H$299,">="&Q$6,'Invoices - Preopening'!$H$20:$H$299,"<="&Q$7,'Invoices - Preopening'!$C$20:$C$299,'Model - Preopening & Fees'!$B30) -> 0 | R30: =SUMIFS('Invoices - Preopening'!$I$20:$I$299,'Invoices - Preopening'!$H$20:$H$299,">="&R$6,'Invoices - Preopening'!$H$20:$H$299,"<="&R$7,'Invoices - Preopening'!$C$20:$C$299,'Model - Preopening & Fees'!$B30) -> 0 | S30: =SUMIFS('Invoices - Preopening'!$I$20:$I$299,'Invoices - Preopening'!$H$20:$H$299,">="&S$6,'Invoices - Preopening'!$H$20:$H$299,"<="&S$7,'Invoices - Preopening'!$C$20:$C$299,'Model - Preopening & Fees'!$B30) -> 0 | ... AC30: =SUMIFS('Invoices - Preopening'!$I$20:$I$299,'Invoices - Preopening'!$H$20:$H$299,">="&AC$6,'Invoices - Preopening'!$H$20:$H$299,"<="&AC$7,'Invoices - Preopening'!$C$20:$C$299,'Model - Preopening & Fees'!$B30) -> 0 | AD30: 0 | AE30: 0 | AF30: 0 | AG30: 200 | AH30: 200 | AI30: 200 | AJ30: 200 | AK30: 0 | AL30: 0 | AM30: 0 | AN30: 0 | AO30: 0 | AP30: 0 | AQ30: 0 | AR30: 0 | AT30: =-SUMIFS($L30:$AR30,$L$5:$AR$5,AT$5) -> 0 | AU30: =-SUMIFS($L30:$AR30,$L$5:$AR$5,AU$5) -> 0 | AV30: =-SUMIFS($L30:$AR30,$L$5:$AR$5,AV$5) -> 0 | AW30: =-SUMIFS($L30:$AR30,$L$5:$AR$5,AW$5) -> 0 | AX30: =-SUMIFS($L30:$AR30,$L$5:$AR$5,AX$5) -> 0 | AY30: =-SUMIFS($L30:$AR30,$L$5:$AR$5,AY$5) -> 0 | AZ30: =-SUMIFS($L30:$AR30,$L$5:$AR$5,AZ$5) -> 0 | BA30: =-SUMIFS($L30:$AR30,$L$5:$AR$5,BA$5) -> -600 | ... BD30: =-SUMIFS($L30:$AR30,$L$5:$AR$5,BD$5) -> 0 | BF30: =SUM(AT30:BD30) -> -800
B32: Online Marketing / Paid Media
A33: 1 | B33: Diginauts Retainer (Sep 2026 till April 2027) | D33: Marketing | E33: Aniek | F33: 7832 | G33: =SUMIFS($L33:$AR33,$L$7:$AR$7,"<="&$J$4) -> 0 | H33: =J33-G33 -> 5548 | J33: =SUM(L33:AR33) -> 5548 | L33: =SUMIFS('Invoices - Preopening'!$I$20:$I$299,'Invoices - Preopening'!$H$20:$H$299,">="&L$6,'Invoices - Preopening'!$H$20:$H$299,"<="&L$7,'Invoices - Preopening'!$C$20:$C$299,'Model - Preopening & Fees'!$B33) -> 0 | M33: =SUMIFS('Invoices - Preopening'!$I$20:$I$299,'Invoices - Preopening'!$H$20:$H$299,">="&M$6,'Invoices - Preopening'!$H$20:$H$299,"<="&M$7,'Invoices - Preopening'!$C$20:$C$299,'Model - Preopening & Fees'!$B33) -> 0 | N33: =SUMIFS('Invoices - Preopening'!$I$20:$I$299,'Invoices - Preopening'!$H$20:$H$299,">="&N$6,'Invoices - Preopening'!$H$20:$H$299,"<="&N$7,'Invoices - Preopening'!$C$20:$C$299,'Model - Preopening & Fees'!$B33) -> 0 | O33: =SUMIFS('Invoices - Preopening'!$I$20:$I$299,'Invoices - Preopening'!$H$20:$H$299,">="&O$6,'Invoices - Preopening'!$H$20:$H$299,"<="&O$7,'Invoices - Preopening'!$C$20:$C$299,'Model - Preopening & Fees'!$B33) -> 0 | P33: =SUMIFS('Invoices - Preopening'!$I$20:$I$299,'Invoices - Preopening'!$H$20:$H$299,">="&P$6,'Invoices - Preopening'!$H$20:$H$299,"<="&P$7,'Invoices - Preopening'!$C$20:$C$299,'Model - Preopening & Fees'!$B33) -> 0 | Q33: =SUMIFS('Invoices - Preopening'!$I$20:$I$299,'Invoices - Preopening'!$H$20:$H$299,">="&Q$6,'Invoices - Preopening'!$H$20:$H$299,"<="&Q$7,'Invoices - Preopening'!$C$20:$C$299,'Model - Preopening & Fees'!$B33) -> 0 | R33: =SUMIFS('Invoices - Preopening'!$I$20:$I$299,'Invoices - Preopening'!$H$20:$H$299,">="&R$6,'Invoices - Preopening'!$H$20:$H$299,"<="&R$7,'Invoices - Preopening'!$C$20:$C$299,'Model - Preopening & Fees'!$B33) -> 0 | S33: =SUMIFS('Invoices - Preopening'!$I$20:$I$299,'Invoices - Preopening'!$H$20:$H$299,">="&S$6,'Invoices - Preopening'!$H$20:$H$299,"<="&S$7,'Invoices - Preopening'!$C$20:$C$299,'Model - Preopening & Fees'!$B33) -> 0 | ... AC33: =SUMIFS('Invoices - Preopening'!$I$20:$I$299,'Invoices - Preopening'!$H$20:$H$299,">="&AC$6,'Invoices - Preopening'!$H$20:$H$299,"<="&AC$7,'Invoices - Preopening'!$C$20:$C$299,'Model - Preopening & Fees'!$B33) -> 0 | AD33: 0 | AE33: 0 | AF33: 460 | AG33: 460 | AH33: 1157 | AI33: 1157 | AJ33: 1157 | AK33: 1157 | AL33: 0 | AM33: 0 | AN33: 0 | AO33: 0 | AP33: 0 | AQ33: 0 | AR33: 0 | AT33: =-SUMIFS($L33:$AR33,$L$5:$AR$5,AT$5) -> 0 | AU33: =-SUMIFS($L33:$AR33,$L$5:$AR$5,AU$5) -> 0 | AV33: =-SUMIFS($L33:$AR33,$L$5:$AR$5,AV$5) -> 0 | AW33: =-SUMIFS($L33:$AR33,$L$5:$AR$5,AW$5) -> 0 | AX33: =-SUMIFS($L33:$AR33,$L$5:$AR$5,AX$5) -> 0 | AY33: =-SUMIFS($L33:$AR33,$L$5:$AR$5,AY$5) -> 0 | AZ33: =-SUMIFS($L33:$AR33,$L$5:$AR$5,AZ$5) -> -460 | BA33: =-SUMIFS($L33:$AR33,$L$5:$AR$5,BA$5) -> -2774 | ... BD33: =-SUMIFS($L33:$AR33,$L$5:$AR$5,BD$5) -> 0 | BF33: =SUM(AT33:BD33) -> -5548
A34: 1 | B34: Room Ads | D34: Marketing | E34: Aniek | F34: 21056 | G34: =SUMIFS($L34:$AR34,$L$7:$AR$7,"<="&$J$4) -> 0 | H34: =J34-G34 -> 10189 | J34: =SUM(L34:AR34) -> 10189 | L34: =SUMIFS('Invoices - Preopening'!$I$20:$I$299,'Invoices - Preopening'!$H$20:$H$299,">="&L$6,'Invoices - Preopening'!$H$20:$H$299,"<="&L$7,'Invoices - Preopening'!$C$20:$C$299,'Model - Preopening & Fees'!$B34) -> 0 | M34: =SUMIFS('Invoices - Preopening'!$I$20:$I$299,'Invoices - Preopening'!$H$20:$H$299,">="&M$6,'Invoices - Preopening'!$H$20:$H$299,"<="&M$7,'Invoices - Preopening'!$C$20:$C$299,'Model - Preopening & Fees'!$B34) -> 0 | N34: =SUMIFS('Invoices - Preopening'!$I$20:$I$299,'Invoices - Preopening'!$H$20:$H$299,">="&N$6,'Invoices - Preopening'!$H$20:$H$299,"<="&N$7,'Invoices - Preopening'!$C$20:$C$299,'Model - Preopening & Fees'!$B34) -> 0 | O34: =SUMIFS('Invoices - Preopening'!$I$20:$I$299,'Invoices - Preopening'!$H$20:$H$299,">="&O$6,'Invoices - Preopening'!$H$20:$H$299,"<="&O$7,'Invoices - Preopening'!$C$20:$C$299,'Model - Preopening & Fees'!$B34) -> 0 | P34: =SUMIFS('Invoices - Preopening'!$I$20:$I$299,'Invoices - Preopening'!$H$20:$H$299,">="&P$6,'Invoices - Preopening'!$H$20:$H$299,"<="&P$7,'Invoices - Preopening'!$C$20:$C$299,'Model - Preopening & Fees'!$B34) -> 0 | Q34: =SUMIFS('Invoices - Preopening'!$I$20:$I$299,'Invoices - Preopening'!$H$20:$H$299,">="&Q$6,'Invoices - Preopening'!$H$20:$H$299,"<="&Q$7,'Invoices - Preopening'!$C$20:$C$299,'Model - Preopening & Fees'!$B34) -> 0 | R34: =SUMIFS('Invoices - Preopening'!$I$20:$I$299,'Invoices - Preopening'!$H$20:$H$299,">="&R$6,'Invoices - Preopening'!$H$20:$H$299,"<="&R$7,'Invoices - Preopening'!$C$20:$C$299,'Model - Preopening & Fees'!$B34) -> 0 | S34: =SUMIFS('Invoices - Preopening'!$I$20:$I$299,'Invoices - Preopening'!$H$20:$H$299,">="&S$6,'Invoices - Preopening'!$H$20:$H$299,"<="&S$7,'Invoices - Preopening'!$C$20:$C$299,'Model - Preopening & Fees'!$B34) -> 0 | ... AC34: =SUMIFS('Invoices - Preopening'!$I$20:$I$299,'Invoices - Preopening'!$H$20:$H$299,">="&AC$6,'Invoices - Preopening'!$H$20:$H$299,"<="&AC$7,'Invoices - Preopening'!$C$20:$C$299,'Model - Preopening & Fees'!$B34) -> 0 | AD34: 0 | AE34: 0 | AF34: 0 | AG34: 883 | AH34: 883 | AI34: 2038 | AJ34: 2038 | AK34: 4347 | AL34: 0 | AM34: 0 | AN34: 0 | AO34: 0 | AP34: 0 | AQ34: 0 | AR34: 0 | AT34: =-SUMIFS($L34:$AR34,$L$5:$AR$5,AT$5) -> 0 | AU34: =-SUMIFS($L34:$AR34,$L$5:$AR$5,AU$5) -> 0 | AV34: =-SUMIFS($L34:$AR34,$L$5:$AR$5,AV$5) -> 0 | AW34: =-SUMIFS($L34:$AR34,$L$5:$AR$5,AW$5) -> 0 | AX34: =-SUMIFS($L34:$AR34,$L$5:$AR$5,AX$5) -> 0 | AY34: =-SUMIFS($L34:$AR34,$L$5:$AR$5,AY$5) -> 0 | AZ34: =-SUMIFS($L34:$AR34,$L$5:$AR$5,AZ$5) -> 0 | BA34: =-SUMIFS($L34:$AR34,$L$5:$AR$5,BA$5) -> -3804 | ... BD34: =-SUMIFS($L34:$AR34,$L$5:$AR$5,BD$5) -> 0 | BF34: =SUM(AT34:BD34) -> -10189
A35: 1 | B35: F&B Ads | D35: Marketing | E35: Aniek | F35: =SUM(AF35:AM35) -> 951 | G35: =SUMIFS($L35:$AR35,$L$7:$AR$7,"<="&$J$4) -> 0 | H35: =J35-G35 -> 951 | J35: =SUM(L35:AR35) -> 951 | L35: =SUMIFS('Invoices - Preopening'!$I$20:$I$299,'Invoices - Preopening'!$H$20:$H$299,">="&L$6,'Invoices - Preopening'!$H$20:$H$299,"<="&L$7,'Invoices - Preopening'!$C$20:$C$299,'Model - Preopening & Fees'!$B35) -> 0 | M35: =SUMIFS('Invoices - Preopening'!$I$20:$I$299,'Invoices - Preopening'!$H$20:$H$299,">="&M$6,'Invoices - Preopening'!$H$20:$H$299,"<="&M$7,'Invoices - Preopening'!$C$20:$C$299,'Model - Preopening & Fees'!$B35) -> 0 | N35: =SUMIFS('Invoices - Preopening'!$I$20:$I$299,'Invoices - Preopening'!$H$20:$H$299,">="&N$6,'Invoices - Preopening'!$H$20:$H$299,"<="&N$7,'Invoices - Preopening'!$C$20:$C$299,'Model - Preopening & Fees'!$B35) -> 0 | O35: =SUMIFS('Invoices - Preopening'!$I$20:$I$299,'Invoices - Preopening'!$H$20:$H$299,">="&O$6,'Invoices - Preopening'!$H$20:$H$299,"<="&O$7,'Invoices - Preopening'!$C$20:$C$299,'Model - Preopening & Fees'!$B35) -> 0 | P35: =SUMIFS('Invoices - Preopening'!$I$20:$I$299,'Invoices - Preopening'!$H$20:$H$299,">="&P$6,'Invoices - Preopening'!$H$20:$H$299,"<="&P$7,'Invoices - Preopening'!$C$20:$C$299,'Model - Preopening & Fees'!$B35) -> 0 | Q35: =SUMIFS('Invoices - Preopening'!$I$20:$I$299,'Invoices - Preopening'!$H$20:$H$299,">="&Q$6,'Invoices - Preopening'!$H$20:$H$299,"<="&Q$7,'Invoices - Preopening'!$C$20:$C$299,'Model - Preopening & Fees'!$B35) -> 0 | R35: =SUMIFS('Invoices - Preopening'!$I$20:$I$299,'Invoices - Preopening'!$H$20:$H$299,">="&R$6,'Invoices - Preopening'!$H$20:$H$299,"<="&R$7,'Invoices - Preopening'!$C$20:$C$299,'Model - Preopening & Fees'!$B35) -> 0 | S35: =SUMIFS('Invoices - Preopening'!$I$20:$I$299,'Invoices - Preopening'!$H$20:$H$299,">="&S$6,'Invoices - Preopening'!$H$20:$H$299,"<="&S$7,'Invoices - Preopening'!$C$20:$C$299,'Model - Preopening & Fees'!$B35) -> 0 | ... AC35: =SUMIFS('Invoices - Preopening'!$I$20:$I$299,'Invoices - Preopening'!$H$20:$H$299,">="&AC$6,'Invoices - Preopening'!$H$20:$H$299,"<="&AC$7,'Invoices - Preopening'!$C$20:$C$299,'Model - Preopening & Fees'!$B35) -> 0 | AD35: 0 | AE35: 0 | AF35: 0 | AG35: 0 | AH35: 0 | AI35: 136 | AJ35: 272 | AK35: 543 | AL35: 0 | AM35: 0 | AN35: 0 | AO35: 0 | AP35: 0 | AQ35: 0 | AR35: 0 | AT35: =-SUMIFS($L35:$AR35,$L$5:$AR$5,AT$5) -> 0 | AU35: =-SUMIFS($L35:$AR35,$L$5:$AR$5,AU$5) -> 0 | AV35: =-SUMIFS($L35:$AR35,$L$5:$AR$5,AV$5) -> 0 | AW35: =-SUMIFS($L35:$AR35,$L$5:$AR$5,AW$5) -> 0 | AX35: =-SUMIFS($L35:$AR35,$L$5:$AR$5,AX$5) -> 0 | AY35: =-SUMIFS($L35:$AR35,$L$5:$AR$5,AY$5) -> 0 | AZ35: =-SUMIFS($L35:$AR35,$L$5:$AR$5,AZ$5) -> 0 | BA35: =-SUMIFS($L35:$AR35,$L$5:$AR$5,BA$5) -> -136 | ... BD35: =-SUMIFS($L35:$AR35,$L$5:$AR$5,BD$5) -> 0 | BF35: =SUM(AT35:BD35) -> -951
A36: 1 | B36: Branded Ads | D36: Marketing | E36: Aniek | F36: =SUM(AF36:AM36) -> 2444 | G36: =SUMIFS($L36:$AR36,$L$7:$AR$7,"<="&$J$4) -> 0 | H36: =J36-G36 -> 2444 | J36: =SUM(L36:AR36) -> 2444 | L36: =SUMIFS('Invoices - Preopening'!$I$20:$I$299,'Invoices - Preopening'!$H$20:$H$299,">="&L$6,'Invoices - Preopening'!$H$20:$H$299,"<="&L$7,'Invoices - Preopening'!$C$20:$C$299,'Model - Preopening & Fees'!$B36) -> 0 | M36: =SUMIFS('Invoices - Preopening'!$I$20:$I$299,'Invoices - Preopening'!$H$20:$H$299,">="&M$6,'Invoices - Preopening'!$H$20:$H$299,"<="&M$7,'Invoices - Preopening'!$C$20:$C$299,'Model - Preopening & Fees'!$B36) -> 0 | N36: =SUMIFS('Invoices - Preopening'!$I$20:$I$299,'Invoices - Preopening'!$H$20:$H$299,">="&N$6,'Invoices - Preopening'!$H$20:$H$299,"<="&N$7,'Invoices - Preopening'!$C$20:$C$299,'Model - Preopening & Fees'!$B36) -> 0 | O36: =SUMIFS('Invoices - Preopening'!$I$20:$I$299,'Invoices - Preopening'!$H$20:$H$299,">="&O$6,'Invoices - Preopening'!$H$20:$H$299,"<="&O$7,'Invoices - Preopening'!$C$20:$C$299,'Model - Preopening & Fees'!$B36) -> 0 | P36: =SUMIFS('Invoices - Preopening'!$I$20:$I$299,'Invoices - Preopening'!$H$20:$H$299,">="&P$6,'Invoices - Preopening'!$H$20:$H$299,"<="&P$7,'Invoices - Preopening'!$C$20:$C$299,'Model - Preopening & Fees'!$B36) -> 0 | Q36: =SUMIFS('Invoices - Preopening'!$I$20:$I$299,'Invoices - Preopening'!$H$20:$H$299,">="&Q$6,'Invoices - Preopening'!$H$20:$H$299,"<="&Q$7,'Invoices - Preopening'!$C$20:$C$299,'Model - Preopening & Fees'!$B36) -> 0 | R36: =SUMIFS('Invoices - Preopening'!$I$20:$I$299,'Invoices - Preopening'!$H$20:$H$299,">="&R$6,'Invoices - Preopening'!$H$20:$H$299,"<="&R$7,'Invoices - Preopening'!$C$20:$C$299,'Model - Preopening & Fees'!$B36) -> 0 | S36: =SUMIFS('Invoices - Preopening'!$I$20:$I$299,'Invoices - Preopening'!$H$20:$H$299,">="&S$6,'Invoices - Preopening'!$H$20:$H$299,"<="&S$7,'Invoices - Preopening'!$C$20:$C$299,'Model - Preopening & Fees'!$B36) -> 0 | ... AC36: =SUMIFS('Invoices - Preopening'!$I$20:$I$299,'Invoices - Preopening'!$H$20:$H$299,">="&AC$6,'Invoices - Preopening'!$H$20:$H$299,"<="&AC$7,'Invoices - Preopening'!$C$20:$C$299,'Model - Preopening & Fees'!$B36) -> 0 | AD36: 0 | AE36: 0 | AF36: 0 | AG36: 475 | AH36: 475 | AI36: 543 | AJ36: 408 | AK36: 543 | AL36: 0 | AM36: 0 | AN36: 0 | AO36: 0 | AP36: 0 | AQ36: 0 | AR36: 0 | AT36: =-SUMIFS($L36:$AR36,$L$5:$AR$5,AT$5) -> 0 | AU36: =-SUMIFS($L36:$AR36,$L$5:$AR$5,AU$5) -> 0 | AV36: =-SUMIFS($L36:$AR36,$L$5:$AR$5,AV$5) -> 0 | AW36: =-SUMIFS($L36:$AR36,$L$5:$AR$5,AW$5) -> 0 | AX36: =-SUMIFS($L36:$AR36,$L$5:$AR$5,AX$5) -> 0 | AY36: =-SUMIFS($L36:$AR36,$L$5:$AR$5,AY$5) -> 0 | AZ36: =-SUMIFS($L36:$AR36,$L$5:$AR$5,AZ$5) -> 0 | BA36: =-SUMIFS($L36:$AR36,$L$5:$AR$5,BA$5) -> -1493 | ... BD36: =-SUMIFS($L36:$AR36,$L$5:$AR$5,BD$5) -> 0 | BF36: =SUM(AT36:BD36) -> -2444
B37: See this doc for split per channel | F37: =SUMIFS($L37:$AR37,$L$7:$AR$7,"<="&$J$4) -> 0 | G37: =SUMIFS($L37:$AR37,$L$7:$AR$7,"<="&$J$4) -> 0 | H37: =J37-G37 -> 0 | J37: =SUM(L37:AR37) -> 0 | L37: =SUMIFS('Invoices - Preopening'!$I$20:$I$299,'Invoices - Preopening'!$H$20:$H$299,">="&L$6,'Invoices - Preopening'!$H$20:$H$299,"<="&L$7,'Invoices - Preopening'!$C$20:$C$299,'Model - Preopening & Fees'!$B37) -> 0 | M37: =SUMIFS('Invoices - Preopening'!$I$20:$I$299,'Invoices - Preopening'!$H$20:$H$299,">="&M$6,'Invoices - Preopening'!$H$20:$H$299,"<="&M$7,'Invoices - Preopening'!$C$20:$C$299,'Model - Preopening & Fees'!$B37) -> 0 | N37: =SUMIFS('Invoices - Preopening'!$I$20:$I$299,'Invoices - Preopening'!$H$20:$H$299,">="&N$6,'Invoices - Preopening'!$H$20:$H$299,"<="&N$7,'Invoices - Preopening'!$C$20:$C$299,'Model - Preopening & Fees'!$B37) -> 0 | O37: =SUMIFS('Invoices - Preopening'!$I$20:$I$299,'Invoices - Preopening'!$H$20:$H$299,">="&O$6,'Invoices - Preopening'!$H$20:$H$299,"<="&O$7,'Invoices - Preopening'!$C$20:$C$299,'Model - Preopening & Fees'!$B37) -> 0 | P37: =SUMIFS('Invoices - Preopening'!$I$20:$I$299,'Invoices - Preopening'!$H$20:$H$299,">="&P$6,'Invoices - Preopening'!$H$20:$H$299,"<="&P$7,'Invoices - Preopening'!$C$20:$C$299,'Model - Preopening & Fees'!$B37) -> 0 | Q37: =SUMIFS('Invoices - Preopening'!$I$20:$I$299,'Invoices - Preopening'!$H$20:$H$299,">="&Q$6,'Invoices - Preopening'!$H$20:$H$299,"<="&Q$7,'Invoices - Preopening'!$C$20:$C$299,'Model - Preopening & Fees'!$B37) -> 0 | R37: =SUMIFS('Invoices - Preopening'!$I$20:$I$299,'Invoices - Preopening'!$H$20:$H$299,">="&R$6,'Invoices - Preopening'!$H$20:$H$299,"<="&R$7,'Invoices - Preopening'!$C$20:$C$299,'Model - Preopening & Fees'!$B37) -> 0 | S37: =SUMIFS('Invoices - Preopening'!$I$20:$I$299,'Invoices - Preopening'!$H$20:$H$299,">="&S$6,'Invoices - Preopening'!$H$20:$H$299,"<="&S$7,'Invoices - Preopening'!$C$20:$C$299,'Model - Preopening & Fees'!$B37) -> 0 | ... AC37: =SUMIFS('Invoices - Preopening'!$I$20:$I$299,'Invoices - Preopening'!$H$20:$H$299,">="&AC$6,'Invoices - Preopening'!$H$20:$H$299,"<="&AC$7,'Invoices - Preopening'!$C$20:$C$299,'Model - Preopening & Fees'!$B37) -> 0 | AD37: 0 | AE37: 0 | AF37: 0 | AG37: 0 | AH37: 0 | AI37: 0 | AJ37: 0 | AK37: 0 | AL37: 0 | AM37: 0 | AN37: 0 | AO37: 0 | AP37: 0 | AQ37: 0 | AR37: 0 | AT37: =-SUMIFS($L37:$AR37,$L$5:$AR$5,AT$5) -> 0 | AU37: =-SUMIFS($L37:$AR37,$L$5:$AR$5,AU$5) -> 0 | AV37: =-SUMIFS($L37:$AR37,$L$5:$AR$5,AV$5) -> 0 | AW37: =-SUMIFS($L37:$AR37,$L$5:$AR$5,AW$5) -> 0 | AX37: =-SUMIFS($L37:$AR37,$L$5:$AR$5,AX$5) -> 0 | AY37: =-SUMIFS($L37:$AR37,$L$5:$AR$5,AY$5) -> 0 | AZ37: =-SUMIFS($L37:$AR37,$L$5:$AR$5,AZ$5) -> 0 | BA37: =-SUMIFS($L37:$AR37,$L$5:$AR$5,BA$5) -> 0 | ... BD37: =-SUMIFS($L37:$AR37,$L$5:$AR$5,BD$5) -> 0 | BF37: =SUM(AT37:BD37) -> 0
B39: Printed Materials & Advertising
A40: 1 | B40: Production Campaign Materials (OOH, Guerilla) | D40: Marketing | E40: Aniek | F40: 25000 | G40: =SUMIFS($L40:$AR40,$L$7:$AR$7,"<="&$J$4) -> 0 | H40: =J40-G40 -> 25000 | J40: =SUM(L40:AR40) -> 25000 | L40: =SUMIFS('Invoices - Preopening'!$I$20:$I$299,'Invoices - Preopening'!$H$20:$H$299,">="&L$6,'Invoices - Preopening'!$H$20:$H$299,"<="&L$7,'Invoices - Preopening'!$C$20:$C$299,'Model - Preopening & Fees'!$B40) -> 0 | M40: =SUMIFS('Invoices - Preopening'!$I$20:$I$299,'Invoices - Preopening'!$H$20:$H$299,">="&M$6,'Invoices - Preopening'!$H$20:$H$299,"<="&M$7,'Invoices - Preopening'!$C$20:$C$299,'Model - Preopening & Fees'!$B40) -> 0 | N40: =SUMIFS('Invoices - Preopening'!$I$20:$I$299,'Invoices - Preopening'!$H$20:$H$299,">="&N$6,'Invoices - Preopening'!$H$20:$H$299,"<="&N$7,'Invoices - Preopening'!$C$20:$C$299,'Model - Preopening & Fees'!$B40) -> 0 | O40: =SUMIFS('Invoices - Preopening'!$I$20:$I$299,'Invoices - Preopening'!$H$20:$H$299,">="&O$6,'Invoices - Preopening'!$H$20:$H$299,"<="&O$7,'Invoices - Preopening'!$C$20:$C$299,'Model - Preopening & Fees'!$B40) -> 0 | P40: =SUMIFS('Invoices - Preopening'!$I$20:$I$299,'Invoices - Preopening'!$H$20:$H$299,">="&P$6,'Invoices - Preopening'!$H$20:$H$299,"<="&P$7,'Invoices - Preopening'!$C$20:$C$299,'Model - Preopening & Fees'!$B40) -> 0 | Q40: =SUMIFS('Invoices - Preopening'!$I$20:$I$299,'Invoices - Preopening'!$H$20:$H$299,">="&Q$6,'Invoices - Preopening'!$H$20:$H$299,"<="&Q$7,'Invoices - Preopening'!$C$20:$C$299,'Model - Preopening & Fees'!$B40) -> 0 | R40: =SUMIFS('Invoices - Preopening'!$I$20:$I$299,'Invoices - Preopening'!$H$20:$H$299,">="&R$6,'Invoices - Preopening'!$H$20:$H$299,"<="&R$7,'Invoices - Preopening'!$C$20:$C$299,'Model - Preopening & Fees'!$B40) -> 0 | S40: =SUMIFS('Invoices - Preopening'!$I$20:$I$299,'Invoices - Preopening'!$H$20:$H$299,">="&S$6,'Invoices - Preopening'!$H$20:$H$299,"<="&S$7,'Invoices - Preopening'!$C$20:$C$299,'Model - Preopening & Fees'!$B40) -> 0 | ... AC40: =SUMIFS('Invoices - Preopening'!$I$20:$I$299,'Invoices - Preopening'!$H$20:$H$299,">="&AC$6,'Invoices - Preopening'!$H$20:$H$299,"<="&AC$7,'Invoices - Preopening'!$C$20:$C$299,'Model - Preopening & Fees'!$B40) -> 0 | AD40: 0 | AE40: 0 | AF40: 0 | AG40: 0 | AH40: 5000 | AI40: 0 | AJ40: 5000 | AK40: 10000 | AL40: 0 | AM40: 5000 | AN40: 0 | AO40: 0 | AP40: 0 | AQ40: 0 | AR40: 0 | AT40: =-SUMIFS($L40:$AR40,$L$5:$AR$5,AT$5) -> 0 | AU40: =-SUMIFS($L40:$AR40,$L$5:$AR$5,AU$5) -> 0 | AV40: =-SUMIFS($L40:$AR40,$L$5:$AR$5,AV$5) -> 0 | AW40: =-SUMIFS($L40:$AR40,$L$5:$AR$5,AW$5) -> 0 | AX40: =-SUMIFS($L40:$AR40,$L$5:$AR$5,AX$5) -> 0 | AY40: =-SUMIFS($L40:$AR40,$L$5:$AR$5,AY$5) -> 0 | AZ40: =-SUMIFS($L40:$AR40,$L$5:$AR$5,AZ$5) -> 0 | BA40: =-SUMIFS($L40:$AR40,$L$5:$AR$5,BA$5) -> -5000 | ... BD40: =-SUMIFS($L40:$AR40,$L$5:$AR$5,BD$5) -> 0 | BF40: =SUM(AT40:BD40) -> -25000
A41: 1 | B41: Print Materials (excl. build & ops/F&B & recruitment materials) | D41: Marketing | E41: Aniek | F41: 5000 | G41: =SUMIFS($L41:$AR41,$L$7:$AR$7,"<="&$J$4) -> 0 | H41: =J41-G41 -> 5000 | J41: =SUM(L41:AR41) -> 5000 | L41: =SUMIFS('Invoices - Preopening'!$I$20:$I$299,'Invoices - Preopening'!$H$20:$H$299,">="&L$6,'Invoices - Preopening'!$H$20:$H$299,"<="&L$7,'Invoices - Preopening'!$C$20:$C$299,'Model - Preopening & Fees'!$B41) -> 0 | M41: =SUMIFS('Invoices - Preopening'!$I$20:$I$299,'Invoices - Preopening'!$H$20:$H$299,">="&M$6,'Invoices - Preopening'!$H$20:$H$299,"<="&M$7,'Invoices - Preopening'!$C$20:$C$299,'Model - Preopening & Fees'!$B41) -> 0 | N41: =SUMIFS('Invoices - Preopening'!$I$20:$I$299,'Invoices - Preopening'!$H$20:$H$299,">="&N$6,'Invoices - Preopening'!$H$20:$H$299,"<="&N$7,'Invoices - Preopening'!$C$20:$C$299,'Model - Preopening & Fees'!$B41) -> 0 | O41: =SUMIFS('Invoices - Preopening'!$I$20:$I$299,'Invoices - Preopening'!$H$20:$H$299,">="&O$6,'Invoices - Preopening'!$H$20:$H$299,"<="&O$7,'Invoices - Preopening'!$C$20:$C$299,'Model - Preopening & Fees'!$B41) -> 0 | P41: =SUMIFS('Invoices - Preopening'!$I$20:$I$299,'Invoices - Preopening'!$H$20:$H$299,">="&P$6,'Invoices - Preopening'!$H$20:$H$299,"<="&P$7,'Invoices - Preopening'!$C$20:$C$299,'Model - Preopening & Fees'!$B41) -> 0 | Q41: =SUMIFS('Invoices - Preopening'!$I$20:$I$299,'Invoices - Preopening'!$H$20:$H$299,">="&Q$6,'Invoices - Preopening'!$H$20:$H$299,"<="&Q$7,'Invoices - Preopening'!$C$20:$C$299,'Model - Preopening & Fees'!$B41) -> 0 | R41: =SUMIFS('Invoices - Preopening'!$I$20:$I$299,'Invoices - Preopening'!$H$20:$H$299,">="&R$6,'Invoices - Preopening'!$H$20:$H$299,"<="&R$7,'Invoices - Preopening'!$C$20:$C$299,'Model - Preopening & Fees'!$B41) -> 0 | S41: =SUMIFS('Invoices - Preopening'!$I$20:$I$299,'Invoices - Preopening'!$H$20:$H$299,">="&S$6,'Invoices - Preopening'!$H$20:$H$299,"<="&S$7,'Invoices - Preopening'!$C$20:$C$299,'Model - Preopening & Fees'!$B41) -> 0 | ... AC41: =SUMIFS('Invoices - Preopening'!$I$20:$I$299,'Invoices - Preopening'!$H$20:$H$299,">="&AC$6,'Invoices - Preopening'!$H$20:$H$299,"<="&AC$7,'Invoices - Preopening'!$C$20:$C$299,'Model - Preopening & Fees'!$B41) -> 0 | AD41: 0 | AE41: 0 | AF41: 0 | AG41: 0 | AH41: 0 | AI41: 0 | AJ41: 0 | AK41: 2000 | AL41: 1500 | AM41: 1500 | AN41: 0 | AO41: 0 | AP41: 0 | AQ41: 0 | AR41: 0 | AT41: =-SUMIFS($L41:$AR41,$L$5:$AR$5,AT$5) -> 0 | AU41: =-SUMIFS($L41:$AR41,$L$5:$AR$5,AU$5) -> 0 | AV41: =-SUMIFS($L41:$AR41,$L$5:$AR$5,AV$5) -> 0 | AW41: =-SUMIFS($L41:$AR41,$L$5:$AR$5,AW$5) -> 0 | AX41: =-SUMIFS($L41:$AR41,$L$5:$AR$5,AX$5) -> 0 | AY41: =-SUMIFS($L41:$AR41,$L$5:$AR$5,AY$5) -> 0 | AZ41: =-SUMIFS($L41:$AR41,$L$5:$AR$5,AZ$5) -> 0 | BA41: =-SUMIFS($L41:$AR41,$L$5:$AR$5,BA$5) -> 0 | ... BD41: =-SUMIFS($L41:$AR41,$L$5:$AR$5,BD$5) -> 0 | BF41: =SUM(AT41:BD41) -> -5000
B43: Website & Content
A44: 1 | B44: Miscellaneous (Illustrations, IBE tbc) | D44: Marketing | E44: Aniek | F44: 3000 | G44: =SUMIFS($L44:$AR44,$L$7:$AR$7,"<="&$J$4) -> 0 | H44: =J44-G44 -> 3000 | J44: =SUM(L44:AR44) -> 3000 | L44: =SUMIFS('Invoices - Preopening'!$I$20:$I$299,'Invoices - Preopening'!$H$20:$H$299,">="&L$6,'Invoices - Preopening'!$H$20:$H$299,"<="&L$7,'Invoices - Preopening'!$C$20:$C$299,'Model - Preopening & Fees'!$B44) -> 0 | M44: =SUMIFS('Invoices - Preopening'!$I$20:$I$299,'Invoices - Preopening'!$H$20:$H$299,">="&M$6,'Invoices - Preopening'!$H$20:$H$299,"<="&M$7,'Invoices - Preopening'!$C$20:$C$299,'Model - Preopening & Fees'!$B44) -> 0 | N44: =SUMIFS('Invoices - Preopening'!$I$20:$I$299,'Invoices - Preopening'!$H$20:$H$299,">="&N$6,'Invoices - Preopening'!$H$20:$H$299,"<="&N$7,'Invoices - Preopening'!$C$20:$C$299,'Model - Preopening & Fees'!$B44) -> 0 | O44: =SUMIFS('Invoices - Preopening'!$I$20:$I$299,'Invoices - Preopening'!$H$20:$H$299,">="&O$6,'Invoices - Preopening'!$H$20:$H$299,"<="&O$7,'Invoices - Preopening'!$C$20:$C$299,'Model - Preopening & Fees'!$B44) -> 0 | P44: =SUMIFS('Invoices - Preopening'!$I$20:$I$299,'Invoices - Preopening'!$H$20:$H$299,">="&P$6,'Invoices - Preopening'!$H$20:$H$299,"<="&P$7,'Invoices - Preopening'!$C$20:$C$299,'Model - Preopening & Fees'!$B44) -> 0 | Q44: =SUMIFS('Invoices - Preopening'!$I$20:$I$299,'Invoices - Preopening'!$H$20:$H$299,">="&Q$6,'Invoices - Preopening'!$H$20:$H$299,"<="&Q$7,'Invoices - Preopening'!$C$20:$C$299,'Model - Preopening & Fees'!$B44) -> 0 | R44: =SUMIFS('Invoices - Preopening'!$I$20:$I$299,'Invoices - Preopening'!$H$20:$H$299,">="&R$6,'Invoices - Preopening'!$H$20:$H$299,"<="&R$7,'Invoices - Preopening'!$C$20:$C$299,'Model - Preopening & Fees'!$B44) -> 0 | S44: =SUMIFS('Invoices - Preopening'!$I$20:$I$299,'Invoices - Preopening'!$H$20:$H$299,">="&S$6,'Invoices - Preopening'!$H$20:$H$299,"<="&S$7,'Invoices - Preopening'!$C$20:$C$299,'Model - Preopening & Fees'!$B44) -> 0 | ... AC44: =SUMIFS('Invoices - Preopening'!$I$20:$I$299,'Invoices - Preopening'!$H$20:$H$299,">="&AC$6,'Invoices - Preopening'!$H$20:$H$299,"<="&AC$7,'Invoices - Preopening'!$C$20:$C$299,'Model - Preopening & Fees'!$B44) -> 0 | AD44: 0 | AE44: 0 | AF44: 0 | AG44: 3000 | AH44: 0 | AI44: 0 | AJ44: 0 | AK44: 0 | AL44: 0 | AM44: 0 | AN44: 0 | AO44: 0 | AP44: 0 | AQ44: 0 | AR44: 0 | AT44: =-SUMIFS($L44:$AR44,$L$5:$AR$5,AT$5) -> 0 | AU44: =-SUMIFS($L44:$AR44,$L$5:$AR$5,AU$5) -> 0 | AV44: =-SUMIFS($L44:$AR44,$L$5:$AR$5,AV$5) -> 0 | AW44: =-SUMIFS($L44:$AR44,$L$5:$AR$5,AW$5) -> 0 | AX44: =-SUMIFS($L44:$AR44,$L$5:$AR$5,AX$5) -> 0 | AY44: =-SUMIFS($L44:$AR44,$L$5:$AR$5,AY$5) -> 0 | AZ44: =-SUMIFS($L44:$AR44,$L$5:$AR$5,AZ$5) -> 0 | BA44: =-SUMIFS($L44:$AR44,$L$5:$AR$5,BA$5) -> -3000 | ... BD44: =-SUMIFS($L44:$AR44,$L$5:$AR$5,BD$5) -> 0 | BF44: =SUM(AT44:BD44) -> -3000
AT45: =-SUMIFS($L45:$AR45,$L$5:$AR$5,AT$5) -> 0 | AU45: =-SUMIFS($L45:$AR45,$L$5:$AR$5,AU$5) -> 0 | AV45: =-SUMIFS($L45:$AR45,$L$5:$AR$5,AV$5) -> 0 | AW45: =-SUMIFS($L45:$AR45,$L$5:$AR$5,AW$5) -> 0 | AX45: =-SUMIFS($L45:$AR45,$L$5:$AR$5,AX$5) -> 0 | AY45: =-SUMIFS($L45:$AR45,$L$5:$AR$5,AY$5) -> 0 | AZ45: =-SUMIFS($L45:$AR45,$L$5:$AR$5,AZ$5) -> 0 | BA45: =-SUMIFS($L45:$AR45,$L$5:$AR$5,BA$5) -> 0 | ... BD45: =-SUMIFS($L45:$AR45,$L$5:$AR$5,BD$5) -> 0 | BF45: =SUM(AT45:BD45) -> 0
B46: Opening Party / Launch Event
A47: 1 | B47: Partner Fees | D47: Marketing | E47: Aniek | F47: 7500 | G47: =SUMIFS($L47:$AR47,$L$7:$AR$7,"<="&$J$4) -> 0 | H47: =J47-G47 -> 7500 | J47: =SUM(L47:AR47) -> 7500 | L47: =SUMIFS('Invoices - Preopening'!$I$20:$I$299,'Invoices - Preopening'!$H$20:$H$299,">="&L$6,'Invoices - Preopening'!$H$20:$H$299,"<="&L$7,'Invoices - Preopening'!$C$20:$C$299,'Model - Preopening & Fees'!$B47) -> 0 | M47: =SUMIFS('Invoices - Preopening'!$I$20:$I$299,'Invoices - Preopening'!$H$20:$H$299,">="&M$6,'Invoices - Preopening'!$H$20:$H$299,"<="&M$7,'Invoices - Preopening'!$C$20:$C$299,'Model - Preopening & Fees'!$B47) -> 0 | N47: =SUMIFS('Invoices - Preopening'!$I$20:$I$299,'Invoices - Preopening'!$H$20:$H$299,">="&N$6,'Invoices - Preopening'!$H$20:$H$299,"<="&N$7,'Invoices - Preopening'!$C$20:$C$299,'Model - Preopening & Fees'!$B47) -> 0 | O47: =SUMIFS('Invoices - Preopening'!$I$20:$I$299,'Invoices - Preopening'!$H$20:$H$299,">="&O$6,'Invoices - Preopening'!$H$20:$H$299,"<="&O$7,'Invoices - Preopening'!$C$20:$C$299,'Model - Preopening & Fees'!$B47) -> 0 | P47: =SUMIFS('Invoices - Preopening'!$I$20:$I$299,'Invoices - Preopening'!$H$20:$H$299,">="&P$6,'Invoices - Preopening'!$H$20:$H$299,"<="&P$7,'Invoices - Preopening'!$C$20:$C$299,'Model - Preopening & Fees'!$B47) -> 0 | Q47: =SUMIFS('Invoices - Preopening'!$I$20:$I$299,'Invoices - Preopening'!$H$20:$H$299,">="&Q$6,'Invoices - Preopening'!$H$20:$H$299,"<="&Q$7,'Invoices - Preopening'!$C$20:$C$299,'Model - Preopening & Fees'!$B47) -> 0 | R47: =SUMIFS('Invoices - Preopening'!$I$20:$I$299,'Invoices - Preopening'!$H$20:$H$299,">="&R$6,'Invoices - Preopening'!$H$20:$H$299,"<="&R$7,'Invoices - Preopening'!$C$20:$C$299,'Model - Preopening & Fees'!$B47) -> 0 | S47: =SUMIFS('Invoices - Preopening'!$I$20:$I$299,'Invoices - Preopening'!$H$20:$H$299,">="&S$6,'Invoices - Preopening'!$H$20:$H$299,"<="&S$7,'Invoices - Preopening'!$C$20:$C$299,'Model - Preopening & Fees'!$B47) -> 0 | ... AC47: =SUMIFS('Invoices - Preopening'!$I$20:$I$299,'Invoices - Preopening'!$H$20:$H$299,">="&AC$6,'Invoices - Preopening'!$H$20:$H$299,"<="&AC$7,'Invoices - Preopening'!$C$20:$C$299,'Model - Preopening & Fees'!$B47) -> 0 | AD47: 0 | AE47: 0 | AF47: 0 | AG47: 0 | AH47: 0 | AI47: 0 | AJ47: 0 | AK47: 0 | AL47: 3750 | AM47: 3750 | AN47: 0 | AO47: 0 | AP47: 0 | AQ47: 0 | AR47: 0 | AT47: =-SUMIFS($L47:$AR47,$L$5:$AR$5,AT$5) -> 0 | AU47: =-SUMIFS($L47:$AR47,$L$5:$AR$5,AU$5) -> 0 | AV47: =-SUMIFS($L47:$AR47,$L$5:$AR$5,AV$5) -> 0 | AW47: =-SUMIFS($L47:$AR47,$L$5:$AR$5,AW$5) -> 0 | AX47: =-SUMIFS($L47:$AR47,$L$5:$AR$5,AX$5) -> 0 | AY47: =-SUMIFS($L47:$AR47,$L$5:$AR$5,AY$5) -> 0 | AZ47: =-SUMIFS($L47:$AR47,$L$5:$AR$5,AZ$5) -> 0 | BA47: =-SUMIFS($L47:$AR47,$L$5:$AR$5,BA$5) -> 0 | ... BD47: =-SUMIFS($L47:$AR47,$L$5:$AR$5,BD$5) -> 0 | BF47: =SUM(AT47:BD47) -> -7500
A48: 1 | B48: F&B Events | D48: Marketing | E48: Aniek | F48: 5000 | G48: =SUMIFS($L48:$AR48,$L$7:$AR$7,"<="&$J$4) -> 0 | H48: =J48-G48 -> 5000 | J48: =SUM(L48:AR48) -> 5000 | L48: =SUMIFS('Invoices - Preopening'!$I$20:$I$299,'Invoices - Preopening'!$H$20:$H$299,">="&L$6,'Invoices - Preopening'!$H$20:$H$299,"<="&L$7,'Invoices - Preopening'!$C$20:$C$299,'Model - Preopening & Fees'!$B48) -> 0 | M48: =SUMIFS('Invoices - Preopening'!$I$20:$I$299,'Invoices - Preopening'!$H$20:$H$299,">="&M$6,'Invoices - Preopening'!$H$20:$H$299,"<="&M$7,'Invoices - Preopening'!$C$20:$C$299,'Model - Preopening & Fees'!$B48) -> 0 | N48: =SUMIFS('Invoices - Preopening'!$I$20:$I$299,'Invoices - Preopening'!$H$20:$H$299,">="&N$6,'Invoices - Preopening'!$H$20:$H$299,"<="&N$7,'Invoices - Preopening'!$C$20:$C$299,'Model - Preopening & Fees'!$B48) -> 0 | O48: =SUMIFS('Invoices - Preopening'!$I$20:$I$299,'Invoices - Preopening'!$H$20:$H$299,">="&O$6,'Invoices - Preopening'!$H$20:$H$299,"<="&O$7,'Invoices - Preopening'!$C$20:$C$299,'Model - Preopening & Fees'!$B48) -> 0 | P48: =SUMIFS('Invoices - Preopening'!$I$20:$I$299,'Invoices - Preopening'!$H$20:$H$299,">="&P$6,'Invoices - Preopening'!$H$20:$H$299,"<="&P$7,'Invoices - Preopening'!$C$20:$C$299,'Model - Preopening & Fees'!$B48) -> 0 | Q48: =SUMIFS('Invoices - Preopening'!$I$20:$I$299,'Invoices - Preopening'!$H$20:$H$299,">="&Q$6,'Invoices - Preopening'!$H$20:$H$299,"<="&Q$7,'Invoices - Preopening'!$C$20:$C$299,'Model - Preopening & Fees'!$B48) -> 0 | R48: =SUMIFS('Invoices - Preopening'!$I$20:$I$299,'Invoices - Preopening'!$H$20:$H$299,">="&R$6,'Invoices - Preopening'!$H$20:$H$299,"<="&R$7,'Invoices - Preopening'!$C$20:$C$299,'Model - Preopening & Fees'!$B48) -> 0 | S48: =SUMIFS('Invoices - Preopening'!$I$20:$I$299,'Invoices - Preopening'!$H$20:$H$299,">="&S$6,'Invoices - Preopening'!$H$20:$H$299,"<="&S$7,'Invoices - Preopening'!$C$20:$C$299,'Model - Preopening & Fees'!$B48) -> 0 | ... AC48: =SUMIFS('Invoices - Preopening'!$I$20:$I$299,'Invoices - Preopening'!$H$20:$H$299,">="&AC$6,'Invoices - Preopening'!$H$20:$H$299,"<="&AC$7,'Invoices - Preopening'!$C$20:$C$299,'Model - Preopening & Fees'!$B48) -> 0 | AD48: 0 | AE48: 0 | AF48: 0 | AG48: 0 | AH48: 0 | AI48: 0 | AJ48: 0 | AK48: 0 | AL48: 0 | AM48: 5000 | AO48: 0 | AP48: 0 | AQ48: 0 | AR48: 0 | AT48: =-SUMIFS($L48:$AR48,$L$5:$AR$5,AT$5) -> 0 | AU48: =-SUMIFS($L48:$AR48,$L$5:$AR$5,AU$5) -> 0 | AV48: =-SUMIFS($L48:$AR48,$L$5:$AR$5,AV$5) -> 0 | AW48: =-SUMIFS($L48:$AR48,$L$5:$AR$5,AW$5) -> 0 | AX48: =-SUMIFS($L48:$AR48,$L$5:$AR$5,AX$5) -> 0 | AY48: =-SUMIFS($L48:$AR48,$L$5:$AR$5,AY$5) -> 0 | AZ48: =-SUMIFS($L48:$AR48,$L$5:$AR$5,AZ$5) -> 0 | BA48: =-SUMIFS($L48:$AR48,$L$5:$AR$5,BA$5) -> 0 | ... BD48: =-SUMIFS($L48:$AR48,$L$5:$AR$5,BD$5) -> 0 | BF48: =SUM(AT48:BD48) -> -5000
A49: 1 | B49: Equipment Events | D49: Marketing | E49: Aniek | F49: 2000 | G49: =SUMIFS($L49:$AR49,$L$7:$AR$7,"<="&$J$4) -> 0 | H49: =J49-G49 -> 2000 | J49: =SUM(L49:AR49) -> 2000 | L49: =SUMIFS('Invoices - Preopening'!$I$20:$I$299,'Invoices - Preopening'!$H$20:$H$299,">="&L$6,'Invoices - Preopening'!$H$20:$H$299,"<="&L$7,'Invoices - Preopening'!$C$20:$C$299,'Model - Preopening & Fees'!$B49) -> 0 | M49: =SUMIFS('Invoices - Preopening'!$I$20:$I$299,'Invoices - Preopening'!$H$20:$H$299,">="&M$6,'Invoices - Preopening'!$H$20:$H$299,"<="&M$7,'Invoices - Preopening'!$C$20:$C$299,'Model - Preopening & Fees'!$B49) -> 0 | N49: =SUMIFS('Invoices - Preopening'!$I$20:$I$299,'Invoices - Preopening'!$H$20:$H$299,">="&N$6,'Invoices - Preopening'!$H$20:$H$299,"<="&N$7,'Invoices - Preopening'!$C$20:$C$299,'Model - Preopening & Fees'!$B49) -> 0 | O49: =SUMIFS('Invoices - Preopening'!$I$20:$I$299,'Invoices - Preopening'!$H$20:$H$299,">="&O$6,'Invoices - Preopening'!$H$20:$H$299,"<="&O$7,'Invoices - Preopening'!$C$20:$C$299,'Model - Preopening & Fees'!$B49) -> 0 | P49: =SUMIFS('Invoices - Preopening'!$I$20:$I$299,'Invoices - Preopening'!$H$20:$H$299,">="&P$6,'Invoices - Preopening'!$H$20:$H$299,"<="&P$7,'Invoices - Preopening'!$C$20:$C$299,'Model - Preopening & Fees'!$B49) -> 0 | Q49: =SUMIFS('Invoices - Preopening'!$I$20:$I$299,'Invoices - Preopening'!$H$20:$H$299,">="&Q$6,'Invoices - Preopening'!$H$20:$H$299,"<="&Q$7,'Invoices - Preopening'!$C$20:$C$299,'Model - Preopening & Fees'!$B49) -> 0 | R49: =SUMIFS('Invoices - Preopening'!$I$20:$I$299,'Invoices - Preopening'!$H$20:$H$299,">="&R$6,'Invoices - Preopening'!$H$20:$H$299,"<="&R$7,'Invoices - Preopening'!$C$20:$C$299,'Model - Preopening & Fees'!$B49) -> 0 | S49: =SUMIFS('Invoices - Preopening'!$I$20:$I$299,'Invoices - Preopening'!$H$20:$H$299,">="&S$6,'Invoices - Preopening'!$H$20:$H$299,"<="&S$7,'Invoices - Preopening'!$C$20:$C$299,'Model - Preopening & Fees'!$B49) -> 0 | ... AC49: =SUMIFS('Invoices - Preopening'!$I$20:$I$299,'Invoices - Preopening'!$H$20:$H$299,">="&AC$6,'Invoices - Preopening'!$H$20:$H$299,"<="&AC$7,'Invoices - Preopening'!$C$20:$C$299,'Model - Preopening & Fees'!$B49) -> 0 | AD49: 0 | AE49: 0 | AF49: 0 | AG49: 0 | AH49: 0 | AI49: 0 | AJ49: 0 | AK49: 0 | AL49: 0 | AM49: 2000 | AN49: 0 | AO49: 0 | AP49: 0 | AQ49: 0 | AR49: 0 | AT49: =-SUMIFS($L49:$AR49,$L$5:$AR$5,AT$5) -> 0 | AU49: =-SUMIFS($L49:$AR49,$L$5:$AR$5,AU$5) -> 0 | AV49: =-SUMIFS($L49:$AR49,$L$5:$AR$5,AV$5) -> 0 | AW49: =-SUMIFS($L49:$AR49,$L$5:$AR$5,AW$5) -> 0 | AX49: =-SUMIFS($L49:$AR49,$L$5:$AR$5,AX$5) -> 0 | AY49: =-SUMIFS($L49:$AR49,$L$5:$AR$5,AY$5) -> 0 | AZ49: =-SUMIFS($L49:$AR49,$L$5:$AR$5,AZ$5) -> 0 | BA49: =-SUMIFS($L49:$AR49,$L$5:$AR$5,BA$5) -> 0 | ... BD49: =-SUMIFS($L49:$AR49,$L$5:$AR$5,BD$5) -> 0 | BF49: =SUM(AT49:BD49) -> -2000
A50: 1 | B50: Gifting | D50: Marketing | E50: Aniek | F50: 5000 | G50: =SUMIFS($L50:$AR50,$L$7:$AR$7,"<="&$J$4) -> 0 | H50: =J50-G50 -> 5000 | J50: =SUM(L50:AR50) -> 5000 | L50: =SUMIFS('Invoices - Preopening'!$I$20:$I$299,'Invoices - Preopening'!$H$20:$H$299,">="&L$6,'Invoices - Preopening'!$H$20:$H$299,"<="&L$7,'Invoices - Preopening'!$C$20:$C$299,'Model - Preopening & Fees'!$B50) -> 0 | M50: =SUMIFS('Invoices - Preopening'!$I$20:$I$299,'Invoices - Preopening'!$H$20:$H$299,">="&M$6,'Invoices - Preopening'!$H$20:$H$299,"<="&M$7,'Invoices - Preopening'!$C$20:$C$299,'Model - Preopening & Fees'!$B50) -> 0 | N50: =SUMIFS('Invoices - Preopening'!$I$20:$I$299,'Invoices - Preopening'!$H$20:$H$299,">="&N$6,'Invoices - Preopening'!$H$20:$H$299,"<="&N$7,'Invoices - Preopening'!$C$20:$C$299,'Model - Preopening & Fees'!$B50) -> 0 | O50: =SUMIFS('Invoices - Preopening'!$I$20:$I$299,'Invoices - Preopening'!$H$20:$H$299,">="&O$6,'Invoices - Preopening'!$H$20:$H$299,"<="&O$7,'Invoices - Preopening'!$C$20:$C$299,'Model - Preopening & Fees'!$B50) -> 0 | P50: =SUMIFS('Invoices - Preopening'!$I$20:$I$299,'Invoices - Preopening'!$H$20:$H$299,">="&P$6,'Invoices - Preopening'!$H$20:$H$299,"<="&P$7,'Invoices - Preopening'!$C$20:$C$299,'Model - Preopening & Fees'!$B50) -> 0 | Q50: =SUMIFS('Invoices - Preopening'!$I$20:$I$299,'Invoices - Preopening'!$H$20:$H$299,">="&Q$6,'Invoices - Preopening'!$H$20:$H$299,"<="&Q$7,'Invoices - Preopening'!$C$20:$C$299,'Model - Preopening & Fees'!$B50) -> 0 | R50: =SUMIFS('Invoices - Preopening'!$I$20:$I$299,'Invoices - Preopening'!$H$20:$H$299,">="&R$6,'Invoices - Preopening'!$H$20:$H$299,"<="&R$7,'Invoices - Preopening'!$C$20:$C$299,'Model - Preopening & Fees'!$B50) -> 0 | S50: =SUMIFS('Invoices - Preopening'!$I$20:$I$299,'Invoices - Preopening'!$H$20:$H$299,">="&S$6,'Invoices - Preopening'!$H$20:$H$299,"<="&S$7,'Invoices - Preopening'!$C$20:$C$299,'Model - Preopening & Fees'!$B50) -> 0 | ... AC50: =SUMIFS('Invoices - Preopening'!$I$20:$I$299,'Invoices - Preopening'!$H$20:$H$299,">="&AC$6,'Invoices - Preopening'!$H$20:$H$299,"<="&AC$7,'Invoices - Preopening'!$C$20:$C$299,'Model - Preopening & Fees'!$B50) -> 0 | AD50: 0 | AE50: 0 | AF50: 0 | AG50: 0 | AH50: 0 | AI50: 0 | AJ50: 2500 | AK50: 0 | AL50: 0 | AM50: 2500 | AN50: 0 | AO50: 0 | AP50: 0 | AQ50: 0 | AR50: 0 | AT50: =-SUMIFS($L50:$AR50,$L$5:$AR$5,AT$5) -> 0 | AU50: =-SUMIFS($L50:$AR50,$L$5:$AR$5,AU$5) -> 0 | AV50: =-SUMIFS($L50:$AR50,$L$5:$AR$5,AV$5) -> 0 | AW50: =-SUMIFS($L50:$AR50,$L$5:$AR$5,AW$5) -> 0 | AX50: =-SUMIFS($L50:$AR50,$L$5:$AR$5,AX$5) -> 0 | AY50: =-SUMIFS($L50:$AR50,$L$5:$AR$5,AY$5) -> 0 | AZ50: =-SUMIFS($L50:$AR50,$L$5:$AR$5,AZ$5) -> 0 | BA50: =-SUMIFS($L50:$AR50,$L$5:$AR$5,BA$5) -> 0 | ... BD50: =-SUMIFS($L50:$AR50,$L$5:$AR$5,BD$5) -> 0 | BF50: =SUM(AT50:BD50) -> -5000
A51: 1 | B51: Photography Events | D51: Marketing | E51: Aniek | F51: 2000 | G51: =SUMIFS($L51:$AR51,$L$7:$AR$7,"<="&$J$4) -> 0 | H51: =J51-G51 -> 2000 | J51: =SUM(L51:AR51) -> 2000 | L51: =SUMIFS('Invoices - Preopening'!$I$20:$I$299,'Invoices - Preopening'!$H$20:$H$299,">="&L$6,'Invoices - Preopening'!$H$20:$H$299,"<="&L$7,'Invoices - Preopening'!$C$20:$C$299,'Model - Preopening & Fees'!$B51) -> 0 | M51: =SUMIFS('Invoices - Preopening'!$I$20:$I$299,'Invoices - Preopening'!$H$20:$H$299,">="&M$6,'Invoices - Preopening'!$H$20:$H$299,"<="&M$7,'Invoices - Preopening'!$C$20:$C$299,'Model - Preopening & Fees'!$B51) -> 0 | N51: =SUMIFS('Invoices - Preopening'!$I$20:$I$299,'Invoices - Preopening'!$H$20:$H$299,">="&N$6,'Invoices - Preopening'!$H$20:$H$299,"<="&N$7,'Invoices - Preopening'!$C$20:$C$299,'Model - Preopening & Fees'!$B51) -> 0 | O51: =SUMIFS('Invoices - Preopening'!$I$20:$I$299,'Invoices - Preopening'!$H$20:$H$299,">="&O$6,'Invoices - Preopening'!$H$20:$H$299,"<="&O$7,'Invoices - Preopening'!$C$20:$C$299,'Model - Preopening & Fees'!$B51) -> 0 | P51: =SUMIFS('Invoices - Preopening'!$I$20:$I$299,'Invoices - Preopening'!$H$20:$H$299,">="&P$6,'Invoices - Preopening'!$H$20:$H$299,"<="&P$7,'Invoices - Preopening'!$C$20:$C$299,'Model - Preopening & Fees'!$B51) -> 0 | Q51: =SUMIFS('Invoices - Preopening'!$I$20:$I$299,'Invoices - Preopening'!$H$20:$H$299,">="&Q$6,'Invoices - Preopening'!$H$20:$H$299,"<="&Q$7,'Invoices - Preopening'!$C$20:$C$299,'Model - Preopening & Fees'!$B51) -> 0 | R51: =SUMIFS('Invoices - Preopening'!$I$20:$I$299,'Invoices - Preopening'!$H$20:$H$299,">="&R$6,'Invoices - Preopening'!$H$20:$H$299,"<="&R$7,'Invoices - Preopening'!$C$20:$C$299,'Model - Preopening & Fees'!$B51) -> 0 | S51: =SUMIFS('Invoices - Preopening'!$I$20:$I$299,'Invoices - Preopening'!$H$20:$H$299,">="&S$6,'Invoices - Preopening'!$H$20:$H$299,"<="&S$7,'Invoices - Preopening'!$C$20:$C$299,'Model - Preopening & Fees'!$B51) -> 0 | ... AC51: =SUMIFS('Invoices - Preopening'!$I$20:$I$299,'Invoices - Preopening'!$H$20:$H$299,">="&AC$6,'Invoices - Preopening'!$H$20:$H$299,"<="&AC$7,'Invoices - Preopening'!$C$20:$C$299,'Model - Preopening & Fees'!$B51) -> 0 | AD51: 0 | AE51: 0 | AF51: 0 | AG51: 0 | AH51: 0 | AI51: 0 | AJ51: 0 | AK51: 0 | AL51: 0 | AM51: 2000 | AN51: 0 | AO51: 0 | AP51: 0 | AQ51: 0 | AR51: 0 | AT51: =-SUMIFS($L51:$AR51,$L$5:$AR$5,AT$5) -> 0 | AU51: =-SUMIFS($L51:$AR51,$L$5:$AR$5,AU$5) -> 0 | AV51: =-SUMIFS($L51:$AR51,$L$5:$AR$5,AV$5) -> 0 | AW51: =-SUMIFS($L51:$AR51,$L$5:$AR$5,AW$5) -> 0 | AX51: =-SUMIFS($L51:$AR51,$L$5:$AR$5,AX$5) -> 0 | AY51: =-SUMIFS($L51:$AR51,$L$5:$AR$5,AY$5) -> 0 | AZ51: =-SUMIFS($L51:$AR51,$L$5:$AR$5,AZ$5) -> 0 | BA51: =-SUMIFS($L51:$AR51,$L$5:$AR$5,BA$5) -> 0 | ... BD51: =-SUMIFS($L51:$AR51,$L$5:$AR$5,BD$5) -> 0 | BF51: =SUM(AT51:BD51) -> -2000
B52: Total Marketing | F52: =SUM(F14:F51) -> 180083 | G52: =SUM(G12:G48) -> 1000 | H52: =SUM(H14:H51) -> 150632 | J52: =SUM(L52:AR52) -> 151632 | L52: =SUM(L14:L51) -> 0 | M52: =SUM(M14:M51) -> 0 | N52: =SUM(N14:N51) -> 0 | O52: =SUM(O14:O51) -> 0 | P52: =SUM(P14:P51) -> 0 | Q52: =SUM(Q14:Q51) -> 0 | R52: =SUM(R14:R51) -> 0 | S52: =SUM(S14:S51) -> 0 | ... BD52: =SUM(BD14:BD51) -> 0 | BF52: =SUM(AT52:BD52) -> -143632
J53: =J52-H52 -> 1000
B54: Legal
B56: Budget | D56: Bucket | F56: Budget | G56: Spent | H56: Remaining
B57: Contracts Review and Advice | D57: Legal | E57: Kim | F57: 0 | G57: =SUMIFS($L57:$AR57,$L$7:$AR$7,"<="&$J$4) -> 0 | H57: =J57-G57 -> 0 | J57: =SUM(L57:AR57) -> 0 | L57: =SUMIFS('Invoices - Preopening'!$I$20:$I$299,'Invoices - Preopening'!$H$20:$H$299,">="&L$6,'Invoices - Preopening'!$H$20:$H$299,"<="&L$7,'Invoices - Preopening'!$C$20:$C$299,'Model - Preopening & Fees'!$B57) -> 0 | M57: =SUMIFS('Invoices - Preopening'!$I$20:$I$299,'Invoices - Preopening'!$H$20:$H$299,">="&M$6,'Invoices - Preopening'!$H$20:$H$299,"<="&M$7,'Invoices - Preopening'!$C$20:$C$299,'Model - Preopening & Fees'!$B57) -> 0 | N57: =SUMIFS('Invoices - Preopening'!$I$20:$I$299,'Invoices - Preopening'!$H$20:$H$299,">="&N$6,'Invoices - Preopening'!$H$20:$H$299,"<="&N$7,'Invoices - Preopening'!$C$20:$C$299,'Model - Preopening & Fees'!$B57) -> 0 | O57: =SUMIFS('Invoices - Preopening'!$I$20:$I$299,'Invoices - Preopening'!$H$20:$H$299,">="&O$6,'Invoices - Preopening'!$H$20:$H$299,"<="&O$7,'Invoices - Preopening'!$C$20:$C$299,'Model - Preopening & Fees'!$B57) -> 0 | P57: =SUMIFS('Invoices - Preopening'!$I$20:$I$299,'Invoices - Preopening'!$H$20:$H$299,">="&P$6,'Invoices - Preopening'!$H$20:$H$299,"<="&P$7,'Invoices - Preopening'!$C$20:$C$299,'Model - Preopening & Fees'!$B57) -> 0 | Q57: =SUMIFS('Invoices - Preopening'!$I$20:$I$299,'Invoices - Preopening'!$H$20:$H$299,">="&Q$6,'Invoices - Preopening'!$H$20:$H$299,"<="&Q$7,'Invoices - Preopening'!$C$20:$C$299,'Model - Preopening & Fees'!$B57) -> 0 | R57: =SUMIFS('Invoices - Preopening'!$I$20:$I$299,'Invoices - Preopening'!$H$20:$H$299,">="&R$6,'Invoices - Preopening'!$H$20:$H$299,"<="&R$7,'Invoices - Preopening'!$C$20:$C$299,'Model - Preopening & Fees'!$B57) -> 0 | S57: =SUMIFS('Invoices - Preopening'!$I$20:$I$299,'Invoices - Preopening'!$H$20:$H$299,">="&S$6,'Invoices - Preopening'!$H$20:$H$299,"<="&S$7,'Invoices - Preopening'!$C$20:$C$299,'Model - Preopening & Fees'!$B57) -> 0 | ... AC57: =SUMIFS('Invoices - Preopening'!$I$20:$I$299,'Invoices - Preopening'!$H$20:$H$299,">="&AC$6,'Invoices - Preopening'!$H$20:$H$299,"<="&AC$7,'Invoices - Preopening'!$C$20:$C$299,'Model - Preopening & Fees'!$B57) -> 0 | AD57: 0 | AE57: 0 | AF57: 0 | AG57: 0 | AH57: 0 | AI57: 0 | AJ57: 0 | AK57: 0 | AL57: 0 | AM57: 0 | AN57: 0 | AO57: 0 | AP57: 0 | AQ57: 0 | AR57: 0 | AT57: =-SUMIFS($L57:$AR57,$L$5:$AR$5,AT$5) -> 0 | AU57: =-SUMIFS($L57:$AR57,$L$5:$AR$5,AU$5) -> 0 | AV57: =-SUMIFS($L57:$AR57,$L$5:$AR$5,AV$5) -> 0 | AW57: =-SUMIFS($L57:$AR57,$L$5:$AR$5,AW$5) -> 0 | AX57: =-SUMIFS($L57:$AR57,$L$5:$AR$5,AX$5) -> 0 | AY57: =-SUMIFS($L57:$AR57,$L$5:$AR$5,AY$5) -> 0 | AZ57: =-SUMIFS($L57:$AR57,$L$5:$AR$5,AZ$5) -> 0 | BA57: =-SUMIFS($L57:$AR57,$L$5:$AR$5,BA$5) -> 0 | ... BD57: =-SUMIFS($L57:$AR57,$L$5:$AR$5,BD$5) -> 0 | BF57: =SUM(AT57:BD57) -> 0
A58: 1 | B58: Construction Agreement | D58: Legal | E58: Kim | F58: 20000 | G58: =SUMIFS($L58:$AR58,$L$7:$AR$7,"<="&$J$4) -> 29500 | H58: =J58-G58 -> 0 | J58: =SUM(L58:AR58) -> 29500 | L58: =SUMIFS('Invoices - Preopening'!$I$20:$I$299,'Invoices - Preopening'!$H$20:$H$299,">="&L$6,'Invoices - Preopening'!$H$20:$H$299,"<="&L$7,'Invoices - Preopening'!$C$20:$C$299,'Model - Preopening & Fees'!$B58) -> 0 | M58: =SUMIFS('Invoices - Preopening'!$I$20:$I$299,'Invoices - Preopening'!$H$20:$H$299,">="&M$6,'Invoices - Preopening'!$H$20:$H$299,"<="&M$7,'Invoices - Preopening'!$C$20:$C$299,'Model - Preopening & Fees'!$B58) -> 0 | N58: =SUMIFS('Invoices - Preopening'!$I$20:$I$299,'Invoices - Preopening'!$H$20:$H$299,">="&N$6,'Invoices - Preopening'!$H$20:$H$299,"<="&N$7,'Invoices - Preopening'!$C$20:$C$299,'Model - Preopening & Fees'!$B58) -> 0 | O58: =SUMIFS('Invoices - Preopening'!$I$20:$I$299,'Invoices - Preopening'!$H$20:$H$299,">="&O$6,'Invoices - Preopening'!$H$20:$H$299,"<="&O$7,'Invoices - Preopening'!$C$20:$C$299,'Model - Preopening & Fees'!$B58) -> 0 | P58: =SUMIFS('Invoices - Preopening'!$I$20:$I$299,'Invoices - Preopening'!$H$20:$H$299,">="&P$6,'Invoices - Preopening'!$H$20:$H$299,"<="&P$7,'Invoices - Preopening'!$C$20:$C$299,'Model - Preopening & Fees'!$B58) -> 0 | Q58: =SUMIFS('Invoices - Preopening'!$I$20:$I$299,'Invoices - Preopening'!$H$20:$H$299,">="&Q$6,'Invoices - Preopening'!$H$20:$H$299,"<="&Q$7,'Invoices - Preopening'!$C$20:$C$299,'Model - Preopening & Fees'!$B58) -> 0 | R58: =SUMIFS('Invoices - Preopening'!$I$20:$I$299,'Invoices - Preopening'!$H$20:$H$299,">="&R$6,'Invoices - Preopening'!$H$20:$H$299,"<="&R$7,'Invoices - Preopening'!$C$20:$C$299,'Model - Preopening & Fees'!$B58) -> 0 | S58: =SUMIFS('Invoices - Preopening'!$I$20:$I$299,'Invoices - Preopening'!$H$20:$H$299,">="&S$6,'Invoices - Preopening'!$H$20:$H$299,"<="&S$7,'Invoices - Preopening'!$C$20:$C$299,'Model - Preopening & Fees'!$B58) -> 0 | ... AC58: =SUMIFS('Invoices - Preopening'!$I$20:$I$299,'Invoices - Preopening'!$H$20:$H$299,">="&AC$6,'Invoices - Preopening'!$H$20:$H$299,"<="&AC$7,'Invoices - Preopening'!$C$20:$C$299,'Model - Preopening & Fees'!$B58) -> 0 | AD58: 0 | AE58: 0 | AF58: 0 | AG58: 0 | AH58: 0 | AI58: 0 | AJ58: 0 | AK58: 0 | AL58: 0 | AM58: 0 | AN58: 0 | AO58: 0 | AP58: 0 | AQ58: 0 | AR58: 0 | AT58: =-SUMIFS($L58:$AR58,$L$5:$AR$5,AT$5) -> 0 | AU58: =-SUMIFS($L58:$AR58,$L$5:$AR$5,AU$5) -> 0 | AV58: =-SUMIFS($L58:$AR58,$L$5:$AR$5,AV$5) -> 0 | AW58: =-SUMIFS($L58:$AR58,$L$5:$AR$5,AW$5) -> -29500 | AX58: =-SUMIFS($L58:$AR58,$L$5:$AR$5,AX$5) -> 0 | AY58: =-SUMIFS($L58:$AR58,$L$5:$AR$5,AY$5) -> 0 | AZ58: =-SUMIFS($L58:$AR58,$L$5:$AR$5,AZ$5) -> 0 | BA58: =-SUMIFS($L58:$AR58,$L$5:$AR$5,BA$5) -> 0 | ... BD58: =-SUMIFS($L58:$AR58,$L$5:$AR$5,BD$5) -> 0 | BF58: =SUM(AT58:BD58) -> -29500
A59: 1 | B59: Template FF&E contracts | D59: Legal | E59: Kim | F59: 4000 | G59: =SUMIFS($L59:$AR59,$L$7:$AR$7,"<="&$J$4) -> 6835.5 | H59: =J59-G59 -> 0 | J59: =SUM(L59:AR59) -> 6835.5 | L59: =SUMIFS('Invoices - Preopening'!$I$20:$I$299,'Invoices - Preopening'!$H$20:$H$299,">="&L$6,'Invoices - Preopening'!$H$20:$H$299,"<="&L$7,'Invoices - Preopening'!$C$20:$C$299,'Model - Preopening & Fees'!$B59) -> 0 | M59: =SUMIFS('Invoices - Preopening'!$I$20:$I$299,'Invoices - Preopening'!$H$20:$H$299,">="&M$6,'Invoices - Preopening'!$H$20:$H$299,"<="&M$7,'Invoices - Preopening'!$C$20:$C$299,'Model - Preopening & Fees'!$B59) -> 0 | N59: =SUMIFS('Invoices - Preopening'!$I$20:$I$299,'Invoices - Preopening'!$H$20:$H$299,">="&N$6,'Invoices - Preopening'!$H$20:$H$299,"<="&N$7,'Invoices - Preopening'!$C$20:$C$299,'Model - Preopening & Fees'!$B59) -> 0 | O59: =SUMIFS('Invoices - Preopening'!$I$20:$I$299,'Invoices - Preopening'!$H$20:$H$299,">="&O$6,'Invoices - Preopening'!$H$20:$H$299,"<="&O$7,'Invoices - Preopening'!$C$20:$C$299,'Model - Preopening & Fees'!$B59) -> 0 | P59: =SUMIFS('Invoices - Preopening'!$I$20:$I$299,'Invoices - Preopening'!$H$20:$H$299,">="&P$6,'Invoices - Preopening'!$H$20:$H$299,"<="&P$7,'Invoices - Preopening'!$C$20:$C$299,'Model - Preopening & Fees'!$B59) -> 0 | Q59: =SUMIFS('Invoices - Preopening'!$I$20:$I$299,'Invoices - Preopening'!$H$20:$H$299,">="&Q$6,'Invoices - Preopening'!$H$20:$H$299,"<="&Q$7,'Invoices - Preopening'!$C$20:$C$299,'Model - Preopening & Fees'!$B59) -> 0 | R59: =SUMIFS('Invoices - Preopening'!$I$20:$I$299,'Invoices - Preopening'!$H$20:$H$299,">="&R$6,'Invoices - Preopening'!$H$20:$H$299,"<="&R$7,'Invoices - Preopening'!$C$20:$C$299,'Model - Preopening & Fees'!$B59) -> 0 | S59: =SUMIFS('Invoices - Preopening'!$I$20:$I$299,'Invoices - Preopening'!$H$20:$H$299,">="&S$6,'Invoices - Preopening'!$H$20:$H$299,"<="&S$7,'Invoices - Preopening'!$C$20:$C$299,'Model - Preopening & Fees'!$B59) -> 0 | ... AC59: =SUMIFS('Invoices - Preopening'!$I$20:$I$299,'Invoices - Preopening'!$H$20:$H$299,">="&AC$6,'Invoices - Preopening'!$H$20:$H$299,"<="&AC$7,'Invoices - Preopening'!$C$20:$C$299,'Model - Preopening & Fees'!$B59) -> 0 | AD59: 0 | AE59: 0 | AF59: 0 | AG59: 0 | AH59: 0 | AI59: 0 | AJ59: 0 | AK59: 0 | AL59: 0 | AM59: 0 | AN59: 0 | AO59: 0 | AP59: 0 | AQ59: 0 | AR59: 0 | AT59: =-SUMIFS($L59:$AR59,$L$5:$AR$5,AT$5) -> 0 | AU59: =-SUMIFS($L59:$AR59,$L$5:$AR$5,AU$5) -> 0 | AV59: =-SUMIFS($L59:$AR59,$L$5:$AR$5,AV$5) -> 0 | AW59: =-SUMIFS($L59:$AR59,$L$5:$AR$5,AW$5) -> 0 | AX59: =-SUMIFS($L59:$AR59,$L$5:$AR$5,AX$5) -> -6835.5 | AY59: =-SUMIFS($L59:$AR59,$L$5:$AR$5,AY$5) -> 0 | AZ59: =-SUMIFS($L59:$AR59,$L$5:$AR$5,AZ$5) -> 0 | BA59: =-SUMIFS($L59:$AR59,$L$5:$AR$5,BA$5) -> 0 | ... BD59: =-SUMIFS($L59:$AR59,$L$5:$AR$5,BD$5) -> 0 | BF59: =SUM(AT59:BD59) -> -6835.5
A60: 1 | B60: Assistance in the FF&E construction agreement with Factory and Sintesi | D60: Legal | E60: Kim | F60: 16000 | G60: =SUMIFS($L60:$AR60,$L$7:$AR$7,"<="&$J$4) -> 0 | H60: =J60-G60 -> 16000 | J60: =SUM(L60:AR60) -> 16000 | L60: =SUMIFS('Invoices - Preopening'!$I$20:$I$299,'Invoices - Preopening'!$H$20:$H$299,">="&L$6,'Invoices - Preopening'!$H$20:$H$299,"<="&L$7,'Invoices - Preopening'!$C$20:$C$299,'Model - Preopening & Fees'!$B60) -> 0 | M60: =SUMIFS('Invoices - Preopening'!$I$20:$I$299,'Invoices - Preopening'!$H$20:$H$299,">="&M$6,'Invoices - Preopening'!$H$20:$H$299,"<="&M$7,'Invoices - Preopening'!$C$20:$C$299,'Model - Preopening & Fees'!$B60) -> 0 | N60: =SUMIFS('Invoices - Preopening'!$I$20:$I$299,'Invoices - Preopening'!$H$20:$H$299,">="&N$6,'Invoices - Preopening'!$H$20:$H$299,"<="&N$7,'Invoices - Preopening'!$C$20:$C$299,'Model - Preopening & Fees'!$B60) -> 0 | O60: =SUMIFS('Invoices - Preopening'!$I$20:$I$299,'Invoices - Preopening'!$H$20:$H$299,">="&O$6,'Invoices - Preopening'!$H$20:$H$299,"<="&O$7,'Invoices - Preopening'!$C$20:$C$299,'Model - Preopening & Fees'!$B60) -> 0 | P60: =SUMIFS('Invoices - Preopening'!$I$20:$I$299,'Invoices - Preopening'!$H$20:$H$299,">="&P$6,'Invoices - Preopening'!$H$20:$H$299,"<="&P$7,'Invoices - Preopening'!$C$20:$C$299,'Model - Preopening & Fees'!$B60) -> 0 | Q60: =SUMIFS('Invoices - Preopening'!$I$20:$I$299,'Invoices - Preopening'!$H$20:$H$299,">="&Q$6,'Invoices - Preopening'!$H$20:$H$299,"<="&Q$7,'Invoices - Preopening'!$C$20:$C$299,'Model - Preopening & Fees'!$B60) -> 0 | R60: =SUMIFS('Invoices - Preopening'!$I$20:$I$299,'Invoices - Preopening'!$H$20:$H$299,">="&R$6,'Invoices - Preopening'!$H$20:$H$299,"<="&R$7,'Invoices - Preopening'!$C$20:$C$299,'Model - Preopening & Fees'!$B60) -> 0 | S60: =SUMIFS('Invoices - Preopening'!$I$20:$I$299,'Invoices - Preopening'!$H$20:$H$299,">="&S$6,'Invoices - Preopening'!$H$20:$H$299,"<="&S$7,'Invoices - Preopening'!$C$20:$C$299,'Model - Preopening & Fees'!$B60) -> 0 | ... AC60: =SUMIFS('Invoices - Preopening'!$I$20:$I$299,'Invoices - Preopening'!$H$20:$H$299,">="&AC$6,'Invoices - Preopening'!$H$20:$H$299,"<="&AC$7,'Invoices - Preopening'!$C$20:$C$299,'Model - Preopening & Fees'!$B60) -> 0 | AD60: 16000 | AE60: 0 | AF60: 0 | AG60: 0 | AH60: 0 | AI60: 0 | AJ60: 0 | AK60: 0 | AL60: 0 | AM60: 0 | AN60: 0 | AO60: 0 | AP60: 0 | AQ60: 0 | AR60: 0 | AT60: =-SUMIFS($L60:$AR60,$L$5:$AR$5,AT$5) -> 0 | AU60: =-SUMIFS($L60:$AR60,$L$5:$AR$5,AU$5) -> 0 | AV60: =-SUMIFS($L60:$AR60,$L$5:$AR$5,AV$5) -> 0 | AW60: =-SUMIFS($L60:$AR60,$L$5:$AR$5,AW$5) -> 0 | AX60: =-SUMIFS($L60:$AR60,$L$5:$AR$5,AX$5) -> 0 | AY60: =-SUMIFS($L60:$AR60,$L$5:$AR$5,AY$5) -> 0 | AZ60: =-SUMIFS($L60:$AR60,$L$5:$AR$5,AZ$5) -> -16000 | BA60: =-SUMIFS($L60:$AR60,$L$5:$AR$5,BA$5) -> 0 | ... BD60: =-SUMIFS($L60:$AR60,$L$5:$AR$5,BD$5) -> 0 | BF60: =SUM(AT60:BD60) -> -16000
A61: 1 | B61: Legal Support Contracts during 2026 | D61: Legal | E61: Kim | F61: 12000 | G61: =SUMIFS($L61:$AR61,$L$7:$AR$7,"<="&$J$4) -> 0 | H61: =J61-G61 -> 12000 | J61: =SUM(L61:AR61) -> 12000 | L61: =SUMIFS('Invoices - Preopening'!$I$20:$I$299,'Invoices - Preopening'!$H$20:$H$299,">="&L$6,'Invoices - Preopening'!$H$20:$H$299,"<="&L$7,'Invoices - Preopening'!$C$20:$C$299,'Model - Preopening & Fees'!$B61) -> 0 | M61: =SUMIFS('Invoices - Preopening'!$I$20:$I$299,'Invoices - Preopening'!$H$20:$H$299,">="&M$6,'Invoices - Preopening'!$H$20:$H$299,"<="&M$7,'Invoices - Preopening'!$C$20:$C$299,'Model - Preopening & Fees'!$B61) -> 0 | N61: =SUMIFS('Invoices - Preopening'!$I$20:$I$299,'Invoices - Preopening'!$H$20:$H$299,">="&N$6,'Invoices - Preopening'!$H$20:$H$299,"<="&N$7,'Invoices - Preopening'!$C$20:$C$299,'Model - Preopening & Fees'!$B61) -> 0 | O61: =SUMIFS('Invoices - Preopening'!$I$20:$I$299,'Invoices - Preopening'!$H$20:$H$299,">="&O$6,'Invoices - Preopening'!$H$20:$H$299,"<="&O$7,'Invoices - Preopening'!$C$20:$C$299,'Model - Preopening & Fees'!$B61) -> 0 | P61: =SUMIFS('Invoices - Preopening'!$I$20:$I$299,'Invoices - Preopening'!$H$20:$H$299,">="&P$6,'Invoices - Preopening'!$H$20:$H$299,"<="&P$7,'Invoices - Preopening'!$C$20:$C$299,'Model - Preopening & Fees'!$B61) -> 0 | Q61: =SUMIFS('Invoices - Preopening'!$I$20:$I$299,'Invoices - Preopening'!$H$20:$H$299,">="&Q$6,'Invoices - Preopening'!$H$20:$H$299,"<="&Q$7,'Invoices - Preopening'!$C$20:$C$299,'Model - Preopening & Fees'!$B61) -> 0 | R61: =SUMIFS('Invoices - Preopening'!$I$20:$I$299,'Invoices - Preopening'!$H$20:$H$299,">="&R$6,'Invoices - Preopening'!$H$20:$H$299,"<="&R$7,'Invoices - Preopening'!$C$20:$C$299,'Model - Preopening & Fees'!$B61) -> 0 | S61: =SUMIFS('Invoices - Preopening'!$I$20:$I$299,'Invoices - Preopening'!$H$20:$H$299,">="&S$6,'Invoices - Preopening'!$H$20:$H$299,"<="&S$7,'Invoices - Preopening'!$C$20:$C$299,'Model - Preopening & Fees'!$B61) -> 0 | ... AC61: =SUMIFS('Invoices - Preopening'!$I$20:$I$299,'Invoices - Preopening'!$H$20:$H$299,">="&AC$6,'Invoices - Preopening'!$H$20:$H$299,"<="&AC$7,'Invoices - Preopening'!$C$20:$C$299,'Model - Preopening & Fees'!$B61) -> 0 | AD61: 0 | AE61: 0 | AF61: 2000 | AG61: 2000 | AH61: 2000 | AI61: 2000 | AJ61: 2000 | AK61: 2000 | AL61: 0 | AM61: 0 | AN61: 0 | AO61: 0 | AP61: 0 | AQ61: 0 | AR61: 0 | AT61: =-SUMIFS($L61:$AR61,$L$5:$AR$5,AT$5) -> 0 | AU61: =-SUMIFS($L61:$AR61,$L$5:$AR$5,AU$5) -> 0 | AV61: =-SUMIFS($L61:$AR61,$L$5:$AR$5,AV$5) -> 0 | AW61: =-SUMIFS($L61:$AR61,$L$5:$AR$5,AW$5) -> 0 | AX61: =-SUMIFS($L61:$AR61,$L$5:$AR$5,AX$5) -> 0 | AY61: =-SUMIFS($L61:$AR61,$L$5:$AR$5,AY$5) -> 0 | AZ61: =-SUMIFS($L61:$AR61,$L$5:$AR$5,AZ$5) -> -2000 | BA61: =-SUMIFS($L61:$AR61,$L$5:$AR$5,BA$5) -> -6000 | ... BD61: =-SUMIFS($L61:$AR61,$L$5:$AR$5,BD$5) -> 0 | BF61: =SUM(AT61:BD61) -> -12000
B62: Corporate Work to Date | D62: Legal | E62: Kim | F62: 0 | G62: =SUMIFS($L62:$AR62,$L$7:$AR$7,"<="&$J$4) -> 0 | H62: =J62-G62 -> 0 | J62: =SUM(L62:AR62) -> 0 | L62: =SUMIFS('Invoices - Preopening'!$I$20:$I$299,'Invoices - Preopening'!$H$20:$H$299,">="&L$6,'Invoices - Preopening'!$H$20:$H$299,"<="&L$7,'Invoices - Preopening'!$C$20:$C$299,'Model - Preopening & Fees'!$B62) -> 0 | M62: =SUMIFS('Invoices - Preopening'!$I$20:$I$299,'Invoices - Preopening'!$H$20:$H$299,">="&M$6,'Invoices - Preopening'!$H$20:$H$299,"<="&M$7,'Invoices - Preopening'!$C$20:$C$299,'Model - Preopening & Fees'!$B62) -> 0 | N62: =SUMIFS('Invoices - Preopening'!$I$20:$I$299,'Invoices - Preopening'!$H$20:$H$299,">="&N$6,'Invoices - Preopening'!$H$20:$H$299,"<="&N$7,'Invoices - Preopening'!$C$20:$C$299,'Model - Preopening & Fees'!$B62) -> 0 | O62: =SUMIFS('Invoices - Preopening'!$I$20:$I$299,'Invoices - Preopening'!$H$20:$H$299,">="&O$6,'Invoices - Preopening'!$H$20:$H$299,"<="&O$7,'Invoices - Preopening'!$C$20:$C$299,'Model - Preopening & Fees'!$B62) -> 0 | P62: =SUMIFS('Invoices - Preopening'!$I$20:$I$299,'Invoices - Preopening'!$H$20:$H$299,">="&P$6,'Invoices - Preopening'!$H$20:$H$299,"<="&P$7,'Invoices - Preopening'!$C$20:$C$299,'Model - Preopening & Fees'!$B62) -> 0 | Q62: =SUMIFS('Invoices - Preopening'!$I$20:$I$299,'Invoices - Preopening'!$H$20:$H$299,">="&Q$6,'Invoices - Preopening'!$H$20:$H$299,"<="&Q$7,'Invoices - Preopening'!$C$20:$C$299,'Model - Preopening & Fees'!$B62) -> 0 | R62: =SUMIFS('Invoices - Preopening'!$I$20:$I$299,'Invoices - Preopening'!$H$20:$H$299,">="&R$6,'Invoices - Preopening'!$H$20:$H$299,"<="&R$7,'Invoices - Preopening'!$C$20:$C$299,'Model - Preopening & Fees'!$B62) -> 0 | S62: =SUMIFS('Invoices - Preopening'!$I$20:$I$299,'Invoices - Preopening'!$H$20:$H$299,">="&S$6,'Invoices - Preopening'!$H$20:$H$299,"<="&S$7,'Invoices - Preopening'!$C$20:$C$299,'Model - Preopening & Fees'!$B62) -> 0 | ... AC62: =SUMIFS('Invoices - Preopening'!$I$20:$I$299,'Invoices - Preopening'!$H$20:$H$299,">="&AC$6,'Invoices - Preopening'!$H$20:$H$299,"<="&AC$7,'Invoices - Preopening'!$C$20:$C$299,'Model - Preopening & Fees'!$B62) -> 0 | AD62: 0 | AE62: 0 | AF62: 0 | AG62: 0 | AH62: 0 | AI62: 0 | AJ62: 0 | AK62: 0 | AL62: 0 | AM62: 0 | AN62: 0 | AO62: 0 | AP62: 0 | AQ62: 0 | AR62: 0 | AT62: =-SUMIFS($L62:$AR62,$L$5:$AR$5,AT$5) -> 0 | AU62: =-SUMIFS($L62:$AR62,$L$5:$AR$5,AU$5) -> 0 | AV62: =-SUMIFS($L62:$AR62,$L$5:$AR$5,AV$5) -> 0 | AW62: =-SUMIFS($L62:$AR62,$L$5:$AR$5,AW$5) -> 0 | AX62: =-SUMIFS($L62:$AR62,$L$5:$AR$5,AX$5) -> 0 | AY62: =-SUMIFS($L62:$AR62,$L$5:$AR$5,AY$5) -> 0 | AZ62: =-SUMIFS($L62:$AR62,$L$5:$AR$5,AZ$5) -> 0 | BA62: =-SUMIFS($L62:$AR62,$L$5:$AR$5,BA$5) -> 0 | ... BD62: =-SUMIFS($L62:$AR62,$L$5:$AR$5,BD$5) -> 0 | BF62: =SUM(AT62:BD62) -> 0
A63: 1 | B63: Corporate Work 2026 (if necessary) | D63: Legal | E63: Kim | F63: 12000 | G63: =SUMIFS($L63:$AR63,$L$7:$AR$7,"<="&$J$4) -> 0 | H63: =J63-G63 -> 12000 | J63: =SUM(L63:AR63) -> 12000 | L63: =SUMIFS('Invoices - Preopening'!$I$20:$I$299,'Invoices - Preopening'!$H$20:$H$299,">="&L$6,'Invoices - Preopening'!$H$20:$H$299,"<="&L$7,'Invoices - Preopening'!$C$20:$C$299,'Model - Preopening & Fees'!$B63) -> 0 | M63: =SUMIFS('Invoices - Preopening'!$I$20:$I$299,'Invoices - Preopening'!$H$20:$H$299,">="&M$6,'Invoices - Preopening'!$H$20:$H$299,"<="&M$7,'Invoices - Preopening'!$C$20:$C$299,'Model - Preopening & Fees'!$B63) -> 0 | N63: =SUMIFS('Invoices - Preopening'!$I$20:$I$299,'Invoices - Preopening'!$H$20:$H$299,">="&N$6,'Invoices - Preopening'!$H$20:$H$299,"<="&N$7,'Invoices - Preopening'!$C$20:$C$299,'Model - Preopening & Fees'!$B63) -> 0 | O63: =SUMIFS('Invoices - Preopening'!$I$20:$I$299,'Invoices - Preopening'!$H$20:$H$299,">="&O$6,'Invoices - Preopening'!$H$20:$H$299,"<="&O$7,'Invoices - Preopening'!$C$20:$C$299,'Model - Preopening & Fees'!$B63) -> 0 | P63: =SUMIFS('Invoices - Preopening'!$I$20:$I$299,'Invoices - Preopening'!$H$20:$H$299,">="&P$6,'Invoices - Preopening'!$H$20:$H$299,"<="&P$7,'Invoices - Preopening'!$C$20:$C$299,'Model - Preopening & Fees'!$B63) -> 0 | Q63: =SUMIFS('Invoices - Preopening'!$I$20:$I$299,'Invoices - Preopening'!$H$20:$H$299,">="&Q$6,'Invoices - Preopening'!$H$20:$H$299,"<="&Q$7,'Invoices - Preopening'!$C$20:$C$299,'Model - Preopening & Fees'!$B63) -> 0 | R63: =SUMIFS('Invoices - Preopening'!$I$20:$I$299,'Invoices - Preopening'!$H$20:$H$299,">="&R$6,'Invoices - Preopening'!$H$20:$H$299,"<="&R$7,'Invoices - Preopening'!$C$20:$C$299,'Model - Preopening & Fees'!$B63) -> 0 | S63: =SUMIFS('Invoices - Preopening'!$I$20:$I$299,'Invoices - Preopening'!$H$20:$H$299,">="&S$6,'Invoices - Preopening'!$H$20:$H$299,"<="&S$7,'Invoices - Preopening'!$C$20:$C$299,'Model - Preopening & Fees'!$B63) -> 0 | ... AC63: =SUMIFS('Invoices - Preopening'!$I$20:$I$299,'Invoices - Preopening'!$H$20:$H$299,">="&AC$6,'Invoices - Preopening'!$H$20:$H$299,"<="&AC$7,'Invoices - Preopening'!$C$20:$C$299,'Model - Preopening & Fees'!$B63) -> 0 | AD63: 0 | AE63: 0 | AF63: 2000 | AG63: 2000 | AH63: 2000 | AI63: 2000 | AJ63: 2000 | AK63: 2000 | AL63: 0 | AM63: 0 | AN63: 0 | AO63: 0 | AP63: 0 | AQ63: 0 | AR63: 0 | AT63: =-SUMIFS($L63:$AR63,$L$5:$AR$5,AT$5) -> 0 | AU63: =-SUMIFS($L63:$AR63,$L$5:$AR$5,AU$5) -> 0 | AV63: =-SUMIFS($L63:$AR63,$L$5:$AR$5,AV$5) -> 0 | AW63: =-SUMIFS($L63:$AR63,$L$5:$AR$5,AW$5) -> 0 | AX63: =-SUMIFS($L63:$AR63,$L$5:$AR$5,AX$5) -> 0 | AY63: =-SUMIFS($L63:$AR63,$L$5:$AR$5,AY$5) -> 0 | AZ63: =-SUMIFS($L63:$AR63,$L$5:$AR$5,AZ$5) -> -2000 | BA63: =-SUMIFS($L63:$AR63,$L$5:$AR$5,BA$5) -> -6000 | ... BD63: =-SUMIFS($L63:$AR63,$L$5:$AR$5,BD$5) -> 0 | BF63: =SUM(AT63:BD63) -> -12000
A64: 1 | B64: Second opinion related to labour and employment pre closing Hotel Corona | D64: Legal | E64: Kim | F64: 4000 | G64: =SUMIFS($L64:$AR64,$L$7:$AR$7,"<="&$J$4) -> 0 | H64: =J64-G64 -> 0 | J64: =SUM(L64:AR64) -> 0 | L64: =SUMIFS('Invoices - Preopening'!$I$20:$I$299,'Invoices - Preopening'!$H$20:$H$299,">="&L$6,'Invoices - Preopening'!$H$20:$H$299,"<="&L$7,'Invoices - Preopening'!$C$20:$C$299,'Model - Preopening & Fees'!$B64) -> 0 | M64: =SUMIFS('Invoices - Preopening'!$I$20:$I$299,'Invoices - Preopening'!$H$20:$H$299,">="&M$6,'Invoices - Preopening'!$H$20:$H$299,"<="&M$7,'Invoices - Preopening'!$C$20:$C$299,'Model - Preopening & Fees'!$B64) -> 0 | N64: =SUMIFS('Invoices - Preopening'!$I$20:$I$299,'Invoices - Preopening'!$H$20:$H$299,">="&N$6,'Invoices - Preopening'!$H$20:$H$299,"<="&N$7,'Invoices - Preopening'!$C$20:$C$299,'Model - Preopening & Fees'!$B64) -> 0 | O64: =SUMIFS('Invoices - Preopening'!$I$20:$I$299,'Invoices - Preopening'!$H$20:$H$299,">="&O$6,'Invoices - Preopening'!$H$20:$H$299,"<="&O$7,'Invoices - Preopening'!$C$20:$C$299,'Model - Preopening & Fees'!$B64) -> 0 | P64: =SUMIFS('Invoices - Preopening'!$I$20:$I$299,'Invoices - Preopening'!$H$20:$H$299,">="&P$6,'Invoices - Preopening'!$H$20:$H$299,"<="&P$7,'Invoices - Preopening'!$C$20:$C$299,'Model - Preopening & Fees'!$B64) -> 0 | Q64: =SUMIFS('Invoices - Preopening'!$I$20:$I$299,'Invoices - Preopening'!$H$20:$H$299,">="&Q$6,'Invoices - Preopening'!$H$20:$H$299,"<="&Q$7,'Invoices - Preopening'!$C$20:$C$299,'Model - Preopening & Fees'!$B64) -> 0 | R64: =SUMIFS('Invoices - Preopening'!$I$20:$I$299,'Invoices - Preopening'!$H$20:$H$299,">="&R$6,'Invoices - Preopening'!$H$20:$H$299,"<="&R$7,'Invoices - Preopening'!$C$20:$C$299,'Model - Preopening & Fees'!$B64) -> 0 | S64: =SUMIFS('Invoices - Preopening'!$I$20:$I$299,'Invoices - Preopening'!$H$20:$H$299,">="&S$6,'Invoices - Preopening'!$H$20:$H$299,"<="&S$7,'Invoices - Preopening'!$C$20:$C$299,'Model - Preopening & Fees'!$B64) -> 0 | ... AC64: =SUMIFS('Invoices - Preopening'!$I$20:$I$299,'Invoices - Preopening'!$H$20:$H$299,">="&AC$6,'Invoices - Preopening'!$H$20:$H$299,"<="&AC$7,'Invoices - Preopening'!$C$20:$C$299,'Model - Preopening & Fees'!$B64) -> 0 | AD64: 0 | AE64: 0 | AF64: 0 | AG64: 0 | AH64: 0 | AI64: 0 | AJ64: 0 | AK64: 0 | AL64: 0 | AM64: 0 | AN64: 0 | AO64: 0 | AP64: 0 | AQ64: 0 | AR64: 0 | AT64: =-SUMIFS($L64:$AR64,$L$5:$AR$5,AT$5) -> 0 | AU64: =-SUMIFS($L64:$AR64,$L$5:$AR$5,AU$5) -> 0 | AV64: =-SUMIFS($L64:$AR64,$L$5:$AR$5,AV$5) -> 0 | AW64: =-SUMIFS($L64:$AR64,$L$5:$AR$5,AW$5) -> 0 | AX64: =-SUMIFS($L64:$AR64,$L$5:$AR$5,AX$5) -> 0 | AY64: =-SUMIFS($L64:$AR64,$L$5:$AR$5,AY$5) -> 0 | AZ64: =-SUMIFS($L64:$AR64,$L$5:$AR$5,AZ$5) -> 0 | BA64: =-SUMIFS($L64:$AR64,$L$5:$AR$5,BA$5) -> 0 | ... BD64: =-SUMIFS($L64:$AR64,$L$5:$AR$5,BD$5) -> 0 | BF64: =SUM(AT64:BD64) -> 0
A65: 1 | B65: Contingency/Italian law queries during the construction phase Jan-Dec 2026 | D65: Legal | E65: Kim | F65: 7000 | G65: =SUMIFS($L65:$AR65,$L$7:$AR$7,"<="&$J$4) -> 0 | H65: =J65-G65 -> 7000 | J65: =SUM(L65:AR65) -> 7000 | L65: =SUMIFS('Invoices - Preopening'!$I$20:$I$299,'Invoices - Preopening'!$H$20:$H$299,">="&L$6,'Invoices - Preopening'!$H$20:$H$299,"<="&L$7,'Invoices - Preopening'!$C$20:$C$299,'Model - Preopening & Fees'!$B65) -> 0 | M65: =SUMIFS('Invoices - Preopening'!$I$20:$I$299,'Invoices - Preopening'!$H$20:$H$299,">="&M$6,'Invoices - Preopening'!$H$20:$H$299,"<="&M$7,'Invoices - Preopening'!$C$20:$C$299,'Model - Preopening & Fees'!$B65) -> 0 | N65: =SUMIFS('Invoices - Preopening'!$I$20:$I$299,'Invoices - Preopening'!$H$20:$H$299,">="&N$6,'Invoices - Preopening'!$H$20:$H$299,"<="&N$7,'Invoices - Preopening'!$C$20:$C$299,'Model - Preopening & Fees'!$B65) -> 0 | O65: =SUMIFS('Invoices - Preopening'!$I$20:$I$299,'Invoices - Preopening'!$H$20:$H$299,">="&O$6,'Invoices - Preopening'!$H$20:$H$299,"<="&O$7,'Invoices - Preopening'!$C$20:$C$299,'Model - Preopening & Fees'!$B65) -> 0 | P65: =SUMIFS('Invoices - Preopening'!$I$20:$I$299,'Invoices - Preopening'!$H$20:$H$299,">="&P$6,'Invoices - Preopening'!$H$20:$H$299,"<="&P$7,'Invoices - Preopening'!$C$20:$C$299,'Model - Preopening & Fees'!$B65) -> 0 | Q65: =SUMIFS('Invoices - Preopening'!$I$20:$I$299,'Invoices - Preopening'!$H$20:$H$299,">="&Q$6,'Invoices - Preopening'!$H$20:$H$299,"<="&Q$7,'Invoices - Preopening'!$C$20:$C$299,'Model - Preopening & Fees'!$B65) -> 0 | R65: =SUMIFS('Invoices - Preopening'!$I$20:$I$299,'Invoices - Preopening'!$H$20:$H$299,">="&R$6,'Invoices - Preopening'!$H$20:$H$299,"<="&R$7,'Invoices - Preopening'!$C$20:$C$299,'Model - Preopening & Fees'!$B65) -> 0 | S65: =SUMIFS('Invoices - Preopening'!$I$20:$I$299,'Invoices - Preopening'!$H$20:$H$299,">="&S$6,'Invoices - Preopening'!$H$20:$H$299,"<="&S$7,'Invoices - Preopening'!$C$20:$C$299,'Model - Preopening & Fees'!$B65) -> 0 | ... AC65: =SUMIFS('Invoices - Preopening'!$I$20:$I$299,'Invoices - Preopening'!$H$20:$H$299,">="&AC$6,'Invoices - Preopening'!$H$20:$H$299,"<="&AC$7,'Invoices - Preopening'!$C$20:$C$299,'Model - Preopening & Fees'!$B65) -> 0 | AD65: 0 | AE65: 1000 | AF65: 1000 | AG65: 1000 | AH65: 1000 | AI65: 1000 | AJ65: 1000 | AK65: 1000 | AL65: 0 | AM65: 0 | AN65: 0 | AO65: 0 | AP65: 0 | AQ65: 0 | AR65: 0 | AT65: =-SUMIFS($L65:$AR65,$L$5:$AR$5,AT$5) -> 0 | AU65: =-SUMIFS($L65:$AR65,$L$5:$AR$5,AU$5) -> 0 | AV65: =-SUMIFS($L65:$AR65,$L$5:$AR$5,AV$5) -> 0 | AW65: =-SUMIFS($L65:$AR65,$L$5:$AR$5,AW$5) -> 0 | AX65: =-SUMIFS($L65:$AR65,$L$5:$AR$5,AX$5) -> 0 | AY65: =-SUMIFS($L65:$AR65,$L$5:$AR$5,AY$5) -> 0 | AZ65: =-SUMIFS($L65:$AR65,$L$5:$AR$5,AZ$5) -> -2000 | BA65: =-SUMIFS($L65:$AR65,$L$5:$AR$5,BA$5) -> -3000 | ... BD65: =-SUMIFS($L65:$AR65,$L$5:$AR$5,BD$5) -> 0 | BF65: =SUM(AT65:BD65) -> -7000
B66: Total Legal | F66: =SUM(F57:F65) -> 75000 | G66: =SUM(G57:G65) -> 36335.5 | H66: =SUM(H57:H65) -> 47000 | J66: =SUM(L66:AR66) -> 83335.5 | L66: =SUM(L57:L65) -> 0 | M66: =SUM(M57:M65) -> 0 | N66: =SUM(N57:N65) -> 0 | O66: =SUM(O57:O65) -> 0 | P66: =SUM(P57:P65) -> 0 | Q66: =SUM(Q57:Q65) -> 0 | R66: =SUM(R57:R65) -> 0 | S66: =SUM(S57:S65) -> 0 | ... AR66: =SUM(AR57:AR65) -> 0 | AT66: =SUM(AT57:AT65) -> 0 | AU66: =SUM(AU57:AU65) -> 0 | AV66: =SUM(AV57:AV65) -> 0 | AW66: =SUM(AW57:AW65) -> -29500 | AX66: =SUM(AX57:AX65) -> -6835.5 | AY66: =SUM(AY57:AY65) -> 0 | AZ66: =SUM(AZ57:AZ65) -> -22000 | BA66: =SUM(BA57:BA65) -> -15000 | ... BD66: =SUM(BD57:BD65) -> 0 | BF66: =SUM(AT66:BD66) -> -83335.5
B68: HR
B70: Budget | D70: Bucket | F70: Budget | G70: Spent | H70: Remaining
B72: Pre-Opening Training & Compliance Budget
A73: 1 | B73: Mandatory Compliance Training | D73: HR | E73: Joyce | F73: 16800 | G73: =SUMIFS($L73:$AR73,$L$7:$AR$7,"<="&$J$4) -> 0 | H73: =J73-G73 -> 12800 | J73: =SUM(L73:AR73) -> 12800 | L73: =SUMIFS('Invoices - Preopening'!$I$20:$I$299,'Invoices - Preopening'!$H$20:$H$299,">="&L$6,'Invoices - Preopening'!$H$20:$H$299,"<="&L$7,'Invoices - Preopening'!$C$20:$C$299,'Model - Preopening & Fees'!$B73) -> 0 | M73: =SUMIFS('Invoices - Preopening'!$I$20:$I$299,'Invoices - Preopening'!$H$20:$H$299,">="&M$6,'Invoices - Preopening'!$H$20:$H$299,"<="&M$7,'Invoices - Preopening'!$C$20:$C$299,'Model - Preopening & Fees'!$B73) -> 0 | N73: =SUMIFS('Invoices - Preopening'!$I$20:$I$299,'Invoices - Preopening'!$H$20:$H$299,">="&N$6,'Invoices - Preopening'!$H$20:$H$299,"<="&N$7,'Invoices - Preopening'!$C$20:$C$299,'Model - Preopening & Fees'!$B73) -> 0 | O73: =SUMIFS('Invoices - Preopening'!$I$20:$I$299,'Invoices - Preopening'!$H$20:$H$299,">="&O$6,'Invoices - Preopening'!$H$20:$H$299,"<="&O$7,'Invoices - Preopening'!$C$20:$C$299,'Model - Preopening & Fees'!$B73) -> 0 | P73: =SUMIFS('Invoices - Preopening'!$I$20:$I$299,'Invoices - Preopening'!$H$20:$H$299,">="&P$6,'Invoices - Preopening'!$H$20:$H$299,"<="&P$7,'Invoices - Preopening'!$C$20:$C$299,'Model - Preopening & Fees'!$B73) -> 0 | Q73: =SUMIFS('Invoices - Preopening'!$I$20:$I$299,'Invoices - Preopening'!$H$20:$H$299,">="&Q$6,'Invoices - Preopening'!$H$20:$H$299,"<="&Q$7,'Invoices - Preopening'!$C$20:$C$299,'Model - Preopening & Fees'!$B73) -> 0 | R73: =SUMIFS('Invoices - Preopening'!$I$20:$I$299,'Invoices - Preopening'!$H$20:$H$299,">="&R$6,'Invoices - Preopening'!$H$20:$H$299,"<="&R$7,'Invoices - Preopening'!$C$20:$C$299,'Model - Preopening & Fees'!$B73) -> 0 | S73: =SUMIFS('Invoices - Preopening'!$I$20:$I$299,'Invoices - Preopening'!$H$20:$H$299,">="&S$6,'Invoices - Preopening'!$H$20:$H$299,"<="&S$7,'Invoices - Preopening'!$C$20:$C$299,'Model - Preopening & Fees'!$B73) -> 0 | ... AC73: =SUMIFS('Invoices - Preopening'!$I$20:$I$299,'Invoices - Preopening'!$H$20:$H$299,">="&AC$6,'Invoices - Preopening'!$H$20:$H$299,"<="&AC$7,'Invoices - Preopening'!$C$20:$C$299,'Model - Preopening & Fees'!$B73) -> 0 | AD73: 0 | AE73: 0 | AF73: 0 | AG73: 0 | AH73: 5000 | AI73: 5000 | AJ73: 2800 | AK73: 0 | AL73: 0 | AM73: 0 | AN73: 0 | AO73: 0 | AP73: 0 | AQ73: 0 | AR73: 0 | AT73: =-SUMIFS($L73:$AR73,$L$5:$AR$5,AT$5) -> 0 | AU73: =-SUMIFS($L73:$AR73,$L$5:$AR$5,AU$5) -> 0 | AV73: =-SUMIFS($L73:$AR73,$L$5:$AR$5,AV$5) -> 0 | AW73: =-SUMIFS($L73:$AR73,$L$5:$AR$5,AW$5) -> 0 | AX73: =-SUMIFS($L73:$AR73,$L$5:$AR$5,AX$5) -> 0 | AY73: =-SUMIFS($L73:$AR73,$L$5:$AR$5,AY$5) -> 0 | AZ73: =-SUMIFS($L73:$AR73,$L$5:$AR$5,AZ$5) -> 0 | BA73: =-SUMIFS($L73:$AR73,$L$5:$AR$5,BA$5) -> -10000 | ... BD73: =-SUMIFS($L73:$AR73,$L$5:$AR$5,BD$5) -> 0 | BF73: =SUM(AT73:BD73) -> -12800
A74: 1 | B74: External Meeting Room & Lunch (2 weeks) | D74: HR | E74: Joyce | F74: 12000 | G74: =SUMIFS($L74:$AR74,$L$7:$AR$7,"<="&$J$4) -> 0 | H74: =J74-G74 -> 12000 | J74: =SUM(L74:AR74) -> 12000 | L74: =SUMIFS('Invoices - Preopening'!$I$20:$I$299,'Invoices - Preopening'!$H$20:$H$299,">="&L$6,'Invoices - Preopening'!$H$20:$H$299,"<="&L$7,'Invoices - Preopening'!$C$20:$C$299,'Model - Preopening & Fees'!$B74) -> 0 | M74: =SUMIFS('Invoices - Preopening'!$I$20:$I$299,'Invoices - Preopening'!$H$20:$H$299,">="&M$6,'Invoices - Preopening'!$H$20:$H$299,"<="&M$7,'Invoices - Preopening'!$C$20:$C$299,'Model - Preopening & Fees'!$B74) -> 0 | N74: =SUMIFS('Invoices - Preopening'!$I$20:$I$299,'Invoices - Preopening'!$H$20:$H$299,">="&N$6,'Invoices - Preopening'!$H$20:$H$299,"<="&N$7,'Invoices - Preopening'!$C$20:$C$299,'Model - Preopening & Fees'!$B74) -> 0 | O74: =SUMIFS('Invoices - Preopening'!$I$20:$I$299,'Invoices - Preopening'!$H$20:$H$299,">="&O$6,'Invoices - Preopening'!$H$20:$H$299,"<="&O$7,'Invoices - Preopening'!$C$20:$C$299,'Model - Preopening & Fees'!$B74) -> 0 | P74: =SUMIFS('Invoices - Preopening'!$I$20:$I$299,'Invoices - Preopening'!$H$20:$H$299,">="&P$6,'Invoices - Preopening'!$H$20:$H$299,"<="&P$7,'Invoices - Preopening'!$C$20:$C$299,'Model - Preopening & Fees'!$B74) -> 0 | Q74: =SUMIFS('Invoices - Preopening'!$I$20:$I$299,'Invoices - Preopening'!$H$20:$H$299,">="&Q$6,'Invoices - Preopening'!$H$20:$H$299,"<="&Q$7,'Invoices - Preopening'!$C$20:$C$299,'Model - Preopening & Fees'!$B74) -> 0 | R74: =SUMIFS('Invoices - Preopening'!$I$20:$I$299,'Invoices - Preopening'!$H$20:$H$299,">="&R$6,'Invoices - Preopening'!$H$20:$H$299,"<="&R$7,'Invoices - Preopening'!$C$20:$C$299,'Model - Preopening & Fees'!$B74) -> 0 | S74: =SUMIFS('Invoices - Preopening'!$I$20:$I$299,'Invoices - Preopening'!$H$20:$H$299,">="&S$6,'Invoices - Preopening'!$H$20:$H$299,"<="&S$7,'Invoices - Preopening'!$C$20:$C$299,'Model - Preopening & Fees'!$B74) -> 0 | ... AC74: =SUMIFS('Invoices - Preopening'!$I$20:$I$299,'Invoices - Preopening'!$H$20:$H$299,">="&AC$6,'Invoices - Preopening'!$H$20:$H$299,"<="&AC$7,'Invoices - Preopening'!$C$20:$C$299,'Model - Preopening & Fees'!$B74) -> 0 | AD74: 0 | AE74: 0 | AF74: 0 | AG74: 2000 | AH74: 3000 | AI74: 3000 | AJ74: 4000 | AK74: 0 | AL74: 0 | AM74: 0 | AN74: 0 | AO74: 0 | AP74: 0 | AQ74: 0 | AR74: 0 | AT74: =-SUMIFS($L74:$AR74,$L$5:$AR$5,AT$5) -> 0 | AU74: =-SUMIFS($L74:$AR74,$L$5:$AR$5,AU$5) -> 0 | AV74: =-SUMIFS($L74:$AR74,$L$5:$AR$5,AV$5) -> 0 | AW74: =-SUMIFS($L74:$AR74,$L$5:$AR$5,AW$5) -> 0 | AX74: =-SUMIFS($L74:$AR74,$L$5:$AR$5,AX$5) -> 0 | AY74: =-SUMIFS($L74:$AR74,$L$5:$AR$5,AY$5) -> 0 | AZ74: =-SUMIFS($L74:$AR74,$L$5:$AR$5,AZ$5) -> 0 | BA74: =-SUMIFS($L74:$AR74,$L$5:$AR$5,BA$5) -> -8000 | ... BD74: =-SUMIFS($L74:$AR74,$L$5:$AR$5,BD$5) -> 0 | BF74: =SUM(AT74:BD74) -> -12000
A75: 1 | B75: Travel Costs - Shadow Shifts Leadership Team Florence | D75: HR | E75: Joyce | F75: 1500 | G75: =SUMIFS($L75:$AR75,$L$7:$AR$7,"<="&$J$4) -> 345.89 | H75: =J75-G75 -> 2000 | J75: =SUM(L75:AR75) -> 2345.89 | L75: =SUMIFS('Invoices - Preopening'!$I$20:$I$299,'Invoices - Preopening'!$H$20:$H$299,">="&L$6,'Invoices - Preopening'!$H$20:$H$299,"<="&L$7,'Invoices - Preopening'!$C$20:$C$299,'Model - Preopening & Fees'!$B75) -> 0 | M75: =SUMIFS('Invoices - Preopening'!$I$20:$I$299,'Invoices - Preopening'!$H$20:$H$299,">="&M$6,'Invoices - Preopening'!$H$20:$H$299,"<="&M$7,'Invoices - Preopening'!$C$20:$C$299,'Model - Preopening & Fees'!$B75) -> 0 | N75: =SUMIFS('Invoices - Preopening'!$I$20:$I$299,'Invoices - Preopening'!$H$20:$H$299,">="&N$6,'Invoices - Preopening'!$H$20:$H$299,"<="&N$7,'Invoices - Preopening'!$C$20:$C$299,'Model - Preopening & Fees'!$B75) -> 0 | O75: =SUMIFS('Invoices - Preopening'!$I$20:$I$299,'Invoices - Preopening'!$H$20:$H$299,">="&O$6,'Invoices - Preopening'!$H$20:$H$299,"<="&O$7,'Invoices - Preopening'!$C$20:$C$299,'Model - Preopening & Fees'!$B75) -> 0 | P75: =SUMIFS('Invoices - Preopening'!$I$20:$I$299,'Invoices - Preopening'!$H$20:$H$299,">="&P$6,'Invoices - Preopening'!$H$20:$H$299,"<="&P$7,'Invoices - Preopening'!$C$20:$C$299,'Model - Preopening & Fees'!$B75) -> 0 | Q75: =SUMIFS('Invoices - Preopening'!$I$20:$I$299,'Invoices - Preopening'!$H$20:$H$299,">="&Q$6,'Invoices - Preopening'!$H$20:$H$299,"<="&Q$7,'Invoices - Preopening'!$C$20:$C$299,'Model - Preopening & Fees'!$B75) -> 0 | R75: =SUMIFS('Invoices - Preopening'!$I$20:$I$299,'Invoices - Preopening'!$H$20:$H$299,">="&R$6,'Invoices - Preopening'!$H$20:$H$299,"<="&R$7,'Invoices - Preopening'!$C$20:$C$299,'Model - Preopening & Fees'!$B75) -> 0 | S75: =SUMIFS('Invoices - Preopening'!$I$20:$I$299,'Invoices - Preopening'!$H$20:$H$299,">="&S$6,'Invoices - Preopening'!$H$20:$H$299,"<="&S$7,'Invoices - Preopening'!$C$20:$C$299,'Model - Preopening & Fees'!$B75) -> 0 | ... AC75: =SUMIFS('Invoices - Preopening'!$I$20:$I$299,'Invoices - Preopening'!$H$20:$H$299,">="&AC$6,'Invoices - Preopening'!$H$20:$H$299,"<="&AC$7,'Invoices - Preopening'!$C$20:$C$299,'Model - Preopening & Fees'!$B75) -> 57.1 | AD75: 0 | AE75: 0 | AF75: 0 | AG75: 0 | AH75: 0 | AI75: 1000 | AJ75: 1000 | AK75: 0 | AL75: 0 | AM75: 0 | AN75: 0 | AO75: 0 | AP75: 0 | AQ75: 0 | AR75: 0 | AT75: =-SUMIFS($L75:$AR75,$L$5:$AR$5,AT$5) -> 0 | AU75: =-SUMIFS($L75:$AR75,$L$5:$AR$5,AU$5) -> 0 | AV75: =-SUMIFS($L75:$AR75,$L$5:$AR$5,AV$5) -> 0 | AW75: =-SUMIFS($L75:$AR75,$L$5:$AR$5,AW$5) -> 0 | AX75: =-SUMIFS($L75:$AR75,$L$5:$AR$5,AX$5) -> -288.79 | AY75: =-SUMIFS($L75:$AR75,$L$5:$AR$5,AY$5) -> -57.1 | AZ75: =-SUMIFS($L75:$AR75,$L$5:$AR$5,AZ$5) -> 0 | BA75: =-SUMIFS($L75:$AR75,$L$5:$AR$5,BA$5) -> -1000 | ... BD75: =-SUMIFS($L75:$AR75,$L$5:$AR$5,BD$5) -> 0 | BF75: =SUM(AT75:BD75) -> -2345.89
A76: 1 | B76: HR Legal Costs - Employee Handbook | D76: HR | E76: Joyce | F76: 10000 | G76: =SUMIFS($L76:$AR76,$L$7:$AR$7,"<="&$J$4) -> 0 | H76: =J76-G76 -> 10000 | J76: =SUM(L76:AR76) -> 10000 | L76: =SUMIFS('Invoices - Preopening'!$I$20:$I$299,'Invoices - Preopening'!$H$20:$H$299,">="&L$6,'Invoices - Preopening'!$H$20:$H$299,"<="&L$7,'Invoices - Preopening'!$C$20:$C$299,'Model - Preopening & Fees'!$B76) -> 0 | M76: =SUMIFS('Invoices - Preopening'!$I$20:$I$299,'Invoices - Preopening'!$H$20:$H$299,">="&M$6,'Invoices - Preopening'!$H$20:$H$299,"<="&M$7,'Invoices - Preopening'!$C$20:$C$299,'Model - Preopening & Fees'!$B76) -> 0 | N76: =SUMIFS('Invoices - Preopening'!$I$20:$I$299,'Invoices - Preopening'!$H$20:$H$299,">="&N$6,'Invoices - Preopening'!$H$20:$H$299,"<="&N$7,'Invoices - Preopening'!$C$20:$C$299,'Model - Preopening & Fees'!$B76) -> 0 | O76: =SUMIFS('Invoices - Preopening'!$I$20:$I$299,'Invoices - Preopening'!$H$20:$H$299,">="&O$6,'Invoices - Preopening'!$H$20:$H$299,"<="&O$7,'Invoices - Preopening'!$C$20:$C$299,'Model - Preopening & Fees'!$B76) -> 0 | P76: =SUMIFS('Invoices - Preopening'!$I$20:$I$299,'Invoices - Preopening'!$H$20:$H$299,">="&P$6,'Invoices - Preopening'!$H$20:$H$299,"<="&P$7,'Invoices - Preopening'!$C$20:$C$299,'Model - Preopening & Fees'!$B76) -> 0 | Q76: =SUMIFS('Invoices - Preopening'!$I$20:$I$299,'Invoices - Preopening'!$H$20:$H$299,">="&Q$6,'Invoices - Preopening'!$H$20:$H$299,"<="&Q$7,'Invoices - Preopening'!$C$20:$C$299,'Model - Preopening & Fees'!$B76) -> 0 | R76: =SUMIFS('Invoices - Preopening'!$I$20:$I$299,'Invoices - Preopening'!$H$20:$H$299,">="&R$6,'Invoices - Preopening'!$H$20:$H$299,"<="&R$7,'Invoices - Preopening'!$C$20:$C$299,'Model - Preopening & Fees'!$B76) -> 0 | S76: =SUMIFS('Invoices - Preopening'!$I$20:$I$299,'Invoices - Preopening'!$H$20:$H$299,">="&S$6,'Invoices - Preopening'!$H$20:$H$299,"<="&S$7,'Invoices - Preopening'!$C$20:$C$299,'Model - Preopening & Fees'!$B76) -> 0 | ... AC76: =SUMIFS('Invoices - Preopening'!$I$20:$I$299,'Invoices - Preopening'!$H$20:$H$299,">="&AC$6,'Invoices - Preopening'!$H$20:$H$299,"<="&AC$7,'Invoices - Preopening'!$C$20:$C$299,'Model - Preopening & Fees'!$B76) -> 0 | AD76: 0 | AE76: 0 | AF76: 0 | AG76: 0 | AH76: 5000 | AI76: 5000 | AJ76: 0 | AK76: 0 | AL76: 0 | AM76: 0 | AN76: 0 | AO76: 0 | AP76: 0 | AQ76: 0 | AR76: 0
B78: Recruitment Budget
A79: 1 | B79: Social Media Recruitment - Tiktok & Meta (Instagram) Ads Daily Budget of €100-€150 recommended for enough visibility. 2x to run different ads (for F&B & front office) | D79: HR | E79: Joyce | F79: 3500 | G79: =SUMIFS($L79:$AR79,$L$7:$AR$7,"<="&$J$4) -> 0 | H79: =J79-G79 -> 3500 | J79: =SUM(L79:AR79) -> 3500 | L79: =SUMIFS('Invoices - Preopening'!$I$20:$I$299,'Invoices - Preopening'!$H$20:$H$299,">="&L$6,'Invoices - Preopening'!$H$20:$H$299,"<="&L$7,'Invoices - Preopening'!$C$20:$C$299,'Model - Preopening & Fees'!$B79) -> 0 | M79: =SUMIFS('Invoices - Preopening'!$I$20:$I$299,'Invoices - Preopening'!$H$20:$H$299,">="&M$6,'Invoices - Preopening'!$H$20:$H$299,"<="&M$7,'Invoices - Preopening'!$C$20:$C$299,'Model - Preopening & Fees'!$B79) -> 0 | N79: =SUMIFS('Invoices - Preopening'!$I$20:$I$299,'Invoices - Preopening'!$H$20:$H$299,">="&N$6,'Invoices - Preopening'!$H$20:$H$299,"<="&N$7,'Invoices - Preopening'!$C$20:$C$299,'Model - Preopening & Fees'!$B79) -> 0 | O79: =SUMIFS('Invoices - Preopening'!$I$20:$I$299,'Invoices - Preopening'!$H$20:$H$299,">="&O$6,'Invoices - Preopening'!$H$20:$H$299,"<="&O$7,'Invoices - Preopening'!$C$20:$C$299,'Model - Preopening & Fees'!$B79) -> 0 | P79: =SUMIFS('Invoices - Preopening'!$I$20:$I$299,'Invoices - Preopening'!$H$20:$H$299,">="&P$6,'Invoices - Preopening'!$H$20:$H$299,"<="&P$7,'Invoices - Preopening'!$C$20:$C$299,'Model - Preopening & Fees'!$B79) -> 0 | Q79: =SUMIFS('Invoices - Preopening'!$I$20:$I$299,'Invoices - Preopening'!$H$20:$H$299,">="&Q$6,'Invoices - Preopening'!$H$20:$H$299,"<="&Q$7,'Invoices - Preopening'!$C$20:$C$299,'Model - Preopening & Fees'!$B79) -> 0 | R79: =SUMIFS('Invoices - Preopening'!$I$20:$I$299,'Invoices - Preopening'!$H$20:$H$299,">="&R$6,'Invoices - Preopening'!$H$20:$H$299,"<="&R$7,'Invoices - Preopening'!$C$20:$C$299,'Model - Preopening & Fees'!$B79) -> 0 | S79: =SUMIFS('Invoices - Preopening'!$I$20:$I$299,'Invoices - Preopening'!$H$20:$H$299,">="&S$6,'Invoices - Preopening'!$H$20:$H$299,"<="&S$7,'Invoices - Preopening'!$C$20:$C$299,'Model - Preopening & Fees'!$B79) -> 0 | ... AC79: =SUMIFS('Invoices - Preopening'!$I$20:$I$299,'Invoices - Preopening'!$H$20:$H$299,">="&AC$6,'Invoices - Preopening'!$H$20:$H$299,"<="&AC$7,'Invoices - Preopening'!$C$20:$C$299,'Model - Preopening & Fees'!$B79) -> 0 | AD79: 0 | AF79: 500 | AG79: 1500 | AH79: 1000 | AI79: 500 | AJ79: 0 | AK79: 0 | AL79: 0 | AM79: 0 | AN79: 0 | AO79: 0 | AP79: 0 | AQ79: 0 | AR79: 0 | AT79: =-SUMIFS($L79:$AR79,$L$5:$AR$5,AT$5) -> 0 | AU79: =-SUMIFS($L79:$AR79,$L$5:$AR$5,AU$5) -> 0 | AV79: =-SUMIFS($L79:$AR79,$L$5:$AR$5,AV$5) -> 0 | AW79: =-SUMIFS($L79:$AR79,$L$5:$AR$5,AW$5) -> 0 | AX79: =-SUMIFS($L79:$AR79,$L$5:$AR$5,AX$5) -> 0 | AY79: =-SUMIFS($L79:$AR79,$L$5:$AR$5,AY$5) -> 0 | AZ79: =-SUMIFS($L79:$AR79,$L$5:$AR$5,AZ$5) -> -500 | BA79: =-SUMIFS($L79:$AR79,$L$5:$AR$5,BA$5) -> -3000 | ... BD79: =-SUMIFS($L79:$AR79,$L$5:$AR$5,BD$5) -> 0 | BF79: =SUM(AT79:BD79) -> -3500
A80: 1 | B80: LinkedIn & Indeed Promotions to be used for specialist roles, e.g. chef, hotel manager, F&B MOD | D80: HR | E80: Joyce | F80: 2000 | G80: =SUMIFS($L80:$AR80,$L$7:$AR$7,"<="&$J$4) -> 0 | H80: =J80-G80 -> 2000 | J80: =SUM(L80:AR80) -> 2000 | L80: =SUMIFS('Invoices - Preopening'!$I$20:$I$299,'Invoices - Preopening'!$H$20:$H$299,">="&L$6,'Invoices - Preopening'!$H$20:$H$299,"<="&L$7,'Invoices - Preopening'!$C$20:$C$299,'Model - Preopening & Fees'!$B80) -> 0 | M80: =SUMIFS('Invoices - Preopening'!$I$20:$I$299,'Invoices - Preopening'!$H$20:$H$299,">="&M$6,'Invoices - Preopening'!$H$20:$H$299,"<="&M$7,'Invoices - Preopening'!$C$20:$C$299,'Model - Preopening & Fees'!$B80) -> 0 | N80: =SUMIFS('Invoices - Preopening'!$I$20:$I$299,'Invoices - Preopening'!$H$20:$H$299,">="&N$6,'Invoices - Preopening'!$H$20:$H$299,"<="&N$7,'Invoices - Preopening'!$C$20:$C$299,'Model - Preopening & Fees'!$B80) -> 0 | O80: =SUMIFS('Invoices - Preopening'!$I$20:$I$299,'Invoices - Preopening'!$H$20:$H$299,">="&O$6,'Invoices - Preopening'!$H$20:$H$299,"<="&O$7,'Invoices - Preopening'!$C$20:$C$299,'Model - Preopening & Fees'!$B80) -> 0 | P80: =SUMIFS('Invoices - Preopening'!$I$20:$I$299,'Invoices - Preopening'!$H$20:$H$299,">="&P$6,'Invoices - Preopening'!$H$20:$H$299,"<="&P$7,'Invoices - Preopening'!$C$20:$C$299,'Model - Preopening & Fees'!$B80) -> 0 | Q80: =SUMIFS('Invoices - Preopening'!$I$20:$I$299,'Invoices - Preopening'!$H$20:$H$299,">="&Q$6,'Invoices - Preopening'!$H$20:$H$299,"<="&Q$7,'Invoices - Preopening'!$C$20:$C$299,'Model - Preopening & Fees'!$B80) -> 0 | R80: =SUMIFS('Invoices - Preopening'!$I$20:$I$299,'Invoices - Preopening'!$H$20:$H$299,">="&R$6,'Invoices - Preopening'!$H$20:$H$299,"<="&R$7,'Invoices - Preopening'!$C$20:$C$299,'Model - Preopening & Fees'!$B80) -> 0 | S80: =SUMIFS('Invoices - Preopening'!$I$20:$I$299,'Invoices - Preopening'!$H$20:$H$299,">="&S$6,'Invoices - Preopening'!$H$20:$H$299,"<="&S$7,'Invoices - Preopening'!$C$20:$C$299,'Model - Preopening & Fees'!$B80) -> 0 | ... AC80: =SUMIFS('Invoices - Preopening'!$I$20:$I$299,'Invoices - Preopening'!$H$20:$H$299,">="&AC$6,'Invoices - Preopening'!$H$20:$H$299,"<="&AC$7,'Invoices - Preopening'!$C$20:$C$299,'Model - Preopening & Fees'!$B80) -> 0 | AD80: 0 | AE80: 1000 | AF80: 500 | AG80: 500 | AI80: 0 | AJ80: 0 | AK80: 0 | AL80: 0 | AM80: 0 | AN80: 0 | AO80: 0 | AP80: 0 | AQ80: 0 | AR80: 0 | AT80: =-SUMIFS($L80:$AR80,$L$5:$AR$5,AT$5) -> 0 | AU80: =-SUMIFS($L80:$AR80,$L$5:$AR$5,AU$5) -> 0 | AV80: =-SUMIFS($L80:$AR80,$L$5:$AR$5,AV$5) -> 0 | AW80: =-SUMIFS($L80:$AR80,$L$5:$AR$5,AW$5) -> 0 | AX80: =-SUMIFS($L80:$AR80,$L$5:$AR$5,AX$5) -> 0 | AY80: =-SUMIFS($L80:$AR80,$L$5:$AR$5,AY$5) -> 0 | AZ80: =-SUMIFS($L80:$AR80,$L$5:$AR$5,AZ$5) -> -1500 | BA80: =-SUMIFS($L80:$AR80,$L$5:$AR$5,BA$5) -> -500 | ... BD80: =-SUMIFS($L80:$AR80,$L$5:$AR$5,BD$5) -> 0 | BF80: =SUM(AT80:BD80) -> -2000
A81: 1 | B81: Offline Visibility - e.g. campaign materials limited - more focus on online visibility to reach target audience | D81: HR | E81: Joyce | F81: 2500 | G81: =SUMIFS($L81:$AR81,$L$7:$AR$7,"<="&$J$4) -> 0 | H81: =J81-G81 -> 2500 | J81: =SUM(L81:AR81) -> 2500 | L81: =SUMIFS('Invoices - Preopening'!$I$20:$I$299,'Invoices - Preopening'!$H$20:$H$299,">="&L$6,'Invoices - Preopening'!$H$20:$H$299,"<="&L$7,'Invoices - Preopening'!$C$20:$C$299,'Model - Preopening & Fees'!$B81) -> 0 | M81: =SUMIFS('Invoices - Preopening'!$I$20:$I$299,'Invoices - Preopening'!$H$20:$H$299,">="&M$6,'Invoices - Preopening'!$H$20:$H$299,"<="&M$7,'Invoices - Preopening'!$C$20:$C$299,'Model - Preopening & Fees'!$B81) -> 0 | N81: =SUMIFS('Invoices - Preopening'!$I$20:$I$299,'Invoices - Preopening'!$H$20:$H$299,">="&N$6,'Invoices - Preopening'!$H$20:$H$299,"<="&N$7,'Invoices - Preopening'!$C$20:$C$299,'Model - Preopening & Fees'!$B81) -> 0 | O81: =SUMIFS('Invoices - Preopening'!$I$20:$I$299,'Invoices - Preopening'!$H$20:$H$299,">="&O$6,'Invoices - Preopening'!$H$20:$H$299,"<="&O$7,'Invoices - Preopening'!$C$20:$C$299,'Model - Preopening & Fees'!$B81) -> 0 | P81: =SUMIFS('Invoices - Preopening'!$I$20:$I$299,'Invoices - Preopening'!$H$20:$H$299,">="&P$6,'Invoices - Preopening'!$H$20:$H$299,"<="&P$7,'Invoices - Preopening'!$C$20:$C$299,'Model - Preopening & Fees'!$B81) -> 0 | Q81: =SUMIFS('Invoices - Preopening'!$I$20:$I$299,'Invoices - Preopening'!$H$20:$H$299,">="&Q$6,'Invoices - Preopening'!$H$20:$H$299,"<="&Q$7,'Invoices - Preopening'!$C$20:$C$299,'Model - Preopening & Fees'!$B81) -> 0 | R81: =SUMIFS('Invoices - Preopening'!$I$20:$I$299,'Invoices - Preopening'!$H$20:$H$299,">="&R$6,'Invoices - Preopening'!$H$20:$H$299,"<="&R$7,'Invoices - Preopening'!$C$20:$C$299,'Model - Preopening & Fees'!$B81) -> 0 | S81: =SUMIFS('Invoices - Preopening'!$I$20:$I$299,'Invoices - Preopening'!$H$20:$H$299,">="&S$6,'Invoices - Preopening'!$H$20:$H$299,"<="&S$7,'Invoices - Preopening'!$C$20:$C$299,'Model - Preopening & Fees'!$B81) -> 0 | ... AC81: =SUMIFS('Invoices - Preopening'!$I$20:$I$299,'Invoices - Preopening'!$H$20:$H$299,">="&AC$6,'Invoices - Preopening'!$H$20:$H$299,"<="&AC$7,'Invoices - Preopening'!$C$20:$C$299,'Model - Preopening & Fees'!$B81) -> 0 | AD81: 0 | AE81: 0 | AF81: 0 | AG81: 750 | AH81: 750 | AI81: 500 | AJ81: 500 | AK81: 0 | AL81: 0 | AM81: 0 | AN81: 0 | AO81: 0 | AP81: 0 | AQ81: 0 | AR81: 0 | AT81: =-SUMIFS($L81:$AR81,$L$5:$AR$5,AT$5) -> 0 | AU81: =-SUMIFS($L81:$AR81,$L$5:$AR$5,AU$5) -> 0 | AV81: =-SUMIFS($L81:$AR81,$L$5:$AR$5,AV$5) -> 0 | AW81: =-SUMIFS($L81:$AR81,$L$5:$AR$5,AW$5) -> 0 | AX81: =-SUMIFS($L81:$AR81,$L$5:$AR$5,AX$5) -> 0 | AY81: =-SUMIFS($L81:$AR81,$L$5:$AR$5,AY$5) -> 0 | AZ81: =-SUMIFS($L81:$AR81,$L$5:$AR$5,AZ$5) -> 0 | BA81: =-SUMIFS($L81:$AR81,$L$5:$AR$5,BA$5) -> -2000 | ... BD81: =-SUMIFS($L81:$AR81,$L$5:$AR$5,BD$5) -> 0 | BF81: =SUM(AT81:BD81) -> -2500
A82: 1 | B82: In-house Recruitment Day | D82: HR | E82: Joyce | F82: 7500 | G82: =SUMIFS($L82:$AR82,$L$7:$AR$7,"<="&$J$4) -> 789.8 | H82: =J82-G82 -> 7500 | J82: =SUM(L82:AR82) -> 8289.8 | L82: =SUMIFS('Invoices - Preopening'!$I$20:$I$299,'Invoices - Preopening'!$H$20:$H$299,">="&L$6,'Invoices - Preopening'!$H$20:$H$299,"<="&L$7,'Invoices - Preopening'!$C$20:$C$299,'Model - Preopening & Fees'!$B82) -> 0 | M82: =SUMIFS('Invoices - Preopening'!$I$20:$I$299,'Invoices - Preopening'!$H$20:$H$299,">="&M$6,'Invoices - Preopening'!$H$20:$H$299,"<="&M$7,'Invoices - Preopening'!$C$20:$C$299,'Model - Preopening & Fees'!$B82) -> 0 | N82: =SUMIFS('Invoices - Preopening'!$I$20:$I$299,'Invoices - Preopening'!$H$20:$H$299,">="&N$6,'Invoices - Preopening'!$H$20:$H$299,"<="&N$7,'Invoices - Preopening'!$C$20:$C$299,'Model - Preopening & Fees'!$B82) -> 0 | O82: =SUMIFS('Invoices - Preopening'!$I$20:$I$299,'Invoices - Preopening'!$H$20:$H$299,">="&O$6,'Invoices - Preopening'!$H$20:$H$299,"<="&O$7,'Invoices - Preopening'!$C$20:$C$299,'Model - Preopening & Fees'!$B82) -> 0 | P82: =SUMIFS('Invoices - Preopening'!$I$20:$I$299,'Invoices - Preopening'!$H$20:$H$299,">="&P$6,'Invoices - Preopening'!$H$20:$H$299,"<="&P$7,'Invoices - Preopening'!$C$20:$C$299,'Model - Preopening & Fees'!$B82) -> 0 | Q82: =SUMIFS('Invoices - Preopening'!$I$20:$I$299,'Invoices - Preopening'!$H$20:$H$299,">="&Q$6,'Invoices - Preopening'!$H$20:$H$299,"<="&Q$7,'Invoices - Preopening'!$C$20:$C$299,'Model - Preopening & Fees'!$B82) -> 0 | R82: =SUMIFS('Invoices - Preopening'!$I$20:$I$299,'Invoices - Preopening'!$H$20:$H$299,">="&R$6,'Invoices - Preopening'!$H$20:$H$299,"<="&R$7,'Invoices - Preopening'!$C$20:$C$299,'Model - Preopening & Fees'!$B82) -> 0 | S82: =SUMIFS('Invoices - Preopening'!$I$20:$I$299,'Invoices - Preopening'!$H$20:$H$299,">="&S$6,'Invoices - Preopening'!$H$20:$H$299,"<="&S$7,'Invoices - Preopening'!$C$20:$C$299,'Model - Preopening & Fees'!$B82) -> 0 | ... AC82: =SUMIFS('Invoices - Preopening'!$I$20:$I$299,'Invoices - Preopening'!$H$20:$H$299,">="&AC$6,'Invoices - Preopening'!$H$20:$H$299,"<="&AC$7,'Invoices - Preopening'!$C$20:$C$299,'Model - Preopening & Fees'!$B82) -> 0 | AD82: 0 | AE82: 0 | AG82: 2500 | AH82: 2500 | AI82: 2500 | AJ82: 0 | AK82: 0 | AL82: 0 | AM82: 0 | AN82: 0 | AO82: 0 | AP82: 0 | AQ82: 0 | AR82: 0 | AT82: =-SUMIFS($L82:$AR82,$L$5:$AR$5,AT$5) -> 0 | AU82: =-SUMIFS($L82:$AR82,$L$5:$AR$5,AU$5) -> 0 | AV82: =-SUMIFS($L82:$AR82,$L$5:$AR$5,AV$5) -> 0 | AW82: =-SUMIFS($L82:$AR82,$L$5:$AR$5,AW$5) -> 0 | AX82: =-SUMIFS($L82:$AR82,$L$5:$AR$5,AX$5) -> 0 | AY82: =-SUMIFS($L82:$AR82,$L$5:$AR$5,AY$5) -> -789.8 | AZ82: =-SUMIFS($L82:$AR82,$L$5:$AR$5,AZ$5) -> 0 | BA82: =-SUMIFS($L82:$AR82,$L$5:$AR$5,BA$5) -> -7500 | ... BD82: =-SUMIFS($L82:$AR82,$L$5:$AR$5,BD$5) -> 0 | BF82: =SUM(AT82:BD82) -> -8289.8
B84: Staff Costs Pre-Opening
A85: 1 | B85: Ongoing Salary - Reception Manager | D85: HR | E85: Joyce | F85: 46702 | G85: =SUMIFS($L85:$AR85,$L$7:$AR$7,"<="&$J$4) -> 12737 | H85: =J85-G85 -> 33965.333 | J85: =SUM(L85:AR85) -> 46702.333 | L85: =SUMIFS('Invoices - Preopening'!$I$20:$I$299,'Invoices - Preopening'!$H$20:$H$299,">="&L$6,'Invoices - Preopening'!$H$20:$H$299,"<="&L$7,'Invoices - Preopening'!$C$20:$C$299,'Model - Preopening & Fees'!$B85) -> 0 | M85: =SUMIFS('Invoices - Preopening'!$I$20:$I$299,'Invoices - Preopening'!$H$20:$H$299,">="&M$6,'Invoices - Preopening'!$H$20:$H$299,"<="&M$7,'Invoices - Preopening'!$C$20:$C$299,'Model - Preopening & Fees'!$B85) -> 0 | N85: =SUMIFS('Invoices - Preopening'!$I$20:$I$299,'Invoices - Preopening'!$H$20:$H$299,">="&N$6,'Invoices - Preopening'!$H$20:$H$299,"<="&N$7,'Invoices - Preopening'!$C$20:$C$299,'Model - Preopening & Fees'!$B85) -> 0 | O85: =SUMIFS('Invoices - Preopening'!$I$20:$I$299,'Invoices - Preopening'!$H$20:$H$299,">="&O$6,'Invoices - Preopening'!$H$20:$H$299,"<="&O$7,'Invoices - Preopening'!$C$20:$C$299,'Model - Preopening & Fees'!$B85) -> 0 | P85: =SUMIFS('Invoices - Preopening'!$I$20:$I$299,'Invoices - Preopening'!$H$20:$H$299,">="&P$6,'Invoices - Preopening'!$H$20:$H$299,"<="&P$7,'Invoices - Preopening'!$C$20:$C$299,'Model - Preopening & Fees'!$B85) -> 0 | Q85: =SUMIFS('Invoices - Preopening'!$I$20:$I$299,'Invoices - Preopening'!$H$20:$H$299,">="&Q$6,'Invoices - Preopening'!$H$20:$H$299,"<="&Q$7,'Invoices - Preopening'!$C$20:$C$299,'Model - Preopening & Fees'!$B85) -> 0 | R85: =SUMIFS('Invoices - Preopening'!$I$20:$I$299,'Invoices - Preopening'!$H$20:$H$299,">="&R$6,'Invoices - Preopening'!$H$20:$H$299,"<="&R$7,'Invoices - Preopening'!$C$20:$C$299,'Model - Preopening & Fees'!$B85) -> 0 | S85: =SUMIFS('Invoices - Preopening'!$I$20:$I$299,'Invoices - Preopening'!$H$20:$H$299,">="&S$6,'Invoices - Preopening'!$H$20:$H$299,"<="&S$7,'Invoices - Preopening'!$C$20:$C$299,'Model - Preopening & Fees'!$B85) -> 0 | ... AC85: =SUMIFS('Invoices - Preopening'!$I$20:$I$299,'Invoices - Preopening'!$H$20:$H$299,">="&AC$6,'Invoices - Preopening'!$H$20:$H$299,"<="&AC$7,'Invoices - Preopening'!$C$20:$C$299,'Model - Preopening & Fees'!$B85) -> 4245.6667 | AD85: 4245.6667 | AE85: 4245.6667 | AF85: 4245.6667 | AG85: 4245.6667 | AH85: 4245.6667 | AI85: 4245.6667 | AJ85: 4245.6667 | AK85: 4245.6667 | AL85: 0 | AM85: 0 | AN85: 0 | AO85: 0 | AP85: 0 | AQ85: 0 | AR85: 0 | AT85: =-SUMIFS($L85:$AR85,$L$5:$AR$5,AT$5) -> 0 | AU85: =-SUMIFS($L85:$AR85,$L$5:$AR$5,AU$5) -> 0 | AV85: =-SUMIFS($L85:$AR85,$L$5:$AR$5,AV$5) -> 0 | AW85: =-SUMIFS($L85:$AR85,$L$5:$AR$5,AW$5) -> 0 | AX85: =-SUMIFS($L85:$AR85,$L$5:$AR$5,AX$5) -> 0 | AY85: =-SUMIFS($L85:$AR85,$L$5:$AR$5,AY$5) -> -12737 | AZ85: =-SUMIFS($L85:$AR85,$L$5:$AR$5,AZ$5) -> -12737 | BA85: =-SUMIFS($L85:$AR85,$L$5:$AR$5,BA$5) -> -12737 | ... BD85: =-SUMIFS($L85:$AR85,$L$5:$AR$5,BD$5) -> 0 | BF85: =SUM(AT85:BD85) -> -46702.333
A86: 1 | B86: Hotel Manager - Fabio | D86: HR | E86: Joyce | F86: 40000 | G86: =SUMIFS($L86:$AR86,$L$7:$AR$7,"<="&$J$4) -> 0 | H86: =J86-G86 -> 45833.333 | J86: =SUM(L86:AR86) -> 45833.333 | L86: =SUMIFS('Invoices - Preopening'!$I$20:$I$299,'Invoices - Preopening'!$H$20:$H$299,">="&L$6,'Invoices - Preopening'!$H$20:$H$299,"<="&L$7,'Invoices - Preopening'!$C$20:$C$299,'Model - Preopening & Fees'!$B86) -> 0 | M86: =SUMIFS('Invoices - Preopening'!$I$20:$I$299,'Invoices - Preopening'!$H$20:$H$299,">="&M$6,'Invoices - Preopening'!$H$20:$H$299,"<="&M$7,'Invoices - Preopening'!$C$20:$C$299,'Model - Preopening & Fees'!$B86) -> 0 | N86: =SUMIFS('Invoices - Preopening'!$I$20:$I$299,'Invoices - Preopening'!$H$20:$H$299,">="&N$6,'Invoices - Preopening'!$H$20:$H$299,"<="&N$7,'Invoices - Preopening'!$C$20:$C$299,'Model - Preopening & Fees'!$B86) -> 0 | O86: =SUMIFS('Invoices - Preopening'!$I$20:$I$299,'Invoices - Preopening'!$H$20:$H$299,">="&O$6,'Invoices - Preopening'!$H$20:$H$299,"<="&O$7,'Invoices - Preopening'!$C$20:$C$299,'Model - Preopening & Fees'!$B86) -> 0 | P86: =SUMIFS('Invoices - Preopening'!$I$20:$I$299,'Invoices - Preopening'!$H$20:$H$299,">="&P$6,'Invoices - Preopening'!$H$20:$H$299,"<="&P$7,'Invoices - Preopening'!$C$20:$C$299,'Model - Preopening & Fees'!$B86) -> 0 | Q86: =SUMIFS('Invoices - Preopening'!$I$20:$I$299,'Invoices - Preopening'!$H$20:$H$299,">="&Q$6,'Invoices - Preopening'!$H$20:$H$299,"<="&Q$7,'Invoices - Preopening'!$C$20:$C$299,'Model - Preopening & Fees'!$B86) -> 0 | R86: =SUMIFS('Invoices - Preopening'!$I$20:$I$299,'Invoices - Preopening'!$H$20:$H$299,">="&R$6,'Invoices - Preopening'!$H$20:$H$299,"<="&R$7,'Invoices - Preopening'!$C$20:$C$299,'Model - Preopening & Fees'!$B86) -> 0 | S86: =SUMIFS('Invoices - Preopening'!$I$20:$I$299,'Invoices - Preopening'!$H$20:$H$299,">="&S$6,'Invoices - Preopening'!$H$20:$H$299,"<="&S$7,'Invoices - Preopening'!$C$20:$C$299,'Model - Preopening & Fees'!$B86) -> 0 | ... AC86: =SUMIFS('Invoices - Preopening'!$I$20:$I$299,'Invoices - Preopening'!$H$20:$H$299,">="&AC$6,'Invoices - Preopening'!$H$20:$H$299,"<="&AC$7,'Invoices - Preopening'!$C$20:$C$299,'Model - Preopening & Fees'!$B86) -> 0 | AD86: 0 | AE86: 0 | AF86: 0 | AG86: =(80000/12)*1.375 -> 9166.6667 | AH86: =(80000/12)*1.375 -> 9166.6667 | AI86: =(80000/12)*1.375 -> 9166.6667 | AJ86: =(80000/12)*1.375 -> 9166.6667 | AK86: =(80000/12)*1.375 -> 9166.6667 | AL86: 0 | AM86: 0 | AN86: 0 | AO86: 0 | AP86: 0 | AQ86: 0 | AR86: 0 | AT86: =-SUMIFS($L86:$AR86,$L$5:$AR$5,AT$5) -> 0 | AU86: =-SUMIFS($L86:$AR86,$L$5:$AR$5,AU$5) -> 0 | AV86: =-SUMIFS($L86:$AR86,$L$5:$AR$5,AV$5) -> 0 | AW86: =-SUMIFS($L86:$AR86,$L$5:$AR$5,AW$5) -> 0 | AX86: =-SUMIFS($L86:$AR86,$L$5:$AR$5,AX$5) -> 0 | AY86: =-SUMIFS($L86:$AR86,$L$5:$AR$5,AY$5) -> 0 | AZ86: =-SUMIFS($L86:$AR86,$L$5:$AR$5,AZ$5) -> 0 | BA86: =-SUMIFS($L86:$AR86,$L$5:$AR$5,BA$5) -> -27500 | ... BD86: =-SUMIFS($L86:$AR86,$L$5:$AR$5,BD$5) -> 0 | BF86: =SUM(AT86:BD86) -> -45833.333
A87: 1 | B87: Staff Costs Preopening (23 FTE) - excl. Fabio & Andi | D87: HR | E87: Joyce | F87: 60000 | G87: =SUMIFS($L87:$AR87,$L$7:$AR$7,"<="&$J$4) -> 0 | H87: =J87-G87 -> 49000 | J87: =SUM(L87:AR87) -> 49000 | L87: =SUMIFS('Invoices - Preopening'!$I$20:$I$299,'Invoices - Preopening'!$H$20:$H$299,">="&L$6,'Invoices - Preopening'!$H$20:$H$299,"<="&L$7,'Invoices - Preopening'!$C$20:$C$299,'Model - Preopening & Fees'!$B87) -> 0 | M87: =SUMIFS('Invoices - Preopening'!$I$20:$I$299,'Invoices - Preopening'!$H$20:$H$299,">="&M$6,'Invoices - Preopening'!$H$20:$H$299,"<="&M$7,'Invoices - Preopening'!$C$20:$C$299,'Model - Preopening & Fees'!$B87) -> 0 | N87: =SUMIFS('Invoices - Preopening'!$I$20:$I$299,'Invoices - Preopening'!$H$20:$H$299,">="&N$6,'Invoices - Preopening'!$H$20:$H$299,"<="&N$7,'Invoices - Preopening'!$C$20:$C$299,'Model - Preopening & Fees'!$B87) -> 0 | O87: =SUMIFS('Invoices - Preopening'!$I$20:$I$299,'Invoices - Preopening'!$H$20:$H$299,">="&O$6,'Invoices - Preopening'!$H$20:$H$299,"<="&O$7,'Invoices - Preopening'!$C$20:$C$299,'Model - Preopening & Fees'!$B87) -> 0 | P87: =SUMIFS('Invoices - Preopening'!$I$20:$I$299,'Invoices - Preopening'!$H$20:$H$299,">="&P$6,'Invoices - Preopening'!$H$20:$H$299,"<="&P$7,'Invoices - Preopening'!$C$20:$C$299,'Model - Preopening & Fees'!$B87) -> 0 | Q87: =SUMIFS('Invoices - Preopening'!$I$20:$I$299,'Invoices - Preopening'!$H$20:$H$299,">="&Q$6,'Invoices - Preopening'!$H$20:$H$299,"<="&Q$7,'Invoices - Preopening'!$C$20:$C$299,'Model - Preopening & Fees'!$B87) -> 0 | R87: =SUMIFS('Invoices - Preopening'!$I$20:$I$299,'Invoices - Preopening'!$H$20:$H$299,">="&R$6,'Invoices - Preopening'!$H$20:$H$299,"<="&R$7,'Invoices - Preopening'!$C$20:$C$299,'Model - Preopening & Fees'!$B87) -> 0 | S87: =SUMIFS('Invoices - Preopening'!$I$20:$I$299,'Invoices - Preopening'!$H$20:$H$299,">="&S$6,'Invoices - Preopening'!$H$20:$H$299,"<="&S$7,'Invoices - Preopening'!$C$20:$C$299,'Model - Preopening & Fees'!$B87) -> 0 | ... AC87: =SUMIFS('Invoices - Preopening'!$I$20:$I$299,'Invoices - Preopening'!$H$20:$H$299,">="&AC$6,'Invoices - Preopening'!$H$20:$H$299,"<="&AC$7,'Invoices - Preopening'!$C$20:$C$299,'Model - Preopening & Fees'!$B87) -> 0 | AD87: 0 | AE87: 0 | AF87: 0 | AG87: 0 | AH87: 0 | AI87: 4000 | AJ87: 10000 | AK87: 35000 | AL87: 0 | AM87: 0 | AN87: 0 | AO87: 0 | AP87: 0 | AQ87: 0 | AR87: 0 | AT87: =-SUMIFS($L87:$AR87,$L$5:$AR$5,AT$5) -> 0 | AU87: =-SUMIFS($L87:$AR87,$L$5:$AR$5,AU$5) -> 0 | AV87: =-SUMIFS($L87:$AR87,$L$5:$AR$5,AV$5) -> 0 | AW87: =-SUMIFS($L87:$AR87,$L$5:$AR$5,AW$5) -> 0 | AX87: =-SUMIFS($L87:$AR87,$L$5:$AR$5,AX$5) -> 0 | AY87: =-SUMIFS($L87:$AR87,$L$5:$AR$5,AY$5) -> 0 | AZ87: =-SUMIFS($L87:$AR87,$L$5:$AR$5,AZ$5) -> 0 | BA87: =-SUMIFS($L87:$AR87,$L$5:$AR$5,BA$5) -> -4000 | ... BD87: =-SUMIFS($L87:$AR87,$L$5:$AR$5,BD$5) -> 0 | BF87: =SUM(AT87:BD87) -> -49000
A88: 1 | B88: Sales Manager External - Preopening Push | D88: HR | E88: Joyce | F88: 15000 | G88: =SUMIFS($L88:$AR88,$L$7:$AR$7,"<="&$J$4) -> 0 | H88: =J88-G88 -> 13200 | J88: =SUM(L88:AR88) -> 13200 | L88: =SUMIFS('Invoices - Preopening'!$I$20:$I$299,'Invoices - Preopening'!$H$20:$H$299,">="&L$6,'Invoices - Preopening'!$H$20:$H$299,"<="&L$7,'Invoices - Preopening'!$C$20:$C$299,'Model - Preopening & Fees'!$B88) -> 0 | M88: =SUMIFS('Invoices - Preopening'!$I$20:$I$299,'Invoices - Preopening'!$H$20:$H$299,">="&M$6,'Invoices - Preopening'!$H$20:$H$299,"<="&M$7,'Invoices - Preopening'!$C$20:$C$299,'Model - Preopening & Fees'!$B88) -> 0 | N88: =SUMIFS('Invoices - Preopening'!$I$20:$I$299,'Invoices - Preopening'!$H$20:$H$299,">="&N$6,'Invoices - Preopening'!$H$20:$H$299,"<="&N$7,'Invoices - Preopening'!$C$20:$C$299,'Model - Preopening & Fees'!$B88) -> 0 | O88: =SUMIFS('Invoices - Preopening'!$I$20:$I$299,'Invoices - Preopening'!$H$20:$H$299,">="&O$6,'Invoices - Preopening'!$H$20:$H$299,"<="&O$7,'Invoices - Preopening'!$C$20:$C$299,'Model - Preopening & Fees'!$B88) -> 0 | P88: =SUMIFS('Invoices - Preopening'!$I$20:$I$299,'Invoices - Preopening'!$H$20:$H$299,">="&P$6,'Invoices - Preopening'!$H$20:$H$299,"<="&P$7,'Invoices - Preopening'!$C$20:$C$299,'Model - Preopening & Fees'!$B88) -> 0 | Q88: =SUMIFS('Invoices - Preopening'!$I$20:$I$299,'Invoices - Preopening'!$H$20:$H$299,">="&Q$6,'Invoices - Preopening'!$H$20:$H$299,"<="&Q$7,'Invoices - Preopening'!$C$20:$C$299,'Model - Preopening & Fees'!$B88) -> 0 | R88: =SUMIFS('Invoices - Preopening'!$I$20:$I$299,'Invoices - Preopening'!$H$20:$H$299,">="&R$6,'Invoices - Preopening'!$H$20:$H$299,"<="&R$7,'Invoices - Preopening'!$C$20:$C$299,'Model - Preopening & Fees'!$B88) -> 0 | S88: =SUMIFS('Invoices - Preopening'!$I$20:$I$299,'Invoices - Preopening'!$H$20:$H$299,">="&S$6,'Invoices - Preopening'!$H$20:$H$299,"<="&S$7,'Invoices - Preopening'!$C$20:$C$299,'Model - Preopening & Fees'!$B88) -> 0 | ... AC88: =SUMIFS('Invoices - Preopening'!$I$20:$I$299,'Invoices - Preopening'!$H$20:$H$299,">="&AC$6,'Invoices - Preopening'!$H$20:$H$299,"<="&AC$7,'Invoices - Preopening'!$C$20:$C$299,'Model - Preopening & Fees'!$B88) -> 0 | AD88: 0 | AE88: 0 | AF88: 2200 | AG88: 2200 | AH88: 2200 | AI88: 2200 | AJ88: 2200 | AK88: 2200 | AL88: 0 | AM88: 0 | AN88: 0 | AO88: 0 | AP88: 0 | AQ88: 0 | AR88: 0 | AT88: =-SUMIFS($L88:$AR88,$L$5:$AR$5,AT$5) -> 0 | AU88: =-SUMIFS($L88:$AR88,$L$5:$AR$5,AU$5) -> 0 | AV88: =-SUMIFS($L88:$AR88,$L$5:$AR$5,AV$5) -> 0 | AW88: =-SUMIFS($L88:$AR88,$L$5:$AR$5,AW$5) -> 0 | AX88: =-SUMIFS($L88:$AR88,$L$5:$AR$5,AX$5) -> 0 | AY88: =-SUMIFS($L88:$AR88,$L$5:$AR$5,AY$5) -> 0 | AZ88: =-SUMIFS($L88:$AR88,$L$5:$AR$5,AZ$5) -> -2200 | BA88: =-SUMIFS($L88:$AR88,$L$5:$AR$5,BA$5) -> -6600 | ... BD88: =-SUMIFS($L88:$AR88,$L$5:$AR$5,BD$5) -> 0 | BF88: =SUM(AT88:BD88) -> -13200
A89: 1 | B89: Sales Representation APLBC | D89: HR | E89: Joyce | F89: 18000 | G89: =SUMIFS($L89:$AR89,$L$7:$AR$7,"<="&$J$4) -> 2000 | H89: =J89-G89 -> 16000 | J89: =SUM(L89:AR89) -> 18000 | L89: =SUMIFS('Invoices - Preopening'!$I$20:$I$299,'Invoices - Preopening'!$H$20:$H$299,">="&L$6,'Invoices - Preopening'!$H$20:$H$299,"<="&L$7,'Invoices - Preopening'!$C$20:$C$299,'Model - Preopening & Fees'!$B89) -> 0 | M89: =SUMIFS('Invoices - Preopening'!$I$20:$I$299,'Invoices - Preopening'!$H$20:$H$299,">="&M$6,'Invoices - Preopening'!$H$20:$H$299,"<="&M$7,'Invoices - Preopening'!$C$20:$C$299,'Model - Preopening & Fees'!$B89) -> 0 | N89: =SUMIFS('Invoices - Preopening'!$I$20:$I$299,'Invoices - Preopening'!$H$20:$H$299,">="&N$6,'Invoices - Preopening'!$H$20:$H$299,"<="&N$7,'Invoices - Preopening'!$C$20:$C$299,'Model - Preopening & Fees'!$B89) -> 0 | O89: =SUMIFS('Invoices - Preopening'!$I$20:$I$299,'Invoices - Preopening'!$H$20:$H$299,">="&O$6,'Invoices - Preopening'!$H$20:$H$299,"<="&O$7,'Invoices - Preopening'!$C$20:$C$299,'Model - Preopening & Fees'!$B89) -> 0 | P89: =SUMIFS('Invoices - Preopening'!$I$20:$I$299,'Invoices - Preopening'!$H$20:$H$299,">="&P$6,'Invoices - Preopening'!$H$20:$H$299,"<="&P$7,'Invoices - Preopening'!$C$20:$C$299,'Model - Preopening & Fees'!$B89) -> 0 | Q89: =SUMIFS('Invoices - Preopening'!$I$20:$I$299,'Invoices - Preopening'!$H$20:$H$299,">="&Q$6,'Invoices - Preopening'!$H$20:$H$299,"<="&Q$7,'Invoices - Preopening'!$C$20:$C$299,'Model - Preopening & Fees'!$B89) -> 0 | R89: =SUMIFS('Invoices - Preopening'!$I$20:$I$299,'Invoices - Preopening'!$H$20:$H$299,">="&R$6,'Invoices - Preopening'!$H$20:$H$299,"<="&R$7,'Invoices - Preopening'!$C$20:$C$299,'Model - Preopening & Fees'!$B89) -> 0 | S89: =SUMIFS('Invoices - Preopening'!$I$20:$I$299,'Invoices - Preopening'!$H$20:$H$299,">="&S$6,'Invoices - Preopening'!$H$20:$H$299,"<="&S$7,'Invoices - Preopening'!$C$20:$C$299,'Model - Preopening & Fees'!$B89) -> 0 | ... AC89: =SUMIFS('Invoices - Preopening'!$I$20:$I$299,'Invoices - Preopening'!$H$20:$H$299,">="&AC$6,'Invoices - Preopening'!$H$20:$H$299,"<="&AC$7,'Invoices - Preopening'!$C$20:$C$299,'Model - Preopening & Fees'!$B89) -> 2000 | AD89: 2000 | AE89: 2000 | AF89: 2000 | AG89: 2000 | AH89: 2000 | AI89: 2000 | AJ89: 2000 | AK89: 2000 | AL89: 0 | AM89: 0 | AN89: 0 | AO89: 0 | AP89: 0 | AQ89: 0 | AR89: 0 | AT89: =-SUMIFS($L89:$AR89,$L$5:$AR$5,AT$5) -> 0 | AU89: =-SUMIFS($L89:$AR89,$L$5:$AR$5,AU$5) -> 0 | AV89: =-SUMIFS($L89:$AR89,$L$5:$AR$5,AV$5) -> 0 | AW89: =-SUMIFS($L89:$AR89,$L$5:$AR$5,AW$5) -> 0 | AX89: =-SUMIFS($L89:$AR89,$L$5:$AR$5,AX$5) -> 0 | AY89: =-SUMIFS($L89:$AR89,$L$5:$AR$5,AY$5) -> -2000 | AZ89: =-SUMIFS($L89:$AR89,$L$5:$AR$5,AZ$5) -> -6000 | BA89: =-SUMIFS($L89:$AR89,$L$5:$AR$5,BA$5) -> -6000 | ... BD89: =-SUMIFS($L89:$AR89,$L$5:$AR$5,BD$5) -> 0 | BF89: =SUM(AT89:BD89) -> -18000
B91: Reorganisation former hotel team
A92: 1 | B92: TFR Costs Reorganisation | D92: HR | E92: Joyce | F92: 198984 | G92: =SUMIFS($L92:$AR92,$L$7:$AR$7,"<="&$J$4) -> 57893 | H92: =J92-G92 -> 141091 | J92: =SUM(L92:AR92) -> 198984 | L92: =SUMIFS('Invoices - Preopening'!$I$20:$I$299,'Invoices - Preopening'!$H$20:$H$299,">="&L$6,'Invoices - Preopening'!$H$20:$H$299,"<="&L$7,'Invoices - Preopening'!$C$20:$C$299,'Model - Preopening & Fees'!$B92) -> 0 | M92: =SUMIFS('Invoices - Preopening'!$I$20:$I$299,'Invoices - Preopening'!$H$20:$H$299,">="&M$6,'Invoices - Preopening'!$H$20:$H$299,"<="&M$7,'Invoices - Preopening'!$C$20:$C$299,'Model - Preopening & Fees'!$B92) -> 0 | N92: =SUMIFS('Invoices - Preopening'!$I$20:$I$299,'Invoices - Preopening'!$H$20:$H$299,">="&N$6,'Invoices - Preopening'!$H$20:$H$299,"<="&N$7,'Invoices - Preopening'!$C$20:$C$299,'Model - Preopening & Fees'!$B92) -> 0 | O92: =SUMIFS('Invoices - Preopening'!$I$20:$I$299,'Invoices - Preopening'!$H$20:$H$299,">="&O$6,'Invoices - Preopening'!$H$20:$H$299,"<="&O$7,'Invoices - Preopening'!$C$20:$C$299,'Model - Preopening & Fees'!$B92) -> 0 | P92: =SUMIFS('Invoices - Preopening'!$I$20:$I$299,'Invoices - Preopening'!$H$20:$H$299,">="&P$6,'Invoices - Preopening'!$H$20:$H$299,"<="&P$7,'Invoices - Preopening'!$C$20:$C$299,'Model - Preopening & Fees'!$B92) -> 0 | Q92: =SUMIFS('Invoices - Preopening'!$I$20:$I$299,'Invoices - Preopening'!$H$20:$H$299,">="&Q$6,'Invoices - Preopening'!$H$20:$H$299,"<="&Q$7,'Invoices - Preopening'!$C$20:$C$299,'Model - Preopening & Fees'!$B92) -> 0 | R92: =SUMIFS('Invoices - Preopening'!$I$20:$I$299,'Invoices - Preopening'!$H$20:$H$299,">="&R$6,'Invoices - Preopening'!$H$20:$H$299,"<="&R$7,'Invoices - Preopening'!$C$20:$C$299,'Model - Preopening & Fees'!$B92) -> 0 | S92: =SUMIFS('Invoices - Preopening'!$I$20:$I$299,'Invoices - Preopening'!$H$20:$H$299,">="&S$6,'Invoices - Preopening'!$H$20:$H$299,"<="&S$7,'Invoices - Preopening'!$C$20:$C$299,'Model - Preopening & Fees'!$B92) -> 0 | ... AC92: =SUMIFS('Invoices - Preopening'!$I$20:$I$299,'Invoices - Preopening'!$H$20:$H$299,">="&AC$6,'Invoices - Preopening'!$H$20:$H$299,"<="&AC$7,'Invoices - Preopening'!$C$20:$C$299,'Model - Preopening & Fees'!$B92) -> 0 | AD92: 141091 | AE92: 0 | AF92: 0 | AG92: 0 | AH92: 0 | AI92: 0 | AJ92: 0 | AK92: 0 | AL92: 0 | AM92: 0 | AN92: 0 | AO92: 0 | AP92: 0 | AQ92: 0 | AR92: 0 | AT92: =-SUMIFS($L92:$AR92,$L$5:$AR$5,AT$5) -> 0 | AU92: =-SUMIFS($L92:$AR92,$L$5:$AR$5,AU$5) -> 0 | AV92: =-SUMIFS($L92:$AR92,$L$5:$AR$5,AV$5) -> 0 | AW92: =-SUMIFS($L92:$AR92,$L$5:$AR$5,AW$5) -> 0 | AX92: =-SUMIFS($L92:$AR92,$L$5:$AR$5,AX$5) -> -57893 | AY92: =-SUMIFS($L92:$AR92,$L$5:$AR$5,AY$5) -> 0 | AZ92: =-SUMIFS($L92:$AR92,$L$5:$AR$5,AZ$5) -> -141091 | BA92: =-SUMIFS($L92:$AR92,$L$5:$AR$5,BA$5) -> 0 | ... BD92: =-SUMIFS($L92:$AR92,$L$5:$AR$5,BD$5) -> 0 | BF92: =SUM(AT92:BD92) -> -198984
A93: 1 | B93: Settlement Costs Staff Reorganisation | D93: HR | E93: Joyce | F93: 166966 | G93: =SUMIFS($L93:$AR93,$L$7:$AR$7,"<="&$J$4) -> 166966 | H93: =J93-G93 -> 41812.35 | J93: =SUM(L93:AR93) -> 208778.35 | L93: =SUMIFS('Invoices - Preopening'!$I$20:$I$299,'Invoices - Preopening'!$H$20:$H$299,">="&L$6,'Invoices - Preopening'!$H$20:$H$299,"<="&L$7,'Invoices - Preopening'!$C$20:$C$299,'Model - Preopening & Fees'!$B93) -> 0 | M93: =SUMIFS('Invoices - Preopening'!$I$20:$I$299,'Invoices - Preopening'!$H$20:$H$299,">="&M$6,'Invoices - Preopening'!$H$20:$H$299,"<="&M$7,'Invoices - Preopening'!$C$20:$C$299,'Model - Preopening & Fees'!$B93) -> 0 | N93: =SUMIFS('Invoices - Preopening'!$I$20:$I$299,'Invoices - Preopening'!$H$20:$H$299,">="&N$6,'Invoices - Preopening'!$H$20:$H$299,"<="&N$7,'Invoices - Preopening'!$C$20:$C$299,'Model - Preopening & Fees'!$B93) -> 0 | O93: =SUMIFS('Invoices - Preopening'!$I$20:$I$299,'Invoices - Preopening'!$H$20:$H$299,">="&O$6,'Invoices - Preopening'!$H$20:$H$299,"<="&O$7,'Invoices - Preopening'!$C$20:$C$299,'Model - Preopening & Fees'!$B93) -> 0 | P93: =SUMIFS('Invoices - Preopening'!$I$20:$I$299,'Invoices - Preopening'!$H$20:$H$299,">="&P$6,'Invoices - Preopening'!$H$20:$H$299,"<="&P$7,'Invoices - Preopening'!$C$20:$C$299,'Model - Preopening & Fees'!$B93) -> 0 | Q93: =SUMIFS('Invoices - Preopening'!$I$20:$I$299,'Invoices - Preopening'!$H$20:$H$299,">="&Q$6,'Invoices - Preopening'!$H$20:$H$299,"<="&Q$7,'Invoices - Preopening'!$C$20:$C$299,'Model - Preopening & Fees'!$B93) -> 0 | R93: =SUMIFS('Invoices - Preopening'!$I$20:$I$299,'Invoices - Preopening'!$H$20:$H$299,">="&R$6,'Invoices - Preopening'!$H$20:$H$299,"<="&R$7,'Invoices - Preopening'!$C$20:$C$299,'Model - Preopening & Fees'!$B93) -> 0 | S93: =SUMIFS('Invoices - Preopening'!$I$20:$I$299,'Invoices - Preopening'!$H$20:$H$299,">="&S$6,'Invoices - Preopening'!$H$20:$H$299,"<="&S$7,'Invoices - Preopening'!$C$20:$C$299,'Model - Preopening & Fees'!$B93) -> 0 | ... AC93: =SUMIFS('Invoices - Preopening'!$I$20:$I$299,'Invoices - Preopening'!$H$20:$H$299,">="&AC$6,'Invoices - Preopening'!$H$20:$H$299,"<="&AC$7,'Invoices - Preopening'!$C$20:$C$299,'Model - Preopening & Fees'!$B93) -> 0 | AD93: =38776+'Invoices - Preopening'!I51 -> 41812.35 | AE93: 0 | AF93: 0 | AG93: 0 | AH93: 0 | AI93: 0 | AJ93: 0 | AK93: 0 | AL93: 0 | AM93: 0 | AN93: 0 | AO93: 0 | AP93: 0 | AQ93: 0 | AR93: 0 | AT93: =-SUMIFS($L93:$AR93,$L$5:$AR$5,AT$5) -> 0 | AU93: =-SUMIFS($L93:$AR93,$L$5:$AR$5,AU$5) -> 0 | AV93: =-SUMIFS($L93:$AR93,$L$5:$AR$5,AV$5) -> 0 | AW93: =-SUMIFS($L93:$AR93,$L$5:$AR$5,AW$5) -> 0 | AX93: =-SUMIFS($L93:$AR93,$L$5:$AR$5,AX$5) -> -166966 | AY93: =-SUMIFS($L93:$AR93,$L$5:$AR$5,AY$5) -> 0 | AZ93: =-SUMIFS($L93:$AR93,$L$5:$AR$5,AZ$5) -> -41812.35 | BA93: =-SUMIFS($L93:$AR93,$L$5:$AR$5,BA$5) -> 0 | ... BD93: =-SUMIFS($L93:$AR93,$L$5:$AR$5,BD$5) -> 0 | BF93: =SUM(AT93:BD93) -> -208778.35
A94: 1 | B94: Legal Costs - Studio Pirola Reorganisation | D94: HR | E94: Joyce | F94: 25000 | G94: =SUMIFS($L94:$AR94,$L$7:$AR$7,"<="&$J$4) -> 12000 | H94: =J94-G94 -> 8000 | J94: =SUM(L94:AR94) -> 20000 | L94: =SUMIFS('Invoices - Preopening'!$I$20:$I$299,'Invoices - Preopening'!$H$20:$H$299,">="&L$6,'Invoices - Preopening'!$H$20:$H$299,"<="&L$7,'Invoices - Preopening'!$C$20:$C$299,'Model - Preopening & Fees'!$B94) -> 0 | M94: =SUMIFS('Invoices - Preopening'!$I$20:$I$299,'Invoices - Preopening'!$H$20:$H$299,">="&M$6,'Invoices - Preopening'!$H$20:$H$299,"<="&M$7,'Invoices - Preopening'!$C$20:$C$299,'Model - Preopening & Fees'!$B94) -> 0 | N94: =SUMIFS('Invoices - Preopening'!$I$20:$I$299,'Invoices - Preopening'!$H$20:$H$299,">="&N$6,'Invoices - Preopening'!$H$20:$H$299,"<="&N$7,'Invoices - Preopening'!$C$20:$C$299,'Model - Preopening & Fees'!$B94) -> 0 | O94: =SUMIFS('Invoices - Preopening'!$I$20:$I$299,'Invoices - Preopening'!$H$20:$H$299,">="&O$6,'Invoices - Preopening'!$H$20:$H$299,"<="&O$7,'Invoices - Preopening'!$C$20:$C$299,'Model - Preopening & Fees'!$B94) -> 0 | P94: =SUMIFS('Invoices - Preopening'!$I$20:$I$299,'Invoices - Preopening'!$H$20:$H$299,">="&P$6,'Invoices - Preopening'!$H$20:$H$299,"<="&P$7,'Invoices - Preopening'!$C$20:$C$299,'Model - Preopening & Fees'!$B94) -> 0 | Q94: =SUMIFS('Invoices - Preopening'!$I$20:$I$299,'Invoices - Preopening'!$H$20:$H$299,">="&Q$6,'Invoices - Preopening'!$H$20:$H$299,"<="&Q$7,'Invoices - Preopening'!$C$20:$C$299,'Model - Preopening & Fees'!$B94) -> 0 | R94: =SUMIFS('Invoices - Preopening'!$I$20:$I$299,'Invoices - Preopening'!$H$20:$H$299,">="&R$6,'Invoices - Preopening'!$H$20:$H$299,"<="&R$7,'Invoices - Preopening'!$C$20:$C$299,'Model - Preopening & Fees'!$B94) -> 0 | S94: =SUMIFS('Invoices - Preopening'!$I$20:$I$299,'Invoices - Preopening'!$H$20:$H$299,">="&S$6,'Invoices - Preopening'!$H$20:$H$299,"<="&S$7,'Invoices - Preopening'!$C$20:$C$299,'Model - Preopening & Fees'!$B94) -> 0 | ... AC94: =SUMIFS('Invoices - Preopening'!$I$20:$I$299,'Invoices - Preopening'!$H$20:$H$299,">="&AC$6,'Invoices - Preopening'!$H$20:$H$299,"<="&AC$7,'Invoices - Preopening'!$C$20:$C$299,'Model - Preopening & Fees'!$B94) -> 0 | AD94: 5000 | AE94: 3000 | AF94: 0 | AG94: 0 | AH94: 0 | AI94: 0 | AJ94: 0 | AK94: 0 | AL94: 0 | AM94: 0 | AN94: 0 | AO94: 0 | AP94: 0 | AQ94: 0 | AR94: 0 | AT94: =-SUMIFS($L94:$AR94,$L$5:$AR$5,AT$5) -> 0 | AU94: =-SUMIFS($L94:$AR94,$L$5:$AR$5,AU$5) -> 0 | AV94: =-SUMIFS($L94:$AR94,$L$5:$AR$5,AV$5) -> 0 | AW94: =-SUMIFS($L94:$AR94,$L$5:$AR$5,AW$5) -> -12000 | AX94: =-SUMIFS($L94:$AR94,$L$5:$AR$5,AX$5) -> 0 | AY94: =-SUMIFS($L94:$AR94,$L$5:$AR$5,AY$5) -> 0 | AZ94: =-SUMIFS($L94:$AR94,$L$5:$AR$5,AZ$5) -> -8000 | BA94: =-SUMIFS($L94:$AR94,$L$5:$AR$5,BA$5) -> 0 | ... BD94: =-SUMIFS($L94:$AR94,$L$5:$AR$5,BD$5) -> 0 | BF94: =SUM(AT94:BD94) -> -20000
B95: Total HR | F95: =SUM(F73:F76,F79:F82,F85:F94) -> 626452 | G95: =SUM(G73:G75,G79:G82,G85:G94) -> 252731.69 | H95: =SUM(H73:H76,H79:H82,H85:H94) -> 401202.02 | J95: =SUM(L95:AR95) -> 653933.71 | L95: =SUM(L73:L76,L79:L82,L85:L94) -> 0 | M95: =SUM(M73:M76,M79:M82,M85:M94) -> 0 | N95: =SUM(N73:N76,N79:N82,N85:N94) -> 0 | O95: =SUM(O73:O76,O79:O82,O85:O94) -> 0 | P95: =SUM(P73:P76,P79:P82,P85:P94) -> 0 | Q95: =SUM(Q73:Q76,Q79:Q82,Q85:Q94) -> 0 | R95: =SUM(R73:R76,R79:R82,R85:R94) -> 0 | S95: =SUM(S73:S76,S79:S82,S85:S94) -> 0 | ... AR95: =SUM(AR73:AR76,AR79:AR82,AR85:AR94) -> 0 | AT95: =SUM(AT73:AT75,AT79:AT82,AT85:AT89) -> 0 | AU95: =SUM(AU73:AU75,AU79:AU82,AU85:AU89) -> 0 | AV95: =SUM(AV73:AV75,AV79:AV82,AV85:AV89) -> 0 | AW95: =SUM(AW73:AW75,AW79:AW82,AW85:AW89) -> 0 | AX95: =SUM(AX73:AX75,AX79:AX82,AX85:AX89) -> -288.79 | AY95: =SUM(AY73:AY75,AY79:AY82,AY85:AY89) -> -15583.9 | AZ95: =SUM(AZ73:AZ75,AZ79:AZ82,AZ85:AZ89) -> -22937 | BA95: =SUM(BA73:BA75,BA79:BA82,BA85:BA89) -> -88837 | ... BD95: =SUM(BD73:BD75,BD79:BD82,BD85:BD89) -> 0 | BF95: =SUM(AT95:BD95) -> -216171.36
B97: IT Systems
B99: Budget | D99: Bucket | F99: Budget | G99: Spent | H99: Remaining
A100: 1 | B100: IT - Administrative & General (Exact, Keeper, Oneteam, Office365) | D100: IT | E100: Marc | F100: 4000 | G100: =SUMIFS($L100:$AR100,$L$7:$AR$7,"<="&$J$4) -> 0 | H100: =J100-G100 -> 4000 | J100: =SUM(L100:AR100) -> 4000 | L100: =SUMIFS('Invoices - Preopening'!$I$20:$I$299,'Invoices - Preopening'!$H$20:$H$299,">="&L$6,'Invoices - Preopening'!$H$20:$H$299,"<="&L$7,'Invoices - Preopening'!$C$20:$C$299,'Model - Preopening & Fees'!$B100) -> 0 | M100: =SUMIFS('Invoices - Preopening'!$I$20:$I$299,'Invoices - Preopening'!$H$20:$H$299,">="&M$6,'Invoices - Preopening'!$H$20:$H$299,"<="&M$7,'Invoices - Preopening'!$C$20:$C$299,'Model - Preopening & Fees'!$B100) -> 0 | N100: =SUMIFS('Invoices - Preopening'!$I$20:$I$299,'Invoices - Preopening'!$H$20:$H$299,">="&N$6,'Invoices - Preopening'!$H$20:$H$299,"<="&N$7,'Invoices - Preopening'!$C$20:$C$299,'Model - Preopening & Fees'!$B100) -> 0 | O100: =SUMIFS('Invoices - Preopening'!$I$20:$I$299,'Invoices - Preopening'!$H$20:$H$299,">="&O$6,'Invoices - Preopening'!$H$20:$H$299,"<="&O$7,'Invoices - Preopening'!$C$20:$C$299,'Model - Preopening & Fees'!$B100) -> 0 | P100: =SUMIFS('Invoices - Preopening'!$I$20:$I$299,'Invoices - Preopening'!$H$20:$H$299,">="&P$6,'Invoices - Preopening'!$H$20:$H$299,"<="&P$7,'Invoices - Preopening'!$C$20:$C$299,'Model - Preopening & Fees'!$B100) -> 0 | Q100: =SUMIFS('Invoices - Preopening'!$I$20:$I$299,'Invoices - Preopening'!$H$20:$H$299,">="&Q$6,'Invoices - Preopening'!$H$20:$H$299,"<="&Q$7,'Invoices - Preopening'!$C$20:$C$299,'Model - Preopening & Fees'!$B100) -> 0 | R100: =SUMIFS('Invoices - Preopening'!$I$20:$I$299,'Invoices - Preopening'!$H$20:$H$299,">="&R$6,'Invoices - Preopening'!$H$20:$H$299,"<="&R$7,'Invoices - Preopening'!$C$20:$C$299,'Model - Preopening & Fees'!$B100) -> 0 | S100: =SUMIFS('Invoices - Preopening'!$I$20:$I$299,'Invoices - Preopening'!$H$20:$H$299,">="&S$6,'Invoices - Preopening'!$H$20:$H$299,"<="&S$7,'Invoices - Preopening'!$C$20:$C$299,'Model - Preopening & Fees'!$B100) -> 0 | ... AC100: =SUMIFS('Invoices - Preopening'!$I$20:$I$299,'Invoices - Preopening'!$H$20:$H$299,">="&AC$6,'Invoices - Preopening'!$H$20:$H$299,"<="&AC$7,'Invoices - Preopening'!$C$20:$C$299,'Model - Preopening & Fees'!$B100) -> 0 | AD100: 0 | AE100: 0 | AF100: 0 | AG100: 0 | AH100: 1000 | AI100: 1000 | AJ100: 1000 | AK100: 1000 | AL100: 0 | AM100: 0 | AN100: 0 | AO100: 0 | AP100: 0 | AQ100: 0 | AR100: 0 | AT100: =-SUMIFS($L100:$AR100,$L$5:$AR$5,AT$5) -> 0 | AU100: =-SUMIFS($L100:$AR100,$L$5:$AR$5,AU$5) -> 0 | AV100: =-SUMIFS($L100:$AR100,$L$5:$AR$5,AV$5) -> 0 | AW100: =-SUMIFS($L100:$AR100,$L$5:$AR$5,AW$5) -> 0 | AX100: =-SUMIFS($L100:$AR100,$L$5:$AR$5,AX$5) -> 0 | AY100: =-SUMIFS($L100:$AR100,$L$5:$AR$5,AY$5) -> 0 | AZ100: =-SUMIFS($L100:$AR100,$L$5:$AR$5,AZ$5) -> 0 | BA100: =-SUMIFS($L100:$AR100,$L$5:$AR$5,BA$5) -> -2000 | ... BD100: =-SUMIFS($L100:$AR100,$L$5:$AR$5,BD$5) -> 0 | BF100: =SUM(AT100:BD100) -> -4000
A101: 1 | B101: IT - Food & Beverage | D101: IT | E101: Marc | F101: =SUM(AD101:AL101) -> 3900 | G101: =SUMIFS($L101:$AR101,$L$7:$AR$7,"<="&$J$4) -> 0 | H101: =J101-G101 -> 3900 | J101: =SUM(L101:AR101) -> 3900 | L101: =SUMIFS('Invoices - Preopening'!$I$20:$I$299,'Invoices - Preopening'!$H$20:$H$299,">="&L$6,'Invoices - Preopening'!$H$20:$H$299,"<="&L$7,'Invoices - Preopening'!$C$20:$C$299,'Model - Preopening & Fees'!$B101) -> 0 | M101: =SUMIFS('Invoices - Preopening'!$I$20:$I$299,'Invoices - Preopening'!$H$20:$H$299,">="&M$6,'Invoices - Preopening'!$H$20:$H$299,"<="&M$7,'Invoices - Preopening'!$C$20:$C$299,'Model - Preopening & Fees'!$B101) -> 0 | N101: =SUMIFS('Invoices - Preopening'!$I$20:$I$299,'Invoices - Preopening'!$H$20:$H$299,">="&N$6,'Invoices - Preopening'!$H$20:$H$299,"<="&N$7,'Invoices - Preopening'!$C$20:$C$299,'Model - Preopening & Fees'!$B101) -> 0 | O101: =SUMIFS('Invoices - Preopening'!$I$20:$I$299,'Invoices - Preopening'!$H$20:$H$299,">="&O$6,'Invoices - Preopening'!$H$20:$H$299,"<="&O$7,'Invoices - Preopening'!$C$20:$C$299,'Model - Preopening & Fees'!$B101) -> 0 | P101: =SUMIFS('Invoices - Preopening'!$I$20:$I$299,'Invoices - Preopening'!$H$20:$H$299,">="&P$6,'Invoices - Preopening'!$H$20:$H$299,"<="&P$7,'Invoices - Preopening'!$C$20:$C$299,'Model - Preopening & Fees'!$B101) -> 0 | Q101: =SUMIFS('Invoices - Preopening'!$I$20:$I$299,'Invoices - Preopening'!$H$20:$H$299,">="&Q$6,'Invoices - Preopening'!$H$20:$H$299,"<="&Q$7,'Invoices - Preopening'!$C$20:$C$299,'Model - Preopening & Fees'!$B101) -> 0 | R101: =SUMIFS('Invoices - Preopening'!$I$20:$I$299,'Invoices - Preopening'!$H$20:$H$299,">="&R$6,'Invoices - Preopening'!$H$20:$H$299,"<="&R$7,'Invoices - Preopening'!$C$20:$C$299,'Model - Preopening & Fees'!$B101) -> 0 | S101: =SUMIFS('Invoices - Preopening'!$I$20:$I$299,'Invoices - Preopening'!$H$20:$H$299,">="&S$6,'Invoices - Preopening'!$H$20:$H$299,"<="&S$7,'Invoices - Preopening'!$C$20:$C$299,'Model - Preopening & Fees'!$B101) -> 0 | ... AC101: =SUMIFS('Invoices - Preopening'!$I$20:$I$299,'Invoices - Preopening'!$H$20:$H$299,">="&AC$6,'Invoices - Preopening'!$H$20:$H$299,"<="&AC$7,'Invoices - Preopening'!$C$20:$C$299,'Model - Preopening & Fees'!$B101) -> 0 | AD101: 0 | AE101: 0 | AF101: 0 | AG101: 0 | AH101: 2100 | AI101: 600 | AJ101: 600 | AK101: 600 | AL101: 0 | AM101: 0 | AN101: 0 | AO101: 0 | AP101: 0 | AQ101: 0 | AR101: 0 | AT101: =-SUMIFS($L101:$AR101,$L$5:$AR$5,AT$5) -> 0 | AU101: =-SUMIFS($L101:$AR101,$L$5:$AR$5,AU$5) -> 0 | AV101: =-SUMIFS($L101:$AR101,$L$5:$AR$5,AV$5) -> 0 | AW101: =-SUMIFS($L101:$AR101,$L$5:$AR$5,AW$5) -> 0 | AX101: =-SUMIFS($L101:$AR101,$L$5:$AR$5,AX$5) -> 0 | AY101: =-SUMIFS($L101:$AR101,$L$5:$AR$5,AY$5) -> 0 | AZ101: =-SUMIFS($L101:$AR101,$L$5:$AR$5,AZ$5) -> 0 | BA101: =-SUMIFS($L101:$AR101,$L$5:$AR$5,BA$5) -> -2700 | ... BD101: =-SUMIFS($L101:$AR101,$L$5:$AR$5,BD$5) -> 0 | BF101: =SUM(AT101:BD101) -> -3900
A102: 1 | B102: IT - Human Resources (Personio, Shiftbase) | D102: IT | E102: Marc | F102: =SUM(AD102:AL102) -> 2000 | G102: =SUMIFS($L102:$AR102,$L$7:$AR$7,"<="&$J$4) -> 0 | H102: =J102-G102 -> 2000 | J102: =SUM(L102:AR102) -> 2000 | L102: =SUMIFS('Invoices - Preopening'!$I$20:$I$299,'Invoices - Preopening'!$H$20:$H$299,">="&L$6,'Invoices - Preopening'!$H$20:$H$299,"<="&L$7,'Invoices - Preopening'!$C$20:$C$299,'Model - Preopening & Fees'!$B102) -> 0 | M102: =SUMIFS('Invoices - Preopening'!$I$20:$I$299,'Invoices - Preopening'!$H$20:$H$299,">="&M$6,'Invoices - Preopening'!$H$20:$H$299,"<="&M$7,'Invoices - Preopening'!$C$20:$C$299,'Model - Preopening & Fees'!$B102) -> 0 | N102: =SUMIFS('Invoices - Preopening'!$I$20:$I$299,'Invoices - Preopening'!$H$20:$H$299,">="&N$6,'Invoices - Preopening'!$H$20:$H$299,"<="&N$7,'Invoices - Preopening'!$C$20:$C$299,'Model - Preopening & Fees'!$B102) -> 0 | O102: =SUMIFS('Invoices - Preopening'!$I$20:$I$299,'Invoices - Preopening'!$H$20:$H$299,">="&O$6,'Invoices - Preopening'!$H$20:$H$299,"<="&O$7,'Invoices - Preopening'!$C$20:$C$299,'Model - Preopening & Fees'!$B102) -> 0 | P102: =SUMIFS('Invoices - Preopening'!$I$20:$I$299,'Invoices - Preopening'!$H$20:$H$299,">="&P$6,'Invoices - Preopening'!$H$20:$H$299,"<="&P$7,'Invoices - Preopening'!$C$20:$C$299,'Model - Preopening & Fees'!$B102) -> 0 | Q102: =SUMIFS('Invoices - Preopening'!$I$20:$I$299,'Invoices - Preopening'!$H$20:$H$299,">="&Q$6,'Invoices - Preopening'!$H$20:$H$299,"<="&Q$7,'Invoices - Preopening'!$C$20:$C$299,'Model - Preopening & Fees'!$B102) -> 0 | R102: =SUMIFS('Invoices - Preopening'!$I$20:$I$299,'Invoices - Preopening'!$H$20:$H$299,">="&R$6,'Invoices - Preopening'!$H$20:$H$299,"<="&R$7,'Invoices - Preopening'!$C$20:$C$299,'Model - Preopening & Fees'!$B102) -> 0 | S102: =SUMIFS('Invoices - Preopening'!$I$20:$I$299,'Invoices - Preopening'!$H$20:$H$299,">="&S$6,'Invoices - Preopening'!$H$20:$H$299,"<="&S$7,'Invoices - Preopening'!$C$20:$C$299,'Model - Preopening & Fees'!$B102) -> 0 | ... AC102: =SUMIFS('Invoices - Preopening'!$I$20:$I$299,'Invoices - Preopening'!$H$20:$H$299,">="&AC$6,'Invoices - Preopening'!$H$20:$H$299,"<="&AC$7,'Invoices - Preopening'!$C$20:$C$299,'Model - Preopening & Fees'!$B102) -> 0 | AD102: 0 | AE102: 0 | AF102: 0 | AG102: 0 | AH102: 500 | AI102: 500 | AJ102: 500 | AK102: 500 | AL102: 0 | AM102: 0 | AN102: 0 | AO102: 0 | AP102: 0 | AQ102: 0 | AR102: 0 | AT102: =-SUMIFS($L102:$AR102,$L$5:$AR$5,AT$5) -> 0 | AU102: =-SUMIFS($L102:$AR102,$L$5:$AR$5,AU$5) -> 0 | AV102: =-SUMIFS($L102:$AR102,$L$5:$AR$5,AV$5) -> 0 | AW102: =-SUMIFS($L102:$AR102,$L$5:$AR$5,AW$5) -> 0 | AX102: =-SUMIFS($L102:$AR102,$L$5:$AR$5,AX$5) -> 0 | AY102: =-SUMIFS($L102:$AR102,$L$5:$AR$5,AY$5) -> 0 | AZ102: =-SUMIFS($L102:$AR102,$L$5:$AR$5,AZ$5) -> 0 | BA102: =-SUMIFS($L102:$AR102,$L$5:$AR$5,BA$5) -> -1000 | ... BD102: =-SUMIFS($L102:$AR102,$L$5:$AR$5,BD$5) -> 0 | BF102: =SUM(AT102:BD102) -> -2000
A103: 1 | B103: IT - Others (Mosyle, Reviewpro, MS Defender) | D103: IT | E103: Marc | F103: =SUM(AD103:AL103) -> 600 | G103: =SUMIFS($L103:$AR103,$L$7:$AR$7,"<="&$J$4) -> 0 | H103: =J103-G103 -> 600 | J103: =SUM(L103:AR103) -> 600 | L103: =SUMIFS('Invoices - Preopening'!$I$20:$I$299,'Invoices - Preopening'!$H$20:$H$299,">="&L$6,'Invoices - Preopening'!$H$20:$H$299,"<="&L$7,'Invoices - Preopening'!$C$20:$C$299,'Model - Preopening & Fees'!$B103) -> 0 | M103: =SUMIFS('Invoices - Preopening'!$I$20:$I$299,'Invoices - Preopening'!$H$20:$H$299,">="&M$6,'Invoices - Preopening'!$H$20:$H$299,"<="&M$7,'Invoices - Preopening'!$C$20:$C$299,'Model - Preopening & Fees'!$B103) -> 0 | N103: =SUMIFS('Invoices - Preopening'!$I$20:$I$299,'Invoices - Preopening'!$H$20:$H$299,">="&N$6,'Invoices - Preopening'!$H$20:$H$299,"<="&N$7,'Invoices - Preopening'!$C$20:$C$299,'Model - Preopening & Fees'!$B103) -> 0 | O103: =SUMIFS('Invoices - Preopening'!$I$20:$I$299,'Invoices - Preopening'!$H$20:$H$299,">="&O$6,'Invoices - Preopening'!$H$20:$H$299,"<="&O$7,'Invoices - Preopening'!$C$20:$C$299,'Model - Preopening & Fees'!$B103) -> 0 | P103: =SUMIFS('Invoices - Preopening'!$I$20:$I$299,'Invoices - Preopening'!$H$20:$H$299,">="&P$6,'Invoices - Preopening'!$H$20:$H$299,"<="&P$7,'Invoices - Preopening'!$C$20:$C$299,'Model - Preopening & Fees'!$B103) -> 0 | Q103: =SUMIFS('Invoices - Preopening'!$I$20:$I$299,'Invoices - Preopening'!$H$20:$H$299,">="&Q$6,'Invoices - Preopening'!$H$20:$H$299,"<="&Q$7,'Invoices - Preopening'!$C$20:$C$299,'Model - Preopening & Fees'!$B103) -> 0 | R103: =SUMIFS('Invoices - Preopening'!$I$20:$I$299,'Invoices - Preopening'!$H$20:$H$299,">="&R$6,'Invoices - Preopening'!$H$20:$H$299,"<="&R$7,'Invoices - Preopening'!$C$20:$C$299,'Model - Preopening & Fees'!$B103) -> 0 | S103: =SUMIFS('Invoices - Preopening'!$I$20:$I$299,'Invoices - Preopening'!$H$20:$H$299,">="&S$6,'Invoices - Preopening'!$H$20:$H$299,"<="&S$7,'Invoices - Preopening'!$C$20:$C$299,'Model - Preopening & Fees'!$B103) -> 0 | ... AC103: =SUMIFS('Invoices - Preopening'!$I$20:$I$299,'Invoices - Preopening'!$H$20:$H$299,">="&AC$6,'Invoices - Preopening'!$H$20:$H$299,"<="&AC$7,'Invoices - Preopening'!$C$20:$C$299,'Model - Preopening & Fees'!$B103) -> 0 | AD103: 0 | AE103: 0 | AF103: 0 | AG103: 0 | AI103: 200 | AJ103: 200 | AK103: 200 | AL103: 0 | AM103: 0 | AN103: 0 | AO103: 0 | AP103: 0 | AQ103: 0 | AR103: 0 | AT103: =-SUMIFS($L103:$AR103,$L$5:$AR$5,AT$5) -> 0 | AU103: =-SUMIFS($L103:$AR103,$L$5:$AR$5,AU$5) -> 0 | AV103: =-SUMIFS($L103:$AR103,$L$5:$AR$5,AV$5) -> 0 | AW103: =-SUMIFS($L103:$AR103,$L$5:$AR$5,AW$5) -> 0 | AX103: =-SUMIFS($L103:$AR103,$L$5:$AR$5,AX$5) -> 0 | AY103: =-SUMIFS($L103:$AR103,$L$5:$AR$5,AY$5) -> 0 | AZ103: =-SUMIFS($L103:$AR103,$L$5:$AR$5,AZ$5) -> 0 | BA103: =-SUMIFS($L103:$AR103,$L$5:$AR$5,BA$5) -> -200 | ... BD103: =-SUMIFS($L103:$AR103,$L$5:$AR$5,BD$5) -> 0 | BF103: =SUM(AT103:BD103) -> -600
A104: 1 | B104: IT - Rooms (D3x, Apaleo, Zaplox, Siteminder, Flyr, Sweeply, Lighthouse, Hibox, Boookboost) | D104: IT | E104: Marc | F104: =SUM(AD104:AL104) -> 17600 | G104: =SUMIFS($L104:$AR104,$L$7:$AR$7,"<="&$J$4) -> 0 | H104: =J104-G104 -> 17600 | J104: =SUM(L104:AR104) -> 17600 | L104: =SUMIFS('Invoices - Preopening'!$I$20:$I$299,'Invoices - Preopening'!$H$20:$H$299,">="&L$6,'Invoices - Preopening'!$H$20:$H$299,"<="&L$7,'Invoices - Preopening'!$C$20:$C$299,'Model - Preopening & Fees'!$B104) -> 0 | M104: =SUMIFS('Invoices - Preopening'!$I$20:$I$299,'Invoices - Preopening'!$H$20:$H$299,">="&M$6,'Invoices - Preopening'!$H$20:$H$299,"<="&M$7,'Invoices - Preopening'!$C$20:$C$299,'Model - Preopening & Fees'!$B104) -> 0 | N104: =SUMIFS('Invoices - Preopening'!$I$20:$I$299,'Invoices - Preopening'!$H$20:$H$299,">="&N$6,'Invoices - Preopening'!$H$20:$H$299,"<="&N$7,'Invoices - Preopening'!$C$20:$C$299,'Model - Preopening & Fees'!$B104) -> 0 | O104: =SUMIFS('Invoices - Preopening'!$I$20:$I$299,'Invoices - Preopening'!$H$20:$H$299,">="&O$6,'Invoices - Preopening'!$H$20:$H$299,"<="&O$7,'Invoices - Preopening'!$C$20:$C$299,'Model - Preopening & Fees'!$B104) -> 0 | P104: =SUMIFS('Invoices - Preopening'!$I$20:$I$299,'Invoices - Preopening'!$H$20:$H$299,">="&P$6,'Invoices - Preopening'!$H$20:$H$299,"<="&P$7,'Invoices - Preopening'!$C$20:$C$299,'Model - Preopening & Fees'!$B104) -> 0 | Q104: =SUMIFS('Invoices - Preopening'!$I$20:$I$299,'Invoices - Preopening'!$H$20:$H$299,">="&Q$6,'Invoices - Preopening'!$H$20:$H$299,"<="&Q$7,'Invoices - Preopening'!$C$20:$C$299,'Model - Preopening & Fees'!$B104) -> 0 | R104: =SUMIFS('Invoices - Preopening'!$I$20:$I$299,'Invoices - Preopening'!$H$20:$H$299,">="&R$6,'Invoices - Preopening'!$H$20:$H$299,"<="&R$7,'Invoices - Preopening'!$C$20:$C$299,'Model - Preopening & Fees'!$B104) -> 0 | S104: =SUMIFS('Invoices - Preopening'!$I$20:$I$299,'Invoices - Preopening'!$H$20:$H$299,">="&S$6,'Invoices - Preopening'!$H$20:$H$299,"<="&S$7,'Invoices - Preopening'!$C$20:$C$299,'Model - Preopening & Fees'!$B104) -> 0 | ... AC104: =SUMIFS('Invoices - Preopening'!$I$20:$I$299,'Invoices - Preopening'!$H$20:$H$299,">="&AC$6,'Invoices - Preopening'!$H$20:$H$299,"<="&AC$7,'Invoices - Preopening'!$C$20:$C$299,'Model - Preopening & Fees'!$B104) -> 0 | AD104: 0 | AE104: 0 | AF104: 1600 | AG104: 3200 | AH104: 3200 | AI104: 3200 | AJ104: 3200 | AK104: 3200 | AL104: 0 | AM104: 0 | AN104: 0 | AO104: 0 | AP104: 0 | AQ104: 0 | AR104: 0 | AT104: =-SUMIFS($L104:$AR104,$L$5:$AR$5,AT$5) -> 0 | AU104: =-SUMIFS($L104:$AR104,$L$5:$AR$5,AU$5) -> 0 | AV104: =-SUMIFS($L104:$AR104,$L$5:$AR$5,AV$5) -> 0 | AW104: =-SUMIFS($L104:$AR104,$L$5:$AR$5,AW$5) -> 0 | AX104: =-SUMIFS($L104:$AR104,$L$5:$AR$5,AX$5) -> 0 | AY104: =-SUMIFS($L104:$AR104,$L$5:$AR$5,AY$5) -> 0 | AZ104: =-SUMIFS($L104:$AR104,$L$5:$AR$5,AZ$5) -> -1600 | BA104: =-SUMIFS($L104:$AR104,$L$5:$AR$5,BA$5) -> -9600 | ... BD104: =-SUMIFS($L104:$AR104,$L$5:$AR$5,BD$5) -> 0 | BF104: =SUM(AT104:BD104) -> -17600
