Workbook

Sheet Overview
B1: OS&E_FF&E Overview
B3: Hotel | C3: The Usual Florence
B4: Brand | C4: The Usual
B5: Status
A7: Package | B7: OSE_FFE | C7: Loose OS&E/Daan/Usual | D7: Budget Artelia | E7: Comments | F7: ordered | G7: deadline | H7: In charge | I7: Information submitted to Daan
A8: P1.0 | B8: F&B: Fixed Kitchen & Bar Equipment | C8: =SUMIF('OS&E_FF&E'!$A:$A,Overview!$A8,'OS&E_FF&E'!$H:$H) -> 0 | H8: Michael
A9: P1.1 | B9: F&B: Coffee equipment | C9: =SUMIF('OS&E_FF&E'!$A:$A,Overview!$A9,'OS&E_FF&E'!$H:$H) -> 0 | H9: Michael
A10: P1.2 | B10: F&B: Operating Systems | C10: =SUMIF('OS&E_FF&E'!$A:$A,Overview!$A10,'OS&E_FF&E'!$H:$H) -> 0 | H10: Michael
A11: P1.3 | B11: F&B: Operating Equipment F&B | C11: 0 | H11: Michael | I11: P1.0 to P1.4: All part of capex 300K
A12: P2 | B12: Branded Stationary | C12: =SUMIF('OS&E_FF&E'!$A:$A,Overview!$A12,'OS&E_FF&E'!$H:$H) -> 25139.41 | H12: Marketing
A13: P3 | B13: Loose Furniture rooms | C13: =SUMIF('OS&E_FF&E'!$A:$A,Overview!$A13,'OS&E_FF&E'!$H:$H) -> 0 | H13: Gisela | I13: TPC
A14: P4 | B14: Linen | C14: =SUMIF('OS&E_FF&E'!$A:$A,Overview!$A14,'OS&E_FF&E'!$H:$H) -> 46800 | H14: Gisela
A15: P5 | B15: Transport & Installation | C15: =SUMIF('OS&E_FF&E'!$A:$A,Overview!$A15,'OS&E_FF&E'!$H:$H) -> 12400 | H15: Michiel | I15: Moving Company + assistance GC
A16: P6 | B16: Events equipment | C16: =SUMIF('OS&E_FF&E'!$A:$A,Overview!$A16,'OS&E_FF&E'!$H:$H) -> 0
A17: P7 | B17: Guestroom equipment and support | C17: =SUMIF('OS&E_FF&E'!$A:$A,Overview!$A17,'OS&E_FF&E'!$H:$H) -> 3787 | H17: Gisela | I17: toothbrush/paste/shavingkit etc.
A18: P8 | B18: Cleaning equipment and tools | C18: =SUMIF('OS&E_FF&E'!$A:$A,Overview!$A18,'OS&E_FF&E'!$H:$H) -> 5050 | H18: HM/Andi | I18: TD equipment
A19: P9 | B19: Wardrobe (uniforms) | C19: =SUMIF('OS&E_FF&E'!$A:$A,Overview!$A19,'OS&E_FF&E'!$H:$H) -> 5000 | H19: Marketing | I19: Uniforms Sweaters
A20: P10 | B20: Storeroom and pantry shelving | H20: HM/Andi | I20: In FF&E/OS&E groundfloor budget (total 51K)
A21: P11 | B21: FF&E PA | H21: Michiel | I21: Artelia capex FF&E groiundfloor
A22: P12 | B22: Wellness, fitness and recreational equipment | H22: Gisela | I22: 20K in budget Artelia
A23: P13 | B23: Baby items | C23: =SUMIF('OS&E_FF&E'!$A:$A,Overview!$A23,'OS&E_FF&E'!$H:$H) -> 713 | H23: HM/Andi
A24: P14 | B24: Office furniture & equipment | H24: HM/Andi | I24: In FF&E/OS&E groundfloor budget (total 51K)
A25: P15 | B25: Public areas accessories | C25: =SUMIF('OS&E_FF&E'!$A:$A,Overview!$A25,'OS&E_FF&E'!$H:$H) -> 6550 | H25: Gisela | I25: Bins public space
A26: P16 | B26: Art & accessories Rooms | H26: Gisela | I26: pictures rooms and statue:TPC and Art budget
A27: P17 | B27: IT | H27: Marc | I27: incl in capex
A28: P18 | B28: FF&E rooms | C28: =SUMIF('OS&E_FF&E'!$A:$A,Overview!$A28,'OS&E_FF&E'!$H:$H) -> 0 | H28: Michiel | I28: Incl in capex
A29: P19 | B29: internal signage | H29: Gisela | I29: Design Stylt 7.5K, rest in capex budget OS&e Groundfloor
A30: P20 | B30: OS&E Rooms | C30: =SUMIF('OS&E_FF&E'!$A:$A,Overview!$A30,'OS&E_FF&E'!$H:$H) -> 10645 | H30: Gisela | I30: Items excluded TPC contract
A31: P21 | B31: Plants | C31: =SUMIF('OS&E_FF&E'!$A:$A,Overview!$A31,'OS&E_FF&E'!$H:$H) -> 15000 | H31: HM/Andi | I31: not in Capex
A32: P22 | B32: Operational Equipment | C32: =SUMIF('OS&E_FF&E'!$A:$A,Overview!$A32,'OS&E_FF&E'!$H:$H) -> 16250.5 | H32: HM/Andi | I32: Marie Stella Maris + 7.5 K qwashmachine etc
A33: P23 | B33: Health & safety | C33: =SUMIF('OS&E_FF&E'!$A:$A,Overview!$A33,'OS&E_FF&E'!$H:$H) -> 2562 | H33: HM/Andi
B35: Total: | C35: =SUM(C8:C33) -> 149896.91 | D35: =SUM(D8:D33) -> 0
B37: total OS&E budget (file budget all dept 27 jan 2026) | C37: 165000
B38: total costs column C: purchase bij UHG | C38: =C35 -> 149896.91
B39: Contigency various items | C39: =-(C38-C37) -> 15103.09

Sheet OS&E_FF&E
A1: Package | C1: Items | D1: Item nr. | E1: Quantity | F1: Supplier | G1: Unit Price | H1: Total | I1: Picture/discription | J1: date of arrival | K1: order placed
A2: P1.0 | B2: =IF(INDEX(Overview!$C$8:$C$33,MATCH('OS&E_FF&E'!A2,Overview!$A$8:$A$33,0))=0,0,1) -> 0 | C2: Induction hot plate round (drop-in) | D2: F&B Wall / Grab & Go | E2: 0 | F2: Beuk - 63564 | G2: 2000 | H2: =E2*G2 -> 0 | L2: =INDEX(Overview!$B$8:$B$33,MATCH('OS&E_FF&E'!$A2,Overview!$A$8:$A$33,0)) -> F&B: Fixed Kitchen & Bar Equipment
A3: P1.0 | B3: =IF(INDEX(Overview!$C$8:$C$33,MATCH('OS&E_FF&E'!A3,Overview!$A$8:$A$33,0))=0,0,1) -> 0 | C3: Scholl Heat lamp | D3: F&B Wall / Grab & Go | E3: 0 | F3: Beuk - 63564 | G3: 350 | H3: =E3*G3 -> 0 | L3: =INDEX(Overview!$B$8:$B$33,MATCH('OS&E_FF&E'!$A3,Overview!$A$8:$A$33,0)) -> F&B: Fixed Kitchen & Bar Equipment
A4: P1.0 | B4: =IF(INDEX(Overview!$C$8:$C$33,MATCH('OS&E_FF&E'!A4,Overview!$A$8:$A$33,0))=0,0,1) -> 0 | C4: Double door refridgerator (black) | D4: F&B Wall / Grab & Go | E4: 0 | F4: Beuk - 63564 | G4: 3950 | H4: =E4*G4 -> 0 | L4: =INDEX(Overview!$B$8:$B$33,MATCH('OS&E_FF&E'!$A4,Overview!$A$8:$A$33,0)) -> F&B: Fixed Kitchen & Bar Equipment
A5: P1.0 | B5: =IF(INDEX(Overview!$C$8:$C$33,MATCH('OS&E_FF&E'!A5,Overview!$A$8:$A$33,0))=0,0,1) -> 0 | C5: Custom made stainless steel sink/work/dispensing furniture | D5: Kitchen equipment & appliances | E5: 0 | F5: Beuk - 63564 | G5: 9716 | H5: =E5*G5 -> 0 | L5: =INDEX(Overview!$B$8:$B$33,MATCH('OS&E_FF&E'!$A5,Overview!$A$8:$A$33,0)) -> F&B: Fixed Kitchen & Bar Equipment
A6: P1.0 | B6: =IF(INDEX(Overview!$C$8:$C$33,MATCH('OS&E_FF&E'!A6,Overview!$A$8:$A$33,0))=0,0,1) -> 0 | C6: Solid water tap with 1-lever / elbow control | D6: Kitchen equipment & appliances | E6: 0 | F6: Beuk - 63564 | G6: 175 | H6: =E6*G6 -> 0 | L6: =INDEX(Overview!$B$8:$B$33,MATCH('OS&E_FF&E'!$A6,Overview!$A$8:$A$33,0)) -> F&B: Fixed Kitchen & Bar Equipment
A7: P1.0 | B7: =IF(INDEX(Overview!$C$8:$C$33,MATCH('OS&E_FF&E'!A7,Overview!$A$8:$A$33,0))=0,0,1) -> 0 | C7: Rubbermaid waste container (with dolly) | D7: Kitchen equipment & appliances | E7: 0 | F7: Beuk - 63564 | G7: 130 | H7: =E7*G7 -> 0 | L7: =INDEX(Overview!$B$8:$B$33,MATCH('OS&E_FF&E'!$A7,Overview!$A$8:$A$33,0)) -> F&B: Fixed Kitchen & Bar Equipment
A8: P1.0 | B8: =IF(INDEX(Overview!$C$8:$C$33,MATCH('OS&E_FF&E'!A8,Overview!$A$8:$A$33,0))=0,0,1) -> 0 | C8: Roeder refrigerated workbench | D8: Kitchen equipment & appliances | E8: 0 | F8: Beuk - 63564 | G8: 3360 | H8: =E8*G8 -> 0 | L8: =INDEX(Overview!$B$8:$B$33,MATCH('OS&E_FF&E'!$A8,Overview!$A$8:$A$33,0)) -> F&B: Fixed Kitchen & Bar Equipment
A9: P1.0 | B9: =IF(INDEX(Overview!$C$8:$C$33,MATCH('OS&E_FF&E'!A9,Overview!$A$8:$A$33,0))=0,0,1) -> 0 | C9: Alto-Shaam warming cabinet | D9: Kitchen equipment & appliances | E9: 0 | F9: Beuk - 63564 | G9: 5695 | H9: =E9*G9 -> 0 | L9: =INDEX(Overview!$B$8:$B$33,MATCH('OS&E_FF&E'!$A9,Overview!$A$8:$A$33,0)) -> F&B: Fixed Kitchen & Bar Equipment
A10: P1.0 | B10: =IF(INDEX(Overview!$C$8:$C$33,MATCH('OS&E_FF&E'!A10,Overview!$A$8:$A$33,0))=0,0,1) -> 0 | C10: Vector Multi Cook Oven | D10: Kitchen equipment & appliances | E10: 0 | F10: Beuk - 63564 | G10: 28500 | H10: =E10*G10 -> 0 | L10: =INDEX(Overview!$B$8:$B$33,MATCH('OS&E_FF&E'!$A10,Overview!$A$8:$A$33,0)) -> F&B: Fixed Kitchen & Bar Equipment
A11: P1.0 | B11: =IF(INDEX(Overview!$C$8:$C$33,MATCH('OS&E_FF&E'!A11,Overview!$A$8:$A$33,0))=0,0,1) -> 0 | C11: Rational iCombi Pro Combisteamer | D11: Kitchen equipment & appliances | E11: 0 | F11: Beuk - 63564 | G11: 10570 | H11: =E11*G11 -> 0 | L11: =INDEX(Overview!$B$8:$B$33,MATCH('OS&E_FF&E'!$A11,Overview!$A$8:$A$33,0)) -> F&B: Fixed Kitchen & Bar Equipment
A12: P1.0 | B12: =IF(INDEX(Overview!$C$8:$C$33,MATCH('OS&E_FF&E'!A12,Overview!$A$8:$A$33,0))=0,0,1) -> 0 | C12: UltraVent Condensation Hood | D12: Kitchen equipment & appliances | E12: 0 | F12: Qualitytec Quote via Artelia, partly instalation budget tbd.. | G12: 33766 | H12: =E12*G12 -> 0 | L12: =INDEX(Overview!$B$8:$B$33,MATCH('OS&E_FF&E'!$A12,Overview!$A$8:$A$33,0)) -> F&B: Fixed Kitchen & Bar Equipment
A13: P1.0 | B13: =IF(INDEX(Overview!$C$8:$C$33,MATCH('OS&E_FF&E'!A13,Overview!$A$8:$A$33,0))=0,0,1) -> 0 | C13: Custom made stainless steel double wall shelf | D13: Kitchen equipment & appliances | E13: 0 | F13: Beuk - 63564 | G13: 1106 | H13: =E13*G13 -> 0 | L13: =INDEX(Overview!$B$8:$B$33,MATCH('OS&E_FF&E'!$A13,Overview!$A$8:$A$33,0)) -> F&B: Fixed Kitchen & Bar Equipment
... A27: P1.0 | B27: =IF(INDEX(Overview!$C$8:$C$33,MATCH('OS&E_FF&E'!A27,Overview!$A$8:$A$33,0))=0,0,1) -> 0 | C27: Cocktail bar | D27: Bar equipment & appliances | E27: 0 | F27: Beuk - 63564 | G27: 4650 | H27: =E27*G27 -> 0 | L27: =INDEX(Overview!$B$8:$B$33,MATCH('OS&E_FF&E'!$A27,Overview!$A$8:$A$33,0)) -> F&B: Fixed Kitchen & Bar Equipment
A28: P1.0 | B28: =IF(INDEX(Overview!$C$8:$C$33,MATCH('OS&E_FF&E'!A28,Overview!$A$8:$A$33,0))=0,0,1) -> 0 | C28: Gamko bar cooling (for milk) | D28: Bar equipment & appliances | E28: 0 | G28: 1470 | H28: =E28*G28 -> 0 | L28: =INDEX(Overview!$B$8:$B$33,MATCH('OS&E_FF&E'!$A28,Overview!$A$8:$A$33,0)) -> F&B: Fixed Kitchen & Bar Equipment
A29: P1.0 | B29: =IF(INDEX(Overview!$C$8:$C$33,MATCH('OS&E_FF&E'!A29,Overview!$A$8:$A$33,0))=0,0,1) -> 0 | C29: Pastry display (build-in) | D29: Bar equipment & appliances | E29: 0 | G29: 0 | H29: =E29*G29 -> 0 | L29: =INDEX(Overview!$B$8:$B$33,MATCH('OS&E_FF&E'!$A29,Overview!$A$8:$A$33,0)) -> F&B: Fixed Kitchen & Bar Equipment
A30: P1.0 | B30: =IF(INDEX(Overview!$C$8:$C$33,MATCH('OS&E_FF&E'!A30,Overview!$A$8:$A$33,0))=0,0,1) -> 0 | C30: Custom made stainless steel debrasing/feeding table with basket guideer racks | D30: Stewarding equipment & appliances | E30: 0 | F30: Beuk - 63564 | G30: 2972 | H30: =E30*G30 -> 0 | L30: =INDEX(Overview!$B$8:$B$33,MATCH('OS&E_FF&E'!$A30,Overview!$A$8:$A$33,0)) -> F&B: Fixed Kitchen & Bar Equipment
A31: P1.0 | B31: =IF(INDEX(Overview!$C$8:$C$33,MATCH('OS&E_FF&E'!A31,Overview!$A$8:$A$33,0))=0,0,1) -> 0 | C31: Pre-rinse shower (with tap) | D31: Stewarding equipment & appliances | E31: 0 | F31: Beuk - 63564 | G31: 315 | H31: =E31*G31 -> 0 | L31: =INDEX(Overview!$B$8:$B$33,MATCH('OS&E_FF&E'!$A31,Overview!$A$8:$A$33,0)) -> F&B: Fixed Kitchen & Bar Equipment
A32: P1.0 | B32: =IF(INDEX(Overview!$C$8:$C$33,MATCH('OS&E_FF&E'!A32,Overview!$A$8:$A$33,0))=0,0,1) -> 0 | C32: Rubbermaid waste container (with dolly) | D32: Stewarding equipment & appliances | E32: 0 | F32: Beuk - 63564 | G32: 130 | H32: =E32*G32 -> 0 | L32: =INDEX(Overview!$B$8:$B$33,MATCH('OS&E_FF&E'!$A32,Overview!$A$8:$A$33,0)) -> F&B: Fixed Kitchen & Bar Equipment
A33: P1.0 | B33: =IF(INDEX(Overview!$C$8:$C$33,MATCH('OS&E_FF&E'!A33,Overview!$A$8:$A$33,0))=0,0,1) -> 0 | C33: Custom made stainless steel debrasingshelf | D33: Stewarding equipment & appliances | E33: 0 | F33: Beuk - 63564 | G33: 996 | H33: =E33*G33 -> 0 | L33: =INDEX(Overview!$B$8:$B$33,MATCH('OS&E_FF&E'!$A33,Overview!$A$8:$A$33,0)) -> F&B: Fixed Kitchen & Bar Equipment
A34: P1.0 | B34: =IF(INDEX(Overview!$C$8:$C$33,MATCH('OS&E_FF&E'!A34,Overview!$A$8:$A$33,0))=0,0,1) -> 0 | C34: Rhima prewashing machine | D34: Stewarding equipment & appliances | E34: 0 | F34: Beuk - 63564 | G34: 5455 | H34: =E34*G34 -> 0 | L34: =INDEX(Overview!$B$8:$B$33,MATCH('OS&E_FF&E'!$A34,Overview!$A$8:$A$33,0)) -> F&B: Fixed Kitchen & Bar Equipment
A35: P1.0 | B35: =IF(INDEX(Overview!$C$8:$C$33,MATCH('OS&E_FF&E'!A35,Overview!$A$8:$A$33,0))=0,0,1) -> 0 | C35: Custom made stainless steel connector | D35: Stewarding equipment & appliances | E35: 0 | F35: Beuk - 63564 | G35: 395 | H35: =E35*G35 -> 0 | L35: =INDEX(Overview!$B$8:$B$33,MATCH('OS&E_FF&E'!$A35,Overview!$A$8:$A$33,0)) -> F&B: Fixed Kitchen & Bar Equipment
A36: P1.0 | B36: =IF(INDEX(Overview!$C$8:$C$33,MATCH('OS&E_FF&E'!A36,Overview!$A$8:$A$33,0))=0,0,1) -> 0 | C36: Rhima pass-through dishwasher with energy-saving steam condensing unit | D36: Stewarding equipment & appliances | E36: 0 | F36: Beuk - 63564 | G36: 13300 | H36: =E36*G36 -> 0 | L36: =INDEX(Overview!$B$8:$B$33,MATCH('OS&E_FF&E'!$A36,Overview!$A$8:$A$33,0)) -> F&B: Fixed Kitchen & Bar Equipment
A37: P1.0 | B37: =IF(INDEX(Overview!$C$8:$C$33,MATCH('OS&E_FF&E'!A37,Overview!$A$8:$A$33,0))=0,0,1) -> 0 | C37: Weighted boiler element | D37: Stewarding equipment & appliances | E37: 0 | F37: Beuk - 63564 | G37: 605 | H37: =E37*G37 -> 0 | L37: =INDEX(Overview!$B$8:$B$33,MATCH('OS&E_FF&E'!$A37,Overview!$A$8:$A$33,0)) -> F&B: Fixed Kitchen & Bar Equipment
A38: P1.0 | B38: =IF(INDEX(Overview!$C$8:$C$33,MATCH('OS&E_FF&E'!A38,Overview!$A$8:$A$33,0))=0,0,1) -> 0 | C38: Custom made stainless steel drain-/roller table | D38: Stewarding equipment & appliances | E38: 0 | F38: Beuk - 63564 | G38: 1786 | H38: =E38*G38 -> 0 | L38: =INDEX(Overview!$B$8:$B$33,MATCH('OS&E_FF&E'!$A38,Overview!$A$8:$A$33,0)) -> F&B: Fixed Kitchen & Bar Equipment
A39: P1.0 | B39: =IF(INDEX(Overview!$C$8:$C$33,MATCH('OS&E_FF&E'!A39,Overview!$A$8:$A$33,0))=0,0,1) -> 0 | C39: Rhima full-automatic volume-operated water descaler | D39: Stewarding equipment & appliances | E39: 0 | F39: Beuk - 63564 | G39: 1395 | H39: =E39*G39 -> 0 | L39: =INDEX(Overview!$B$8:$B$33,MATCH('OS&E_FF&E'!$A39,Overview!$A$8:$A$33,0)) -> F&B: Fixed Kitchen & Bar Equipment
A40: P1.0 | B40: =IF(INDEX(Overview!$C$8:$C$33,MATCH('OS&E_FF&E'!A40,Overview!$A$8:$A$33,0))=0,0,1) -> 0 | C40: Rhima Pro Wash Water softening salt | D40: Stewarding equipment & appliances | E40: 0 | F40: Beuk - 63564 | G40: 29 | H40: =E40*G40 -> 0 | L40: =INDEX(Overview!$B$8:$B$33,MATCH('OS&E_FF&E'!$A40,Overview!$A$8:$A$33,0)) -> F&B: Fixed Kitchen & Bar Equipment
A41: P1.0 | B41: =IF(INDEX(Overview!$C$8:$C$33,MATCH('OS&E_FF&E'!A41,Overview!$A$8:$A$33,0))=0,0,1) -> 0 | C41: Custom mode stainless steel cutlery sorting station | D41: Stewarding equipment & appliances | E41: 0 | F41: Beuk - 63564 | G41: 165 | H41: =E41*G41 -> 0 | L41: =INDEX(Overview!$B$8:$B$33,MATCH('OS&E_FF&E'!$A41,Overview!$A$8:$A$33,0)) -> F&B: Fixed Kitchen & Bar Equipment
... A45: P1.0 | B45: =IF(INDEX(Overview!$C$8:$C$33,MATCH('OS&E_FF&E'!A45,Overview!$A$8:$A$33,0))=0,0,1) -> 0 | C45: Custom cold storage/freezer room | D45: Storage (fridge, freezer & dry) | E45: 0 | F45: Querci Quote via Artelia | G45: 17560 | H45: =E45*G45 -> 0 | L45: =INDEX(Overview!$B$8:$B$33,MATCH('OS&E_FF&E'!$A45,Overview!$A$8:$A$33,0)) -> F&B: Fixed Kitchen & Bar Equipment
A46: P1.0 | B46: =IF(INDEX(Overview!$C$8:$C$33,MATCH('OS&E_FF&E'!A46,Overview!$A$8:$A$33,0))=0,0,1) -> 0 | C46: Fermostock HACCP 4 level shelf in U-shape | D46: Storage (fridge, freezer & dry) | E46: 0 | G46: 1850 | H46: =E46*G46 -> 0 | L46: =INDEX(Overview!$B$8:$B$33,MATCH('OS&E_FF&E'!$A46,Overview!$A$8:$A$33,0)) -> F&B: Fixed Kitchen & Bar Equipment
A47: P1.0 | B47: =IF(INDEX(Overview!$C$8:$C$33,MATCH('OS&E_FF&E'!A47,Overview!$A$8:$A$33,0))=0,0,1) -> 0 | C47: Fermostock HACCP 4 level shelf in U-shape | D47: Storage (fridge, freezer & dry) | E47: 0 | F47: Beuk - 63564 | G47: 1850 | H47: =E47*G47 -> 0 | L47: =INDEX(Overview!$B$8:$B$33,MATCH('OS&E_FF&E'!$A47,Overview!$A$8:$A$33,0)) -> F&B: Fixed Kitchen & Bar Equipment
A48: P1.0 | B48: =IF(INDEX(Overview!$C$8:$C$33,MATCH('OS&E_FF&E'!A48,Overview!$A$8:$A$33,0))=0,0,1) -> 0 | C48: Fermostock HACCP 5 level shelf in U-shape | D48: Storage (fridge, freezer & dry) | E48: 0 | F48: Beuk - 63564 | G48: 2250 | H48: =E48*G48 -> 0 | L48: =INDEX(Overview!$B$8:$B$33,MATCH('OS&E_FF&E'!$A48,Overview!$A$8:$A$33,0)) -> F&B: Fixed Kitchen & Bar Equipment
A49: P1.0 | B49: =IF(INDEX(Overview!$C$8:$C$33,MATCH('OS&E_FF&E'!A49,Overview!$A$8:$A$33,0))=0,0,1) -> 0 | C49: Projected installation costs | D49: Connection & placement fees | E49: 0 | F49: Beuk - 63564 | G49: 3500 | H49: =E49*G49 -> 0 | L49: =INDEX(Overview!$B$8:$B$33,MATCH('OS&E_FF&E'!$A49,Overview!$A$8:$A$33,0)) -> F&B: Fixed Kitchen & Bar Equipment
A50: P1.0 | B50: =IF(INDEX(Overview!$C$8:$C$33,MATCH('OS&E_FF&E'!A50,Overview!$A$8:$A$33,0))=0,0,1) -> 0 | C50: Projected transportation costs | D50: Transportation costs | E50: 0 | F50: Beuk - 63564 | G50: 6450 | H50: =E50*G50 -> 0 | L50: =INDEX(Overview!$B$8:$B$33,MATCH('OS&E_FF&E'!$A50,Overview!$A$8:$A$33,0)) -> F&B: Fixed Kitchen & Bar Equipment
A51: P1.0 | B51: =IF(INDEX(Overview!$C$8:$C$33,MATCH('OS&E_FF&E'!A51,Overview!$A$8:$A$33,0))=0,0,1) -> 0 | C51: Special EXTRA rounding and project discount on NETTO quote (on undivided order) | D51: Discount | E51: 0 | F51: Beuk - 63564 | G51: =-3542+50 -> -3492 | H51: =E51*G51 -> 0 | L51: =INDEX(Overview!$B$8:$B$33,MATCH('OS&E_FF&E'!$A51,Overview!$A$8:$A$33,0)) -> F&B: Fixed Kitchen & Bar Equipment
A52: P1.1 | B52: =IF(INDEX(Overview!$C$8:$C$33,MATCH('OS&E_FF&E'!A52,Overview!$A$8:$A$33,0))=0,0,1) -> 0 | C52: Single Jet 6 5.6 Kw | D52: Back of House | E52: 0 | G52: 2784.64 | H52: =E52*G52 -> 0 | L52: =INDEX(Overview!$B$8:$B$33,MATCH('OS&E_FF&E'!$A52,Overview!$A$8:$A$33,0)) -> F&B: Coffee equipment
A53: P1.1 | B53: =IF(INDEX(Overview!$C$8:$C$33,MATCH('OS&E_FF&E'!A53,Overview!$A$8:$A$33,0))=0,0,1) -> 0 | C53: URN | D53: Back of House | E53: 0 | G53: 591.64 | H53: =E53*G53 -> 0 | L53: =INDEX(Overview!$B$8:$B$33,MATCH('OS&E_FF&E'!$A53,Overview!$A$8:$A$33,0)) -> F&B: Coffee equipment
A54: P1.1 | B54: =IF(INDEX(Overview!$C$8:$C$33,MATCH('OS&E_FF&E'!A54,Overview!$A$8:$A$33,0))=0,0,1) -> 0 | C54: Jet grinder | D54: Back of House | E54: 0 | G54: 2141.79 | H54: =E54*G54 -> 0 | L54: =INDEX(Overview!$B$8:$B$33,MATCH('OS&E_FF&E'!$A54,Overview!$A$8:$A$33,0)) -> F&B: Coffee equipment
A55: P1.1 | B55: =IF(INDEX(Overview!$C$8:$C$33,MATCH('OS&E_FF&E'!A55,Overview!$A$8:$A$33,0))=0,0,1) -> 0 | C55: Transport | D55: Back of House | E55: 0 | G55: 350 | H55: =E55*G55 -> 0 | L55: =INDEX(Overview!$B$8:$B$33,MATCH('OS&E_FF&E'!$A55,Overview!$A$8:$A$33,0)) -> F&B: Coffee equipment
A56: P1.1 | B56: =IF(INDEX(Overview!$C$8:$C$33,MATCH('OS&E_FF&E'!A56,Overview!$A$8:$A$33,0))=0,0,1) -> 0 | C56: Full Automatic Spritz Bar tbd | D56: Back of House | E56: 0 | G56: 2000 | H56: =E56*G56 -> 0 | L56: =INDEX(Overview!$B$8:$B$33,MATCH('OS&E_FF&E'!$A56,Overview!$A$8:$A$33,0)) -> F&B: Coffee equipment
A57: P1.1 | B57: =IF(INDEX(Overview!$C$8:$C$33,MATCH('OS&E_FF&E'!A57,Overview!$A$8:$A$33,0))=0,0,1) -> 0 | C57: San Remo Racer (2 group) | D57: Bar equipment & appliances | E57: 0 | G57: 16610 | H57: =E57*G57 -> 0 | L57: =INDEX(Overview!$B$8:$B$33,MATCH('OS&E_FF&E'!$A57,Overview!$A$8:$A$33,0)) -> F&B: Coffee equipment
A58: P1.1 | B58: =IF(INDEX(Overview!$C$8:$C$33,MATCH('OS&E_FF&E'!A58,Overview!$A$8:$A$33,0))=0,0,1) -> 0 | C58: Additional cost customisation espresso machine | D58: Bar equipment & appliances | E58: 0 | G58: 0 | H58: =E58*G58 -> 0 | L58: =INDEX(Overview!$B$8:$B$33,MATCH('OS&E_FF&E'!$A58,Overview!$A$8:$A$33,0)) -> F&B: Coffee equipment
A59: P1.1 | B59: =IF(INDEX(Overview!$C$8:$C$33,MATCH('OS&E_FF&E'!A59,Overview!$A$8:$A$33,0))=0,0,1) -> 0 | C59: Bottomless Knockbox | D59: Bar equipment & appliances | E59: 0 | G59: 46 | H59: =E59*G59 -> 0 | L59: =INDEX(Overview!$B$8:$B$33,MATCH('OS&E_FF&E'!$A59,Overview!$A$8:$A$33,0)) -> F&B: Coffee equipment
A60: P1.1 | B60: =IF(INDEX(Overview!$C$8:$C$33,MATCH('OS&E_FF&E'!A60,Overview!$A$8:$A$33,0))=0,0,1) -> 0 | C60: SR 83 OD | D60: Bar equipment & appliances | E60: 0 | G60: 600 | H60: =E60*G60 -> 0 | L60: =INDEX(Overview!$B$8:$B$33,MATCH('OS&E_FF&E'!$A60,Overview!$A$8:$A$33,0)) -> F&B: Coffee equipment
A61: P1.1 | B61: =IF(INDEX(Overview!$C$8:$C$33,MATCH('OS&E_FF&E'!A61,Overview!$A$8:$A$33,0))=0,0,1) -> 0 | C61: Extra pump Line (fo) | D61: Bar equipment & appliances | E61: 0 | G61: 420 | H61: =E61*G61 -> 0 | L61: =INDEX(Overview!$B$8:$B$33,MATCH('OS&E_FF&E'!$A61,Overview!$A$8:$A$33,0)) -> F&B: Coffee equipment
A62: P1.1 | B62: =IF(INDEX(Overview!$C$8:$C$33,MATCH('OS&E_FF&E'!A62,Overview!$A$8:$A$33,0))=0,0,1) -> 0 | C62: Puqpress Q2 | D62: Bar equipment & appliances | E62: 0 | G62: 885 | H62: =E62*G62 -> 0 | L62: =INDEX(Overview!$B$8:$B$33,MATCH('OS&E_FF&E'!$A62,Overview!$A$8:$A$33,0)) -> F&B: Coffee equipment
A63: P1.1 | B63: =IF(INDEX(Overview!$C$8:$C$33,MATCH('OS&E_FF&E'!A63,Overview!$A$8:$A$33,0))=0,0,1) -> 0 | C63: Milkmate 2.0 | D63: Bar equipment & appliances | E63: 0 | G63: 2940 | H63: =E63*G63 -> 0 | L63: =INDEX(Overview!$B$8:$B$33,MATCH('OS&E_FF&E'!$A63,Overview!$A$8:$A$33,0)) -> F&B: Coffee equipment
... A65: P1.1 | B65: =IF(INDEX(Overview!$C$8:$C$33,MATCH('OS&E_FF&E'!A65,Overview!$A$8:$A$33,0))=0,0,1) -> 0 | C65: Pitcher rinser De Vrij M | D65: Bar equipment & appliances | E65: 0 | G65: 214 | H65: =E65*G65 -> 0 | L65: =INDEX(Overview!$B$8:$B$33,MATCH('OS&E_FF&E'!$A65,Overview!$A$8:$A$33,0)) -> F&B: Coffee equipment
A66: P1.2 | B66: =IF(INDEX(Overview!$C$8:$C$33,MATCH('OS&E_FF&E'!A66,Overview!$A$8:$A$33,0))=0,0,1) -> 0 | C66: Lightspeed K-series 1 POS Station, Tableside or Mobile Inventory | D66: POS System | E66: 0 | F66: Lightspeed 3013166 | G66: 1068 | H66: =E66*G66 -> 0 | L66: =INDEX(Overview!$B$8:$B$33,MATCH('OS&E_FF&E'!$A66,Overview!$A$8:$A$33,0)) -> F&B: Operating Systems
A67: P1.2 | B67: =IF(INDEX(Overview!$C$8:$C$33,MATCH('OS&E_FF&E'!A67,Overview!$A$8:$A$33,0))=0,0,1) -> 0 | C67: 1 POS Station, Tableside or Mobile | D67: POS System | E67: 0 | F67: Lightspeed 3013166 | G67: 348 | H67: =E67*G67 -> 0 | L67: =INDEX(Overview!$B$8:$B$33,MATCH('OS&E_FF&E'!$A67,Overview!$A$8:$A$33,0)) -> F&B: Operating Systems
A68: P1.2 | B68: =IF(INDEX(Overview!$C$8:$C$33,MATCH('OS&E_FF&E'!A68,Overview!$A$8:$A$33,0))=0,0,1) -> 0 | C68: Silver Base Pro Service License 1/3 | D68: POS System | E68: 0 | F68: Lightspeed 3013166 | G68: =5364/3 -> 1788 | H68: =E68*G68 -> 0 | L68: =INDEX(Overview!$B$8:$B$33,MATCH('OS&E_FF&E'!$A68,Overview!$A$8:$A$33,0)) -> F&B: Operating Systems
A69: P1.2 | B69: =IF(INDEX(Overview!$C$8:$C$33,MATCH('OS&E_FF&E'!A69,Overview!$A$8:$A$33,0))=0,0,1) -> 0 | C69: FDM (Fiscal Data Module) | D69: POS System | E69: 0 | F69: Lightspeed 3013166 | G69: =758/2 -> 379 | H69: =E69*G69 -> 0 | L69: =INDEX(Overview!$B$8:$B$33,MATCH('OS&E_FF&E'!$A69,Overview!$A$8:$A$33,0)) -> F&B: Operating Systems
A70: P1.2 | B70: =IF(INDEX(Overview!$C$8:$C$33,MATCH('OS&E_FF&E'!A70,Overview!$A$8:$A$33,0))=0,0,1) -> 0 | C70: FDM Service Charge | D70: POS System | E70: 0 | F70: Lightspeed 3013166 | G70: =184/2 -> 92 | H70: =E70*G70 -> 0 | L70: =INDEX(Overview!$B$8:$B$33,MATCH('OS&E_FF&E'!$A70,Overview!$A$8:$A$33,0)) -> F&B: Operating Systems
A71: P1.2 | B71: =IF(INDEX(Overview!$C$8:$C$33,MATCH('OS&E_FF&E'!A71,Overview!$A$8:$A$33,0))=0,0,1) -> 0 | C71: EU: Apple Ipad 10.2", WIFI 64 GB, Space Grey 9th Gen | D71: POS System | E71: 0 | F71: Lightspeed 3013166 | G71: =1914/6 -> 319 | H71: =E71*G71 -> 0 | L71: =INDEX(Overview!$B$8:$B$33,MATCH('OS&E_FF&E'!$A71,Overview!$A$8:$A$33,0)) -> F&B: Operating Systems
A72: P1.2 | B72: =IF(INDEX(Overview!$C$8:$C$33,MATCH('OS&E_FF&E'!A72,Overview!$A$8:$A$33,0))=0,0,1) -> 0 | C72: Windfall Ipad stand 10.2" 8th/9th Gen | D72: POS System | E72: 0 | F72: Lightspeed 3013166 | G72: =864/6 -> 144 | H72: =E72*G72 -> 0 | L72: =INDEX(Overview!$B$8:$B$33,MATCH('OS&E_FF&E'!$A72,Overview!$A$8:$A$33,0)) -> F&B: Operating Systems
A73: P1.2 | B73: =IF(INDEX(Overview!$C$8:$C$33,MATCH('OS&E_FF&E'!A73,Overview!$A$8:$A$33,0))=0,0,1) -> 0 | C73: EU: Epson TM-M30II-NT LAN Receipt Printer (Ethernet, Black) | D73: POS System | E73: 0 | F73: Lightspeed 3013166 | G73: =1974/6 -> 329 | H73: =E73*G73 -> 0 | L73: =INDEX(Overview!$B$8:$B$33,MATCH('OS&E_FF&E'!$A73,Overview!$A$8:$A$33,0)) -> F&B: Operating Systems
A74: P1.2 | B74: =IF(INDEX(Overview!$C$8:$C$33,MATCH('OS&E_FF&E'!A74,Overview!$A$8:$A$33,0))=0,0,1) -> 0 | C74: Thermal Paper for Network Printer | D74: POS System | E74: 0 | F74: Lightspeed 3013166 | G74: =117/3 -> 39 | H74: =E74*G74 -> 0 | L74: =INDEX(Overview!$B$8:$B$33,MATCH('OS&E_FF&E'!$A74,Overview!$A$8:$A$33,0)) -> F&B: Operating Systems
A75: P1.2 | B75: =IF(INDEX(Overview!$C$8:$C$33,MATCH('OS&E_FF&E'!A75,Overview!$A$8:$A$33,0))=0,0,1) -> 0 | C75: Lightspeed FST - On site Implementation Package (small) | D75: POS System | E75: 0 | F75: Lightspeed 3013166 | G75: =3600/3 -> 1200 | H75: =E75*G75 -> 0 | L75: =INDEX(Overview!$B$8:$B$33,MATCH('OS&E_FF&E'!$A75,Overview!$A$8:$A$33,0)) -> F&B: Operating Systems
A76: P1.2 | B76: =IF(INDEX(Overview!$C$8:$C$33,MATCH('OS&E_FF&E'!A76,Overview!$A$8:$A$33,0))=0,0,1) -> 0 | C76: Payment terminal Receipt Paper (20 rolls) | D76: POS System | E76: 0 | F76: Lightspeed 3013166 | G76: =36/3 -> 12 | H76: =E76*G76 -> 0 | L76: =INDEX(Overview!$B$8:$B$33,MATCH('OS&E_FF&E'!$A76,Overview!$A$8:$A$33,0)) -> F&B: Operating Systems
A77: P1.2 | B77: =IF(INDEX(Overview!$C$8:$C$33,MATCH('OS&E_FF&E'!A77,Overview!$A$8:$A$33,0))=0,0,1) -> 0 | C77: PROMO: Payments Restaurant Mobile S1F2 (EU) (€360 Value) | D77: POS System | E77: 0 | F77: Lightspeed 3013166 | G77: 0 | H77: =E77*G77 -> 0 | L77: =INDEX(Overview!$B$8:$B$33,MATCH('OS&E_FF&E'!$A77,Overview!$A$8:$A$33,0)) -> F&B: Operating Systems
A78: P1.2 | B78: =IF(INDEX(Overview!$C$8:$C$33,MATCH('OS&E_FF&E'!A78,Overview!$A$8:$A$33,0))=0,0,1) -> 0 | C78: Shipping & Handling (Europe) 1/3 | D78: POS System | E78: 0 | F78: Lightspeed 3013166 | G78: =12.5/3 -> 4.1666667 | H78: =E78*G78 -> 0 | L78: =INDEX(Overview!$B$8:$B$33,MATCH('OS&E_FF&E'!$A78,Overview!$A$8:$A$33,0)) -> F&B: Operating Systems
A79: P1.3 | B79: =IF(INDEX(Overview!$C$8:$C$33,MATCH('OS&E_FF&E'!A79,Overview!$A$8:$A$33,0))=0,0,1) -> 0 | C79: Small plate 20 cm | D79: Chinaware | E79: 150 | G79: 12.6 | H79: =E79*G79 -> 1890 | L79: =INDEX(Overview!$B$8:$B$33,MATCH('OS&E_FF&E'!$A79,Overview!$A$8:$A$33,0)) -> F&B: Operating Equipment F&B
A80: P1.3 | B80: =IF(INDEX(Overview!$C$8:$C$33,MATCH('OS&E_FF&E'!A80,Overview!$A$8:$A$33,0))=0,0,1) -> 0 | C80: Large plate 26 cm | D80: Chinaware | E80: 200 | G80: 15.96 | H80: =E80*G80 -> 3192 | L80: =INDEX(Overview!$B$8:$B$33,MATCH('OS&E_FF&E'!$A80,Overview!$A$8:$A$33,0)) -> F&B: Operating Equipment F&B
A81: P1.3 | B81: =IF(INDEX(Overview!$C$8:$C$33,MATCH('OS&E_FF&E'!A81,Overview!$A$8:$A$33,0))=0,0,1) -> 0 | C81: Deep plate | D81: Chinaware | E81: 150 | G81: 17.56 | H81: =E81*G81 -> 2634 | L81: =INDEX(Overview!$B$8:$B$33,MATCH('OS&E_FF&E'!$A81,Overview!$A$8:$A$33,0)) -> F&B: Operating Equipment F&B
A82: P1.3 | B82: =IF(INDEX(Overview!$C$8:$C$33,MATCH('OS&E_FF&E'!A82,Overview!$A$8:$A$33,0))=0,0,1) -> 0 | C82: Serving platter | D82: Chinaware | E82: 25 | G82: 23.35 | H82: =E82*G82 -> 583.75 | L82: =INDEX(Overview!$B$8:$B$33,MATCH('OS&E_FF&E'!$A82,Overview!$A$8:$A$33,0)) -> F&B: Operating Equipment F&B
A83: P1.3 | B83: =IF(INDEX(Overview!$C$8:$C$33,MATCH('OS&E_FF&E'!A83,Overview!$A$8:$A$33,0))=0,0,1) -> 0 | C83: Snack bowl | D83: Chinaware | E83: 75 | G83: 4.76 | H83: =E83*G83 -> 357 | L83: =INDEX(Overview!$B$8:$B$33,MATCH('OS&E_FF&E'!$A83,Overview!$A$8:$A$33,0)) -> F&B: Operating Equipment F&B
A84: P1.3 | B84: =IF(INDEX(Overview!$C$8:$C$33,MATCH('OS&E_FF&E'!A84,Overview!$A$8:$A$33,0))=0,0,1) -> 0 | C84: Bowl | D84: Chinaware | E84: 150 | G84: 7.96 | H84: =E84*G84 -> 1194 | L84: =INDEX(Overview!$B$8:$B$33,MATCH('OS&E_FF&E'!$A84,Overview!$A$8:$A$33,0)) -> F&B: Operating Equipment F&B
A85: P1.3 | B85: =IF(INDEX(Overview!$C$8:$C$33,MATCH('OS&E_FF&E'!A85,Overview!$A$8:$A$33,0))=0,0,1) -> 0 | C85: Bento tray | D85: Chinaware | E85: 200 | G85: 16 | H85: =E85*G85 -> 3200 | L85: =INDEX(Overview!$B$8:$B$33,MATCH('OS&E_FF&E'!$A85,Overview!$A$8:$A$33,0)) -> F&B: Operating Equipment F&B
A86: P1.3 | B86: =IF(INDEX(Overview!$C$8:$C$33,MATCH('OS&E_FF&E'!A86,Overview!$A$8:$A$33,0))=0,0,1) -> 0 | C86: Container (weckpot/mason jar) | D86: Chinaware | E86: 75 | G86: 2.08 | H86: =E86*G86 -> 156 | L86: =INDEX(Overview!$B$8:$B$33,MATCH('OS&E_FF&E'!$A86,Overview!$A$8:$A$33,0)) -> F&B: Operating Equipment F&B
A87: P1.3 | B87: =IF(INDEX(Overview!$C$8:$C$33,MATCH('OS&E_FF&E'!A87,Overview!$A$8:$A$33,0))=0,0,1) -> 0 | C87: Pepper and salt mill | D87: Chinaware | E87: 15 | G87: 26.9 | H87: =E87*G87 -> 403.5 | L87: =INDEX(Overview!$B$8:$B$33,MATCH('OS&E_FF&E'!$A87,Overview!$A$8:$A$33,0)) -> F&B: Operating Equipment F&B
A88: P1.3 | B88: =IF(INDEX(Overview!$C$8:$C$33,MATCH('OS&E_FF&E'!A88,Overview!$A$8:$A$33,0))=0,0,1) -> 0 | C88: Sauce container/cup/bowl | D88: Chinaware | E88: 150 | G88: 4.09 | H88: =E88*G88 -> 613.5 | L88: =INDEX(Overview!$B$8:$B$33,MATCH('OS&E_FF&E'!$A88,Overview!$A$8:$A$33,0)) -> F&B: Operating Equipment F&B
A89: P1.3 | B89: =IF(INDEX(Overview!$C$8:$C$33,MATCH('OS&E_FF&E'!A89,Overview!$A$8:$A$33,0))=0,0,1) -> 0 | C89: Little spoon | D89: Cutlery | E89: 250 | G89: 1.67 | H89: =E89*G89 -> 417.5 | L89: =INDEX(Overview!$B$8:$B$33,MATCH('OS&E_FF&E'!$A89,Overview!$A$8:$A$33,0)) -> F&B: Operating Equipment F&B
A90: P1.3 | B90: =IF(INDEX(Overview!$C$8:$C$33,MATCH('OS&E_FF&E'!A90,Overview!$A$8:$A$33,0))=0,0,1) -> 0 | C90: Large spoon | D90: Cutlery | E90: 250 | G90: 2.42 | H90: =E90*G90 -> 605 | L90: =INDEX(Overview!$B$8:$B$33,MATCH('OS&E_FF&E'!$A90,Overview!$A$8:$A$33,0)) -> F&B: Operating Equipment F&B
... A174: P1.3 | B174: =IF(INDEX(Overview!$C$8:$C$33,MATCH('OS&E_FF&E'!A174,Overview!$A$8:$A$33,0))=0,0,1) -> 0 | C174: Silicon mats 1/1 | D174: Kitchen equipment | E174: 5 | G174: 20.11 | H174: =E174*G174 -> 100.55 | L174: =INDEX(Overview!$B$8:$B$33,MATCH('OS&E_FF&E'!$A174,Overview!$A$8:$A$33,0)) -> F&B: Operating Equipment F&B
A175: P1.3 | B175: =IF(INDEX(Overview!$C$8:$C$33,MATCH('OS&E_FF&E'!A175,Overview!$A$8:$A$33,0))=0,0,1) -> 0 | C175: Can opener | D175: Kitchen equipment | E175: 1 | H175: =E175*G175 -> 0 | L175: =INDEX(Overview!$B$8:$B$33,MATCH('OS&E_FF&E'!$A175,Overview!$A$8:$A$33,0)) -> F&B: Operating Equipment F&B
A176: P1.3 | B176: =IF(INDEX(Overview!$C$8:$C$33,MATCH('OS&E_FF&E'!A176,Overview!$A$8:$A$33,0))=0,0,1) -> 0 | C176: Oven tray | D176: Kitchen equipment | E176: 10 | G176: 20.95 | H176: =E176*G176 -> 209.5 | L176: =INDEX(Overview!$B$8:$B$33,MATCH('OS&E_FF&E'!$A176,Overview!$A$8:$A$33,0)) -> F&B: Operating Equipment F&B
A177: P1.3 | B177: =IF(INDEX(Overview!$C$8:$C$33,MATCH('OS&E_FF&E'!A177,Overview!$A$8:$A$33,0))=0,0,1) -> 0 | C177: Serving shovel | D177: Kitchen equipment | E177: 1 | G177: 19.52 | H177: =E177*G177 -> 19.52 | L177: =INDEX(Overview!$B$8:$B$33,MATCH('OS&E_FF&E'!$A177,Overview!$A$8:$A$33,0)) -> F&B: Operating Equipment F&B
A178: P1.3 | B178: =IF(INDEX(Overview!$C$8:$C$33,MATCH('OS&E_FF&E'!A178,Overview!$A$8:$A$33,0))=0,0,1) -> 0 | C178: Kitchen towel | D178: Kitchen equipment | E178: 20 | G178: 2.95 | H178: =E178*G178 -> 59 | L178: =INDEX(Overview!$B$8:$B$33,MATCH('OS&E_FF&E'!$A178,Overview!$A$8:$A$33,0)) -> F&B: Operating Equipment F&B
A179: P1.3 | B179: =IF(INDEX(Overview!$C$8:$C$33,MATCH('OS&E_FF&E'!A179,Overview!$A$8:$A$33,0))=0,0,1) -> 0 | C179: Scraper (pannenlikker) | D179: Kitchen equipment | E179: 2 | G179: 5.44 | H179: =E179*G179 -> 10.88 | L179: =INDEX(Overview!$B$8:$B$33,MATCH('OS&E_FF&E'!$A179,Overview!$A$8:$A$33,0)) -> F&B: Operating Equipment F&B
A180: P1.3 | B180: =IF(INDEX(Overview!$C$8:$C$33,MATCH('OS&E_FF&E'!A180,Overview!$A$8:$A$33,0))=0,0,1) -> 0 | C180: Inox spatula | D180: Kitchen equipment | E180: 2 | G180: 5.86 | H180: =E180*G180 -> 11.72 | L180: =INDEX(Overview!$B$8:$B$33,MATCH('OS&E_FF&E'!$A180,Overview!$A$8:$A$33,0)) -> F&B: Operating Equipment F&B
A181: P1.3 | B181: =IF(INDEX(Overview!$C$8:$C$33,MATCH('OS&E_FF&E'!A181,Overview!$A$8:$A$33,0))=0,0,1) -> 0 | C181: Pizza cutter | D181: Kitchen equipment | E181: 2 | G181: 15.36 | H181: =E181*G181 -> 30.72 | L181: =INDEX(Overview!$B$8:$B$33,MATCH('OS&E_FF&E'!$A181,Overview!$A$8:$A$33,0)) -> F&B: Operating Equipment F&B
A182: P1.3 | B182: =IF(INDEX(Overview!$C$8:$C$33,MATCH('OS&E_FF&E'!A182,Overview!$A$8:$A$33,0))=0,0,1) -> 0 | C182: Cutting board (red, green, white, blue) | D182: Kitchen equipment | E182: 4 | G182: 32.5 | H182: =E182*G182 -> 130 | L182: =INDEX(Overview!$B$8:$B$33,MATCH('OS&E_FF&E'!$A182,Overview!$A$8:$A$33,0)) -> F&B: Operating Equipment F&B
A183: P1.3 | B183: =IF(INDEX(Overview!$C$8:$C$33,MATCH('OS&E_FF&E'!A183,Overview!$A$8:$A$33,0))=0,0,1) -> 0 | C183: Thermometer | D183: Kitchen equipment | E183: 1 | G183: 178.2 | H183: =E183*G183 -> 178.2 | L183: =INDEX(Overview!$B$8:$B$33,MATCH('OS&E_FF&E'!$A183,Overview!$A$8:$A$33,0)) -> F&B: Operating Equipment F&B
A184: P1.3 | B184: =IF(INDEX(Overview!$C$8:$C$33,MATCH('OS&E_FF&E'!A184,Overview!$A$8:$A$33,0))=0,0,1) -> 0 | C184: Kitchen knife | D184: Kitchen equipment | E184: 4 | G184: 32.07 | H184: =E184*G184 -> 128.28 | L184: =INDEX(Overview!$B$8:$B$33,MATCH('OS&E_FF&E'!$A184,Overview!$A$8:$A$33,0)) -> F&B: Operating Equipment F&B
A185: P1.3 | B185: =IF(INDEX(Overview!$C$8:$C$33,MATCH('OS&E_FF&E'!A185,Overview!$A$8:$A$33,0))=0,0,1) -> 0 | C185: Zester | D185: Kitchen equipment | E185: 1 | G185: 8.22 | H185: =E185*G185 -> 8.22 | L185: =INDEX(Overview!$B$8:$B$33,MATCH('OS&E_FF&E'!$A185,Overview!$A$8:$A$33,0)) -> F&B: Operating Equipment F&B
A186: P1.3 | B186: =IF(INDEX(Overview!$C$8:$C$33,MATCH('OS&E_FF&E'!A186,Overview!$A$8:$A$33,0))=0,0,1) -> 0 | C186: Peeler | D186: Kitchen equipment | E186: 1 | G186: 3.67 | H186: =E186*G186 -> 3.67 | L186: =INDEX(Overview!$B$8:$B$33,MATCH('OS&E_FF&E'!$A186,Overview!$A$8:$A$33,0)) -> F&B: Operating Equipment F&B
A187: P1.3 | B187: =IF(INDEX(Overview!$C$8:$C$33,MATCH('OS&E_FF&E'!A187,Overview!$A$8:$A$33,0))=0,0,1) -> 0 | C187: Knife sharpener | D187: Kitchen equipment | E187: 1 | G187: 30.98 | H187: =E187*G187 -> 30.98 | L187: =INDEX(Overview!$B$8:$B$33,MATCH('OS&E_FF&E'!$A187,Overview!$A$8:$A$33,0)) -> F&B: Operating Equipment F&B
... A244: P1.3 | B244: =IF(INDEX(Overview!$C$8:$C$33,MATCH('OS&E_FF&E'!A244,Overview!$A$8:$A$33,0))=0,0,1) -> 0 | C244: Bag (400) | D244: Branded disposables | E244: 10 | G244: 32.5 | H244: =E244*G244 -> 325 | L244: =INDEX(Overview!$B$8:$B$33,MATCH('OS&E_FF&E'!$A244,Overview!$A$8:$A$33,0)) -> F&B: Operating Equipment F&B
A245: P10 | B245: =IF(INDEX(Overview!$C$8:$C$33,MATCH('OS&E_FF&E'!A245,Overview!$A$8:$A$33,0))=0,0,1) -> 0 | C245: Shelving | D245: Furniture | E245: 6 | F245: Juro | G245: 2000 | H245: =E245*G245 -> 12000 | L245: =INDEX(Overview!$B$8:$B$33,MATCH('OS&E_FF&E'!$A245,Overview!$A$8:$A$33,0)) -> Storeroom and pantry shelving
A246: P11 | B246: =IF(INDEX(Overview!$C$8:$C$33,MATCH('OS&E_FF&E'!A246,Overview!$A$8:$A$33,0))=0,0,1) -> 0 | C246: Armchair lounge | D246: Furniture | E246: 4 | F246: tableplacechairs.com | G246: 1500 | H246: =E246*G246 -> 6000 | I246: LF-014 | L246: =INDEX(Overview!$B$8:$B$33,MATCH('OS&E_FF&E'!$A246,Overview!$A$8:$A$33,0)) -> FF&E PA
A247: P11 | B247: =IF(INDEX(Overview!$C$8:$C$33,MATCH('OS&E_FF&E'!A247,Overview!$A$8:$A$33,0))=0,0,1) -> 0 | C247: Banquet chair | D247: Furniture | E247: 35 | F247: Gisela? | G247: 350 | H247: =E247*G247 -> 12250 | L247: =INDEX(Overview!$B$8:$B$33,MATCH('OS&E_FF&E'!$A247,Overview!$A$8:$A$33,0)) -> FF&E PA
A248: P11 | B248: =IF(INDEX(Overview!$C$8:$C$33,MATCH('OS&E_FF&E'!A248,Overview!$A$8:$A$33,0))=0,0,1) -> 0 | C248: Bar Stool FL001 | D248: Furniture | E248: 14 | F248: Fort M | G248: 487 | H248: =E248*G248 -> 6818 | L248: =INDEX(Overview!$B$8:$B$33,MATCH('OS&E_FF&E'!$A248,Overview!$A$8:$A$33,0)) -> FF&E PA
A249: P11 | B249: =IF(INDEX(Overview!$C$8:$C$33,MATCH('OS&E_FF&E'!A249,Overview!$A$8:$A$33,0))=0,0,1) -> 0 | C249: Carpets | D249: FF&E Public Area | E249: 3 | F249: Oertel | G249: 1000 | H249: =E249*G249 -> 3000 | L249: =INDEX(Overview!$B$8:$B$33,MATCH('OS&E_FF&E'!$A249,Overview!$A$8:$A$33,0)) -> FF&E PA
A250: P11 | B250: =IF(INDEX(Overview!$C$8:$C$33,MATCH('OS&E_FF&E'!A250,Overview!$A$8:$A$33,0))=0,0,1) -> 0 | C250: Chair dining table | D250: Furniture | E250: 36 | F250: Menu | G250: 245 | H250: =E250*G250 -> 8820 | L250: =INDEX(Overview!$B$8:$B$33,MATCH('OS&E_FF&E'!$A250,Overview!$A$8:$A$33,0)) -> FF&E PA
A251: P11 | B251: =IF(INDEX(Overview!$C$8:$C$33,MATCH('OS&E_FF&E'!A251,Overview!$A$8:$A$33,0))=0,0,1) -> 0 | C251: Chair wood | D251: Furniture | E251: 4 | F251: Hay | G251: 385 | H251: =E251*G251 -> 1540 | I251: LF-031 | L251: =INDEX(Overview!$B$8:$B$33,MATCH('OS&E_FF&E'!$A251,Overview!$A$8:$A$33,0)) -> FF&E PA
A252: P11 | B252: =IF(INDEX(Overview!$C$8:$C$33,MATCH('OS&E_FF&E'!A252,Overview!$A$8:$A$33,0))=0,0,1) -> 0 | C252: Chair/stool | D252: Furniture | E252: 2 | F252: Menu | G252: 245 | H252: =E252*G252 -> 490 | I252: LF-032 | L252: =INDEX(Overview!$B$8:$B$33,MATCH('OS&E_FF&E'!$A252,Overview!$A$8:$A$33,0)) -> FF&E PA
A253: P11 | B253: =IF(INDEX(Overview!$C$8:$C$33,MATCH('OS&E_FF&E'!A253,Overview!$A$8:$A$33,0))=0,0,1) -> 0 | C253: Coffe table concrete high | D253: Furniture | E253: 2 | F253: Pedrali | G253: 868 | H253: =E253*G253 -> 1736 | I253: LF-024 | L253: =INDEX(Overview!$B$8:$B$33,MATCH('OS&E_FF&E'!$A253,Overview!$A$8:$A$33,0)) -> FF&E PA
A254: P11 | B254: =IF(INDEX(Overview!$C$8:$C$33,MATCH('OS&E_FF&E'!A254,Overview!$A$8:$A$33,0))=0,0,1) -> 0 | C254: Coffe table concrete low | D254: Furniture | E254: 1 | F254: Pedrali | G254: 1104 | H254: =E254*G254 -> 1104 | I254: LF-023 | L254: =INDEX(Overview!$B$8:$B$33,MATCH('OS&E_FF&E'!$A254,Overview!$A$8:$A$33,0)) -> FF&E PA
A255: P11 | B255: =IF(INDEX(Overview!$C$8:$C$33,MATCH('OS&E_FF&E'!A255,Overview!$A$8:$A$33,0))=0,0,1) -> 0 | C255: Coffee table | D255: Furniture | E255: 2 | F255: TIPTOE | G255: 549 | H255: =E255*G255 -> 1098 | I255: LF-029 | L255: =INDEX(Overview!$B$8:$B$33,MATCH('OS&E_FF&E'!$A255,Overview!$A$8:$A$33,0)) -> FF&E PA
A256: P11 | B256: =IF(INDEX(Overview!$C$8:$C$33,MATCH('OS&E_FF&E'!A256,Overview!$A$8:$A$33,0))=0,0,1) -> 0 | C256: Cover arm chair FL038 | D256: Furniture | E256: 8 | F256: Muuto | G256: 499 | H256: =E256*G256 -> 3992 | I256: FL038 | L256: =INDEX(Overview!$B$8:$B$33,MATCH('OS&E_FF&E'!$A256,Overview!$A$8:$A$33,0)) -> FF&E PA
...

Sheet Blad1
A1: Item nr.
A2: F&B Wall / Grab & Go
A3: Kitchen equipment & appliances
A4: Bar equipment & appliances
A5: Stewarding equipment & appliances
A6: Storage (fridge, freezer & dry)
A7: Connection & placement fees
A8: Transportation costs
A9: Discount
A10: Back of House
A11: POS System
A12: Chinaware
... A46: Decoration

Sheet comments

Sheet Payment schedule
A1: Supplier | B1: Total | C1: payment terms | D1: Jan | E1: Feb | F1: Mrt | G1: Apr | H1: Mei | I1: Jun | J1: Jul | K1: Aug | L1: Sep | M1: Okt | N1: Nov | O1: Dec | P1: Comments:
A2: Crown International | B2: =SUMIF('OS&E_FF&E'!F:F,'Payment schedule'!A2,'OS&E_FF&E'!H:H) -> 0 | C2: 30% up front, 70% after delivery | H2: 8183.85 | M2: 19095.65
A3: Hilding Anders | B3: =SUMIF('OS&E_FF&E'!F:F,'Payment schedule'!A3,'OS&E_FF&E'!H:H) -> 0 | C3: 50% after order placement, 50% before delivery. | J3: 35636.73 | K3: 35636.72
A4: Essem Design | B4: =SUMIF('OS&E_FF&E'!F:F,'Payment schedule'!A4,'OS&E_FF&E'!H:H) -> 0
A5: Star Linen | B5: =SUMIF('OS&E_FF&E'!F:F,'Payment schedule'!A5,'OS&E_FF&E'!H:H) -> 0 | J5: 11033.38 | M5: 11033.38
A6: kingdom hotel supplies | B6: =SUMIF('OS&E_FF&E'!F:F,'Payment schedule'!A6,'OS&E_FF&E'!H:H) -> 653 | L6: 2357.5
A7: Stokke | B7: =SUMIF('OS&E_FF&E'!F:F,'Payment schedule'!A7,'OS&E_FF&E'!H:H) -> 320 | L7: 1074
A8: bol.com | B8: =SUMIF('OS&E_FF&E'!F:F,'Payment schedule'!A8,'OS&E_FF&E'!H:H) -> 0 | C8: 100% up front | K8: 951
A9: IME | B9: =SUMIF('OS&E_FF&E'!F:F,'Payment schedule'!A9,'OS&E_FF&E'!H:H) -> 9380 | C9: 50% after order placement, 30% before delivery, 20% 30 days after | J9: 9991.37 | L9: 5994.83 | M9: 3996.55
A10: Hobeka | B10: =SUMIF('OS&E_FF&E'!F:F,'Payment schedule'!A10,'OS&E_FF&E'!H:H) -> 0 | C10: 50% after order placement, 45% before delivery, 5% 30 days after. | J10: 5321.5 | K10: 4789.35 | L10: 532.15
A11: Manutan | B11: =SUMIF('OS&E_FF&E'!F:F,'Payment schedule'!A11,'OS&E_FF&E'!H:H) -> 5950 | C11: 100% after delivery | L11: 2720.1
A12: Bunzl | B12: =SUMIF('OS&E_FF&E'!F:F,'Payment schedule'!A12,'OS&E_FF&E'!H:H) -> 3817
A13: Nonius | B13: =SUMIF('OS&E_FF&E'!F:F,'Payment schedule'!A13,'OS&E_FF&E'!H:H) -> 0 | C13: 40% up front, 60% after delivery | H13: 5000 | L13: 7000
A14: Hydrozorg | B14: =Overview!C31 -> 15000
A15: doublestitch | B15: =Overview!C19 -> 5000
A16: deudekom | B16: =Overview!C30 -> 10645
H18: =SUM(H2:H17) -> 13183.85 | I18: =SUM(I2:I17) -> 0 | J18: =SUM(J2:J17) -> 61982.98 | K18: =SUM(K2:K17) -> 41377.07 | L18: =SUM(L2:L17) -> 19678.58 | M18: =SUM(M2:M17) -> 34125.58
